Workbook

Sheet Reporte
A1: REPORTE DIARIO | S1: 1670 | T1: 27641.37 | U1: 1 al 3 | X1: 5 al 9 | AH1: REPORTE DIARIO
A2: Fecha | B2: h | C2: MINERAL (TMS) | D2: TORTA (TMS) | E2: S | F2: RM 1/2/3 DTT-100 S | G2: RM 1/2/3 DTT-100 S/F | H2: RM 5/6/7/8/9 DTT-100 S | I2: RM 5/6/7/8/9 DTT-100 S/F | J2: ESP.Ant Fe | K2: ESP.N Fe Sol | L2: ESP.Ant FeO | M2: ESP.N FeO | N2: Promedio de Fe Sol | O2: Promedio de FeO | P2: H2O | Q2: %RECUP. PESO | R2: RATIO | S2: Eficiencia Alimentación | T2: Eficiencia Concentrado | U2: Mediana | V2: Mayor | W2: Menor | X2: Mediana | Y2: Mayor | Z2: Menor | AA2: KPI S | AB2: KPI Fe | AC2: KPI FeO | AI2: 13360 | AJ2: Turno A | AK2: Turno B | AL2: Turno C | AM2: Día
A3: =+'CONTROL PROD.TORTA'!A105 -> 46269 | B3: 0.375 | C3: =+'CONTROL PROD.TORTA'!B106 -> 1430 | D3: =+'CONTROL PROD.TORTA'!C106 -> 923 | E3: =+'CONTROL PROD.TORTA'!D106 -> 0.182 | F3: =+'CONTROL PROD.TORTA'!E106 -> 0.898 | G3: =+'CONTROL PROD.TORTA'!F106 -> 0.43 | H3: =+'CONTROL PROD.TORTA'!G106 -> 0.927 | I3: =+'CONTROL PROD.TORTA'!H106 -> 0.46 | J3: =+'CONTROL PROD.TORTA'!I106 -> 25 | ... R3: =+'CONTROL PROD.TORTA'!Q106 -> 1.5492958 | S3: =+C3/$S$1*100 -> 85.628743 | T3: =+D3/1151.7 -> 0.80142398 | U3: =MEDIAN(F3:F26) -> 0.232 | V3: =+U3+U3*0.075 -> 0.2494 | W3: =+U3-U3*0.075 -> 0.2146 | X3: =MEDIAN(H2:H26) -> 0.258 | Y3: =+X3+X3*0.075 -> 0.27735 | Z3: =+X3-X3*0.075 -> 0.23865 | AA3: 0.2 | AB3: 15 | AC3: 1.8 | AI3: Tratamiento (TMH) | AJ3: =SUM(C3:C10) -> 11253 | AK3: =SUM(C11:C18) -> 11492 | AL3: =SUM(C19:C26) -> 11560 | AM3: =SUM(AJ3:AL3) -> 34305
B4: 0.41666667 | C4: =+'CONTROL PROD.TORTA'!B107 -> 1406 | D4: =+'CONTROL PROD.TORTA'!C107 -> 573 | E4: =+'CONTROL PROD.TORTA'!D107 -> 0 | F4: =+'CONTROL PROD.TORTA'!E107 -> 0 | G4: =+'CONTROL PROD.TORTA'!F107 -> 0 | H4: =+'CONTROL PROD.TORTA'!G107 -> 0 | I4: =+'CONTROL PROD.TORTA'!H107 -> 0 | J4: =+'CONTROL PROD.TORTA'!I107 -> 0 | ... R4: =+'CONTROL PROD.TORTA'!Q107 -> 2.4537522 | S4: =+C4/$S$1*100 -> 84.191617 | T4: =+D4/1151.7 -> 0.4975254 | U4: =+U3 -> 0.232 | V4: =+U4+U4*0.075 -> 0.2494 | W4: =+U4-U4*0.075 -> 0.2146 | X4: =+X3 -> 0.258 | Y4: =+X4+X4*0.075 -> 0.27735 | Z4: =+X4-X4*0.075 -> 0.23865 | AA4: 0.2 | AB4: 15 | AC4: 1.8 | AI4: Concentrado (TMS) | AJ4: =SUM(D3:D10) -> 7279 | AK4: =SUM(D11:D18) -> 7742 | AL4: =SUM(D19:D26) -> 7443 | AM4: =SUM(AJ4:AL4) -> 22464
B5: 0.45833333 | C5: =+'CONTROL PROD.TORTA'!B108 -> 1411 | D5: =+'CONTROL PROD.TORTA'!C108 -> 1115 | E5: =+'CONTROL PROD.TORTA'!D108 -> 0.189 | F5: =+'CONTROL PROD.TORTA'!E108 -> 0.737 | G5: =+'CONTROL PROD.TORTA'!F108 -> 0.41 | H5: =+'CONTROL PROD.TORTA'!G108 -> 0.668 | I5: =+'CONTROL PROD.TORTA'!H108 -> 0.4 | J5: =+'CONTROL PROD.TORTA'!I108 -> 30.1 | ... R5: =+'CONTROL PROD.TORTA'!Q108 -> 1.2654709 | S5: =+C5/$S$1*100 -> 84.491018 | T5: =+D5/1151.7 -> 0.96813406 | U5: =+U4 -> 0.232 | V5: =+U5+U5*0.075 -> 0.2494 | W5: =+U5-U5*0.075 -> 0.2146 | X5: =+X4 -> 0.258 | Y5: =+X5+X5*0.075 -> 0.27735 | Z5: =+X5-X5*0.075 -> 0.23865 | AA5: 0.2 | AB5: 15 | AC5: 1.8 | AI5: Ratio | AJ5: =+AJ3/AJ4 -> 1.5459541 | AK5: =+AK3/AK4 -> 1.484371 | AL5: =+AL3/AL4 -> 1.5531372 | AM5: =+AM3/AM4 -> 1.52711
B6: 0.5 | C6: =+'CONTROL PROD.TORTA'!B109 -> 1419 | D6: =+'CONTROL PROD.TORTA'!C109 -> 1013 | E6: =+'CONTROL PROD.TORTA'!D109 -> 0 | F6: =+'CONTROL PROD.TORTA'!E109 -> 0 | G6: =+'CONTROL PROD.TORTA'!F109 -> 0 | H6: =+'CONTROL PROD.TORTA'!G109 -> 0 | I6: =+'CONTROL PROD.TORTA'!H109 -> 0 | J6: =+'CONTROL PROD.TORTA'!I109 -> 0 | ... R6: =+'CONTROL PROD.TORTA'!Q109 -> 1.4007897 | S6: =+C6/$S$1*100 -> 84.97006 | T6: =+D6/1151.7 -> 0.87956933 | U6: =+U5 -> 0.232 | V6: =+U6+U6*0.075 -> 0.2494 | W6: =+U6-U6*0.075 -> 0.2146 | X6: =+X5 -> 0.258 | Y6: =+X6+X6*0.075 -> 0.27735 | Z6: =+X6-X6*0.075 -> 0.23865 | AA6: 0.2 | AB6: 15 | AC6: 1.8 | AI6: Recuperación (%) | AJ6: =+AJ4/AJ3 -> 0.64684973 | AK6: =+AK4/AK3 -> 0.67368604 | AL6: =+AL4/AL3 -> 0.64385813 | AM6: =+AM4/AM3 -> 0.65483166
B7: 0.54166667 | C7: =+'CONTROL PROD.TORTA'!B110 -> 1404 | D7: =+'CONTROL PROD.TORTA'!C110 -> 1012 | E7: =+'CONTROL PROD.TORTA'!D110 -> 0.178 | F7: =+'CONTROL PROD.TORTA'!E110 -> 0.694 | G7: =+'CONTROL PROD.TORTA'!F110 -> 0.4 | H7: =+'CONTROL PROD.TORTA'!G110 -> 0.76 | I7: =+'CONTROL PROD.TORTA'!H110 -> 0.43 | J7: =+'CONTROL PROD.TORTA'!I110 -> 31.2 | ... R7: =+'CONTROL PROD.TORTA'!Q110 -> 1.3873518 | S7: =+C7/$S$1*100 -> 84.071856 | T7: =+D7/1151.7 -> 0.87870105 | U7: =+U6 -> 0.232 | V7: =+U7+U7*0.075 -> 0.2494 | W7: =+U7-U7*0.075 -> 0.2146 | X7: =+X6 -> 0.258 | Y7: =+X7+X7*0.075 -> 0.27735 | Z7: =+X7-X7*0.075 -> 0.23865 | AA7: 0.2 | AB7: 15 | AC7: 1.8 | AJ7: =+AJ3/$AI$2*100 -> 84.229042 | AK7: =+AK3/$AI$2*100 -> 86.017964 | AL7: =+AL3/$AI$2*100 -> 86.526946
B8: 0.58333333 | C8: =+'CONTROL PROD.TORTA'!B111 -> 1388 | D8: =+'CONTROL PROD.TORTA'!C111 -> 1036 | E8: =+'CONTROL PROD.TORTA'!D111 -> 0 | F8: =+'CONTROL PROD.TORTA'!E111 -> 0 | G8: =+'CONTROL PROD.TORTA'!F111 -> 0 | H8: =+'CONTROL PROD.TORTA'!G111 -> 0 | I8: =+'CONTROL PROD.TORTA'!H111 -> 0 | J8: =+'CONTROL PROD.TORTA'!I111 -> 0 | ... R8: =+'CONTROL PROD.TORTA'!Q111 -> 1.3397683 | S8: =+C8/$S$1*100 -> 83.113772 | T8: =+D8/1151.7 -> 0.89953981 | U8: =+U7 -> 0.232 | V8: =+U8+U8*0.075 -> 0.2494 | W8: =+U8-U8*0.075 -> 0.2146 | X8: =+X7 -> 0.258 | Y8: =+X8+X8*0.075 -> 0.27735 | Z8: =+X8-X8*0.075 -> 0.23865 | AA8: 0.2 | AB8: 15 | AC8: 1.8
B9: 0.625 | C9: =+'CONTROL PROD.TORTA'!B112 -> 1391 | D9: =+'CONTROL PROD.TORTA'!C112 -> 1004 | E9: =+'CONTROL PROD.TORTA'!D112 -> 0.148 | F9: =+'CONTROL PROD.TORTA'!E112 -> 0.629 | G9: =+'CONTROL PROD.TORTA'!F112 -> 0.38 | H9: =+'CONTROL PROD.TORTA'!G112 -> 0.797 | I9: =+'CONTROL PROD.TORTA'!H112 -> 0.44 | J9: =+'CONTROL PROD.TORTA'!I112 -> 27 | ... R9: =+'CONTROL PROD.TORTA'!Q112 -> 1.3854582 | S9: =+C9/$S$1*100 -> 83.293413 | T9: =+D9/1151.7 -> 0.8717548 | U9: =+U8 -> 0.232 | V9: =+U9+U9*0.075 -> 0.2494 | W9: =+U9-U9*0.075 -> 0.2146 | X9: =+X8 -> 0.258 | Y9: =+X9+X9*0.075 -> 0.27735 | Z9: =+X9-X9*0.075 -> 0.23865 | AA9: 0.2 | AB9: 15 | AC9: 1.8 | AI9: Datos metalúrgicos
B10: 0.66666667 | C10: =+'CONTROL PROD.TORTA'!B113 -> 1404 | D10: =+'CONTROL PROD.TORTA'!C113 -> 603 | E10: =+'CONTROL PROD.TORTA'!D113 -> 0 | F10: =+'CONTROL PROD.TORTA'!E113 -> 0 | G10: =+'CONTROL PROD.TORTA'!F113 -> 0 | H10: =+'CONTROL PROD.TORTA'!G113 -> 0 | I10: =+'CONTROL PROD.TORTA'!H113 -> 0 | J10: =+'CONTROL PROD.TORTA'!I113 -> 0 | ... R10: =+'CONTROL PROD.TORTA'!Q113 -> 2.3283582 | S10: =+C10/$S$1*100 -> 84.071856 | T10: =+D10/1151.7 -> 0.52357385 | U10: =+U9 -> 0.232 | V10: =+U10+U10*0.075 -> 0.2494 | W10: =+U10-U10*0.075 -> 0.2146 | X10: =+X9 -> 0.258 | Y10: =+X10+X10*0.075 -> 0.27735 | Z10: =+X10-X10*0.075 -> 0.23865 | AA10: 0.2 | AB10: 15 | AC10: 1.8 | AI10: S (%) | AM10: z
B11: 0.70833333 | C11: =+'CONTROL PROD.TORTA'!B114 -> 1420 | D11: =+'CONTROL PROD.TORTA'!C114 -> 1047 | E11: =+'CONTROL PROD.TORTA'!D114 -> 0.162 | F11: =+'CONTROL PROD.TORTA'!E114 -> 0.743 | G11: =+'CONTROL PROD.TORTA'!F114 -> 0.41 | H11: =+'CONTROL PROD.TORTA'!G114 -> 0.61 | I11: =+'CONTROL PROD.TORTA'!H114 -> 0.37 | J11: =+'CONTROL PROD.TORTA'!I114 -> 27.5 | ... R11: =+'CONTROL PROD.TORTA'!Q114 -> 1.356256 | S11: =+C11/$S$1*100 -> 85.02994 | T11: =+D11/1151.7 -> 0.90909091 | U11: =+U10 -> 0.232 | V11: =+U11+U11*0.075 -> 0.2494 | W11: =+U11-U11*0.075 -> 0.2146 | X11: =+X10 -> 0.258 | Y11: =+X11+X11*0.075 -> 0.27735 | Z11: =+X11-X11*0.075 -> 0.23865 | AA11: 0.2 | AB11: 15 | AC11: 1.8 | AI11: Malla 200 (%)
B12: 0.75 | C12: =+'CONTROL PROD.TORTA'!B115 -> 1418 | D12: =+'CONTROL PROD.TORTA'!C115 -> 1018 | E12: =+'CONTROL PROD.TORTA'!D115 -> 0 | F12: =+'CONTROL PROD.TORTA'!E115 -> 0 | G12: =+'CONTROL PROD.TORTA'!F115 -> 0 | H12: =+'CONTROL PROD.TORTA'!G115 -> 0 | I12: =+'CONTROL PROD.TORTA'!H115 -> 0 | J12: =+'CONTROL PROD.TORTA'!I115 -> 0 | ... R12: =+'CONTROL PROD.TORTA'!Q115 -> 1.3929273 | S12: =+C12/$S$1*100 -> 84.91018 | T12: =+D12/1151.7 -> 0.88391074 | U12: =+U11 -> 0.232 | V12: =+U12+U12*0.075 -> 0.2494 | W12: =+U12-U12*0.075 -> 0.2146 | X12: =+X11 -> 0.258 | Y12: =+X12+X12*0.075 -> 0.27735 | Z12: =+X12-X12*0.075 -> 0.23865 | AA12: 0.2 | AB12: 15 | AC12: 1.8 | AI12: Malla 325 (%)
B13: 0.79166667 | C13: =+'CONTROL PROD.TORTA'!B116 -> 1413 | D13: =+'CONTROL PROD.TORTA'!C116 -> 912 | E13: =+'CONTROL PROD.TORTA'!D116 -> 0.161 | F13: =+'CONTROL PROD.TORTA'!E116 -> 0.757 | G13: =+'CONTROL PROD.TORTA'!F116 -> 0.43 | H13: =+'CONTROL PROD.TORTA'!G116 -> 0.661 | I13: =+'CONTROL PROD.TORTA'!H116 -> 0.39 | J13: =+'CONTROL PROD.TORTA'!I116 -> 25.3 | ... R13: =+'CONTROL PROD.TORTA'!Q116 -> 1.5493421 | S13: =+C13/$S$1*100 -> 84.610778 | T13: =+D13/1151.7 -> 0.79187288 | U13: =+U12 -> 0.232 | V13: =+U13+U13*0.075 -> 0.2494 | W13: =+U13-U13*0.075 -> 0.2146 | X13: =+X12 -> 0.258 | Y13: =+X13+X13*0.075 -> 0.27735 | Z13: =+X13-X13*0.075 -> 0.23865 | AA13: 0.2 | AB13: 15 | AC13: 1.8
B14: 0.83333333 | C14: =+'CONTROL PROD.TORTA'!B117 -> 1436 | D14: =+'CONTROL PROD.TORTA'!C117 -> 1048 | E14: =+'CONTROL PROD.TORTA'!D117 -> 0 | F14: =+'CONTROL PROD.TORTA'!E117 -> 0 | G14: =+'CONTROL PROD.TORTA'!F117 -> 0 | H14: =+'CONTROL PROD.TORTA'!G117 -> 0 | I14: =+'CONTROL PROD.TORTA'!H117 -> 0 | J14: =+'CONTROL PROD.TORTA'!I117 -> 0 | ... R14: =+'CONTROL PROD.TORTA'!Q117 -> 1.370229 | S14: =+C14/$S$1*100 -> 85.988024 | T14: =+D14/1151.7 -> 0.90995919 | U14: =+U13 -> 0.232 | V14: =+U14+U14*0.075 -> 0.2494 | W14: =+U14-U14*0.075 -> 0.2146 | X14: =+X13 -> 0.258 | Y14: =+X14+X14*0.075 -> 0.27735 | Z14: =+X14-X14*0.075 -> 0.23865 | AA14: 0.2 | AB14: 15 | AC14: 1.8 | AI14: Embarque
B15: 0.875 | C15: =+'CONTROL PROD.TORTA'!B118 -> 1440 | D15: =+'CONTROL PROD.TORTA'!C118 -> 932 | E15: =+'CONTROL PROD.TORTA'!D118 -> 0.153 | F15: =+'CONTROL PROD.TORTA'!E118 -> 0.601 | G15: =+'CONTROL PROD.TORTA'!F118 -> 0.37 | H15: =+'CONTROL PROD.TORTA'!G118 -> 0.672 | I15: =+'CONTROL PROD.TORTA'!H118 -> 0.4 | J15: =+'CONTROL PROD.TORTA'!I118 -> 24.2 | ... R15: =+'CONTROL PROD.TORTA'!Q118 -> 1.5450644 | S15: =+C15/$S$1*100 -> 86.227545 | T15: =+D15/1151.7 -> 0.80923852 | U15: =+U14 -> 0.232 | V15: =+U15+U15*0.075 -> 0.2494 | W15: =+U15-U15*0.075 -> 0.2146 | X15: =+X14 -> 0.258 | Y15: =+X15+X15*0.075 -> 0.27735 | Z15: =+X15-X15*0.075 -> 0.23865 | AA15: 0.2 | AB15: 15 | AC15: 1.8 | AI15: Nave | AJ15: =+AP72 -> 0
B16: 0.91666667 | C16: =+'CONTROL PROD.TORTA'!B119 -> 1443 | D16: =+'CONTROL PROD.TORTA'!C119 -> 898 | E16: =+'CONTROL PROD.TORTA'!D119 -> 0 | F16: =+'CONTROL PROD.TORTA'!E119 -> 0 | G16: =+'CONTROL PROD.TORTA'!F119 -> 0 | H16: =+'CONTROL PROD.TORTA'!G119 -> 0 | I16: =+'CONTROL PROD.TORTA'!H119 -> 0 | J16: =+'CONTROL PROD.TORTA'!I119 -> 0 | ... R16: =+'CONTROL PROD.TORTA'!Q119 -> 1.6069042 | S16: =+C16/$S$1*100 -> 86.407186 | T16: =+D16/1151.7 -> 0.77971694 | U16: =+U15 -> 0.232 | V16: =+U16+U16*0.075 -> 0.2494 | W16: =+U16-U16*0.075 -> 0.2146 | X16: =+X15 -> 0.258 | Y16: =+X16+X16*0.075 -> 0.27735 | Z16: =+X16-X16*0.075 -> 0.23865 | AA16: 0.2 | AB16: 15 | AC16: 1.8 | AI16: Fecha de inicio | AJ16: =+AQ72 -> 0
B17: 0.95833333 | C17: =+'CONTROL PROD.TORTA'!B120 -> 1462 | D17: =+'CONTROL PROD.TORTA'!C120 -> 967 | E17: =+'CONTROL PROD.TORTA'!D120 -> 0.14 | F17: =+'CONTROL PROD.TORTA'!E120 -> 0.636 | G17: =+'CONTROL PROD.TORTA'!F120 -> 0.39 | H17: =+'CONTROL PROD.TORTA'!G120 -> 0.703 | I17: =+'CONTROL PROD.TORTA'!H120 -> 0.42 | J17: =+'CONTROL PROD.TORTA'!I120 -> 23.7 | ... R17: =+'CONTROL PROD.TORTA'!Q120 -> 1.5118925 | S17: =+C17/$S$1*100 -> 87.54491 | T17: =+D17/1151.7 -> 0.83962838 | U17: =+U16 -> 0.232 | V17: =+U17+U17*0.075 -> 0.2494 | W17: =+U17-U17*0.075 -> 0.2146 | X17: =+X16 -> 0.258 | Y17: =+X17+X17*0.075 -> 0.27735 | Z17: =+X17-X17*0.075 -> 0.23865 | AA17: 0.2 | AB17: 15 | AC17: 1.8 | AI17: Fecha de término
B18: 1 | C18: =+'CONTROL PROD.TORTA'!B121 -> 1460 | D18: =+'CONTROL PROD.TORTA'!C121 -> 920 | E18: =+'CONTROL PROD.TORTA'!D121 -> 0 | F18: =+'CONTROL PROD.TORTA'!E121 -> 0 | G18: =+'CONTROL PROD.TORTA'!F121 -> 0 | H18: =+'CONTROL PROD.TORTA'!G121 -> 0 | I18: =+'CONTROL PROD.TORTA'!H121 -> 0 | J18: =+'CONTROL PROD.TORTA'!I121 -> 0 | ... R18: =+'CONTROL PROD.TORTA'!Q121 -> 1.5869565 | S18: =+C18/$S$1*100 -> 87.42515 | T18: =+D18/1151.7 -> 0.79881914 | U18: =+U17 -> 0.232 | V18: =+U18+U18*0.075 -> 0.2494 | W18: =+U18-U18*0.075 -> 0.2146 | X18: =+X17 -> 0.258 | Y18: =+X18+X18*0.075 -> 0.27735 | Z18: =+X18-X18*0.075 -> 0.23865 | AA18: 0.2 | AB18: 15 | AC18: 1.8 | AI18: Embarcado (TMH) | AJ18: =+AS72 -> 0
B19: 1.0416667 | C19: =+'CONTROL PROD.TORTA'!B122 -> 1455 | D19: =+'CONTROL PROD.TORTA'!C122 -> 960 | E19: =+'CONTROL PROD.TORTA'!D122 -> 0.136 | F19: =+'CONTROL PROD.TORTA'!E122 -> 0.464 | G19: =+'CONTROL PROD.TORTA'!F122 -> 0.25 | H19: =+'CONTROL PROD.TORTA'!G122 -> 0.527 | I19: =+'CONTROL PROD.TORTA'!H122 -> 0.28 | J19: =+'CONTROL PROD.TORTA'!I122 -> 28.2 | ... R19: =+'CONTROL PROD.TORTA'!Q122 -> 1.515625 | S19: =+C19/$S$1*100 -> 87.125749 | T19: =+D19/1151.7 -> 0.8335504 | U19: =+U18 -> 0.232 | V19: =+U19+U19*0.075 -> 0.2494 | W19: =+U19-U19*0.075 -> 0.2146 | X19: =+X18 -> 0.258 | Y19: =+X19+X19*0.075 -> 0.27735 | Z19: =+X19-X19*0.075 -> 0.23865 | AA19: 0.2 | AB19: 15 | AC19: 1.8
B20: 1.0833333 | C20: =+'CONTROL PROD.TORTA'!B123 -> 1438 | D20: =+'CONTROL PROD.TORTA'!C123 -> 902 | E20: =+'CONTROL PROD.TORTA'!D123 -> 0 | F20: =+'CONTROL PROD.TORTA'!E123 -> 0 | G20: =+'CONTROL PROD.TORTA'!F123 -> 0 | H20: =+'CONTROL PROD.TORTA'!G123 -> 0 | I20: =+'CONTROL PROD.TORTA'!H123 -> 0 | J20: =+'CONTROL PROD.TORTA'!I123 -> 0 | ... R20: =+'CONTROL PROD.TORTA'!Q123 -> 1.594235 | S20: =+C20/$S$1*100 -> 86.107784 | T20: =+D20/1151.7 -> 0.78319007 | U20: =+U19 -> 0.232 | V20: =+U20+U20*0.075 -> 0.2494 | W20: =+U20-U20*0.075 -> 0.2146 | X20: =+X19 -> 0.258 | Y20: =+X20+X20*0.075 -> 0.27735 | Z20: =+X20-X20*0.075 -> 0.23865 | AA20: 0.2 | AB20: 15 | AC20: 1.8 | AI20: Concentrado
B21: 1.125 | C21: =+'CONTROL PROD.TORTA'!B124 -> 1447 | D21: =+'CONTROL PROD.TORTA'!C124 -> 1000 | E21: =+'CONTROL PROD.TORTA'!D124 -> 0.132 | F21: =+'CONTROL PROD.TORTA'!E124 -> 0.474 | G21: =+'CONTROL PROD.TORTA'!F124 -> 0.3 | H21: =+'CONTROL PROD.TORTA'!G124 -> 0.516 | I21: =+'CONTROL PROD.TORTA'!H124 -> 0.25 | J21: =+'CONTROL PROD.TORTA'!I124 -> 25.1 | ... R21: =+'CONTROL PROD.TORTA'!Q124 -> 1.447 | S21: =+C21/$S$1*100 -> 86.646707 | T21: =+D21/1151.7 -> 0.86828167 | U21: =+U20 -> 0.232 | V21: =+U21+U21*0.075 -> 0.2494 | W21: =+U21-U21*0.075 -> 0.2146 | X21: =+X20 -> 0.258 | Y21: =+X21+X21*0.075 -> 0.27735 | Z21: =+X21-X21*0.075 -> 0.23865 | AA21: 0.2 | AB21: 15 | AC21: 1.8 | AJ21: Diario | AK21: Semana | AL21: Agosto | AM21: Anual
B22: 1.1666667 | C22: =+'CONTROL PROD.TORTA'!B125 -> 1418 | D22: =+'CONTROL PROD.TORTA'!C125 -> 824 | E22: =+'CONTROL PROD.TORTA'!D125 -> 0 | F22: =+'CONTROL PROD.TORTA'!E125 -> 0 | G22: =+'CONTROL PROD.TORTA'!F125 -> 0 | H22: =+'CONTROL PROD.TORTA'!G125 -> 0 | I22: =+'CONTROL PROD.TORTA'!H125 -> 0 | J22: =+'CONTROL PROD.TORTA'!I125 -> 0 | ... R22: =+'CONTROL PROD.TORTA'!Q125 -> 1.7208738 | S22: =+C22/$S$1*100 -> 84.91018 | T22: =+D22/1151.7 -> 0.7154641 | U22: =+U21 -> 0.232 | V22: =+U22+U22*0.075 -> 0.2494 | W22: =+U22-U22*0.075 -> 0.2146 | X22: =+X21 -> 0.258 | Y22: =+X22+X22*0.075 -> 0.27735 | Z22: =+X22-X22*0.075 -> 0.23865 | AA22: 0.2 | AB22: 15 | AC22: 1.8 | AI22: Acumulado (TMS) | AJ22: =+AJ89 -> 18772 | AK22: =+AL89 -> 141713 | AL22: =+AJ95 -> 542272 | AM22: =+AK113 -> 5669033 | AN22: =+AL113 -> -252669.12
B23: 1.2083333 | C23: =+'CONTROL PROD.TORTA'!B126 -> 1454 | D23: =+'CONTROL PROD.TORTA'!C126 -> 812 | E23: =+'CONTROL PROD.TORTA'!D126 -> 0.155 | F23: =+'CONTROL PROD.TORTA'!E126 -> 0.528 | G23: =+'CONTROL PROD.TORTA'!F126 -> 0.32 | H23: =+'CONTROL PROD.TORTA'!G126 -> 0.57 | I23: =+'CONTROL PROD.TORTA'!H126 -> 0.36 | J23: =+'CONTROL PROD.TORTA'!I126 -> 30 | ... R23: =+'CONTROL PROD.TORTA'!Q126 -> 1.7906404 | S23: =+C23/$S$1*100 -> 87.065868 | T23: =+D23/1151.7 -> 0.70504472 | U23: =+U22 -> 0.232 | V23: =+U23+U23*0.075 -> 0.2494 | W23: =+U23-U23*0.075 -> 0.2146 | X23: =+X22 -> 0.258 | Y23: =+X23+X23*0.075 -> 0.27735 | Z23: =+X23-X23*0.075 -> 0.23865 | AA23: 0.2 | AB23: 15 | AC23: 1.8 | AI23: Ppto 2026 (TMS) | AJ23: =+AL63 -> 23201.567 | AK23: 162410 | AL23: =+AJ106 -> 660185 | AM23: 8000015
B24: 1.25 | C24: =+'CONTROL PROD.TORTA'!B127 -> 1445 | D24: =+'CONTROL PROD.TORTA'!C127 -> 1046 | E24: =+'CONTROL PROD.TORTA'!D127 -> 0 | F24: =+'CONTROL PROD.TORTA'!E127 -> 0 | G24: =+'CONTROL PROD.TORTA'!F127 -> 0 | H24: =+'CONTROL PROD.TORTA'!G127 -> 0 | I24: =+'CONTROL PROD.TORTA'!H127 -> 0 | J24: =+'CONTROL PROD.TORTA'!I127 -> 0 | ... R24: =+'CONTROL PROD.TORTA'!Q127 -> 1.3814532 | S24: =+C24/$S$1*100 -> 86.526946 | T24: =+D24/1151.7 -> 0.90822263 | U24: =+U23 -> 0.232 | V24: =+U24+U24*0.075 -> 0.2494 | W24: =+U24-U24*0.075 -> 0.2146 | X24: =+X23 -> 0.258 | Y24: =+X24+X24*0.075 -> 0.27735 | Z24: =+X24-X24*0.075 -> 0.23865 | AA24: 0.2 | AB24: 15 | AC24: 1.8 | AI24: % cumplimiento | AJ24: =+AJ22/AJ23 -> 0.80908329 | AK24: =+AK22/AK23 -> 0.87256327 | AL24: =+AL22/AL23 -> 0.821394 | AM24: =+AM22/AM23 -> 0.7086278
B25: 1.2916667 | C25: =+'CONTROL PROD.TORTA'!B128 -> 1457 | D25: =+'CONTROL PROD.TORTA'!C128 -> 1066 | E25: =+'CONTROL PROD.TORTA'!D128 -> 0.162 | F25: =+'CONTROL PROD.TORTA'!E128 -> 0.49 | G25: =+'CONTROL PROD.TORTA'!F128 -> 0.31 | H25: =+'CONTROL PROD.TORTA'!G128 -> 0.527 | I25: =+'CONTROL PROD.TORTA'!H128 -> 0.34 | J25: =+'CONTROL PROD.TORTA'!I128 -> 25.4 | ... R25: =+'CONTROL PROD.TORTA'!Q128 -> 1.3667917 | S25: =+C25/$S$1*100 -> 87.245509 | T25: =+D25/1151.7 -> 0.92558826 | U25: =+U24 -> 0.232 | V25: =+U25+U25*0.075 -> 0.2494 | W25: =+U25-U25*0.075 -> 0.2146 | X25: =+X24 -> 0.258 | Y25: =+X25+X25*0.075 -> 0.27735 | Z25: =+X25-X25*0.075 -> 0.23865 | AA25: 0.2 | AB25: 15 | AC25: 1.8
B26: 1.3333333 | C26: =+'CONTROL PROD.TORTA'!B129 -> 1446 | D26: =+'CONTROL PROD.TORTA'!C129 -> 833 | E26: =+'CONTROL PROD.TORTA'!D129 -> 0 | F26: =+'CONTROL PROD.TORTA'!E129 -> 0 | G26: =+'CONTROL PROD.TORTA'!F129 -> 0 | H26: =+'CONTROL PROD.TORTA'!G129 -> 0 | I26: =+'CONTROL PROD.TORTA'!H129 -> 0 | J26: =+'CONTROL PROD.TORTA'!I129 -> 0 | ... R26: =+'CONTROL PROD.TORTA'!Q129 -> 1.7358944 | S26: =+C26/$S$1*100 -> 86.586826 | T26: =+D26/1151.7 -> 0.72327863 | U26: =+U25 -> 0.232 | V26: =+U26+U26*0.075 -> 0.2494 | W26: =+U26-U26*0.075 -> 0.2146 | X26: =+X25 -> 0.258 | Y26: =+X26+X26*0.075 -> 0.27735 | Z26: =+X26-X26*0.075 -> 0.23865 | AA26: 0.2 | AB26: 15 | AC26: 1.8 | AI26: Sinter Calibrado
A27: Total | C27: =+'CONTROL PROD.TORTA'!B130 -> 34305 | D27: =+'CONTROL PROD.TORTA'!C130 -> 22464 | E27: =+'CONTROL PROD.TORTA'!D130 -> 0.15816667 | F27: =+'CONTROL PROD.TORTA'!E130 -> 0.63758333 | G27: =+'CONTROL PROD.TORTA'!F130 -> 0.36666667 | H27: =+'CONTROL PROD.TORTA'!G130 -> 0.6615 | I27: =+'CONTROL PROD.TORTA'!H130 -> 0.37833333 | J27: =+'CONTROL PROD.TORTA'!I130 -> 26.891667 | ... R27: =+'CONTROL PROD.TORTA'!Q130 -> 1.52711 | S27: =AVERAGE(S3:S26) -> 85.591317 | T27: =+D27/T1 -> 0.81269488 | U27: =+C27/S27*100 -> 40080 | AJ27: Diario | AK27: Semana | AL27: Agosto | AM27: Anual
AI28: Acumulado (TMS) | AJ28: =+AK89 -> 3994 | AK28: =+AM89 -> 21323 | AL28: =+AK95 -> 93041 | AM28: =+AN113 -> 1099219 | AN28: =+AO113 -> 215778.14
T29: =+C27/U27 -> 0.85591317 | AI29: Ppto 2026 (TMS) | AJ29: =+AM63 -> 3333.3333 | AK29: 23333 | AL29: 100000 | AM29: 1200000
AI30: % cumplimiento | AJ30: =+AJ28/AJ29 -> 1.1982 | AK30: =+AK28/AK29 -> 0.91385591 | AL30: =+AL28/AL29 -> 0.93041 | AM30: =+AM28/AM29 -> 0.91601583
AL55: 22218 | AM55: =+AL55*5 -> 111090
AL56: 18889.52 | AM56: =+AL56*2 -> 37779.04
AM57: =SUM(AM55:AM56) -> 148869.04
AJ61: 45361 | AK61: 6693
AI62: SETIEMBRE | AP62: SETIEMBRE
AI63: Día | AJ63: Concentrado | AK63: Sinter Calibrado | AL63: 23201.567 | AM63: 3333.3333 | AN63: 26 | AP63: Embarque
AI64: 1 | AJ64: 23744 | AK64: 3144 | AO64: Nro | AP64: Setiembre | AQ64: Inicio | AR64: Fin | AS64: Total (TM) | AT64: oxidado | AU64: sinter
AI65: 2 | AJ65: 24312 | AK65: 3286 | AO65: 1 | AP65: M/V “EPIC UNION ” | AQ65: 26/08/2026 12:15hrs | AR65: 01/09/2026 11:55 hrs | AS65: 168408
AI66: 3 | AJ66: 21281 | AK66: 3318 | AO66: 2 | AP66: M/V “ASL LOONG” | AQ66: 01/09/2026 14:15hrs | AR66: 03/09/2026 🕐 20:13 hrs | AS66: 163104.86
AI67: 4 | AJ67: 21231 | AK67: 4243 | AO67: 3 | AP67: M/V "SHANDOND HUA ZHANG” | AQ67: 04/09/2026 🕐 00:00 hrs
AI68: 5 | AJ68: 21964 | AK68: 2510 | AL68: =+SUM(AJ61,AJ64:AJ68) -> 157893 | AM68: =+SUM(AK61,AK64:AK68) -> 23194 | AO68: 4
AI69: 6 | AJ69: 21113 | AK69: 4183 | AO69: 5
AI70: 7 | AJ70: 20225 | AK70: 3814 | AO70: 6
AI71: 8 | AJ71: 23222 | AK71: 3401 | AO71: 7
AI72: 9 | AJ72: 24549 | AK72: 3119 | AO72: 8
AI73: 10 | AJ73: 22889 | AK73: 3381 | AO73: 9
AI74: 11 | AJ74: 24603 | AK74: 2499 | AO74: 10 | AV74: 128010 TM
AI75: 12 | AJ75: 10197 | AK75: 820 | AL75: =+SUM(AJ69:AJ75) -> 146798 | AM75: =+SUM(AK69:AK75) -> 21217 | AO75: 11
AI76: 13 | AJ76: 23245 | AK76: 5450 | AO76: 12
AI77: 14 | AJ77: 22572 | AK77: 4888 | AO77: 13
AI78: 15 | AJ78: 18958 | AK78: 5804 | AR78: Total | AS78: =SUM(AS65:AS77) -> 331512.86
AI79: 16 | AJ79: 20090 | AK79: 4381 | AO79: 10
AI80: 17 | AJ80: 18072 | AK80: 4128
AI81: 18 | AJ81: 18854 | AK81: 5191
AI82: 19 | AJ82: 19438 | AK82: 4158 | AL82: =+SUM(AJ76:AJ82) -> 141229 | AM82: =+SUM(AK76:AK82) -> 34000
AI83: 20 | AJ83: 19413 | AK83: 4126
AI84: 21 | AJ84: 17987 | AK84: 3588
AI85: 22 | AJ85: 20607 | AK85: 0
AI86: 23 | AJ86: 21802 | AK86: 3355
AG87: 7{} | AI87: 24 | AJ87: 21632 | AK87: 2694
AI88: 25 | AJ88: 21500 | AK88: 3566
AI89: 26 | AJ89: 18772 | AK89: 3994 | AL89: =+SUM(AJ83:AJ89) -> 141713 | AM89: =+SUM(AK83:AK89) -> 21323
AI90: 27
AI91: 28
AI92: 29
AI93: 30
AI94: 31 | AL94: =+SUM(AJ90:AJ94) -> 0 | AM94: =+SUM(AK90:AK94) -> 0
AI95: Total | AJ95: =SUM(AJ64:AJ94) -> 542272 | AK95: =SUM(AK64:AK94) -> 93041
AJ96: =+AK113 -> 5669033 | AK96: =+AN113 -> 1099219
AI98: Anual
AJ99: Concentrado | AM99: Sinter Calibrado
AI100: Mes | AJ100: Budget | AK100: Real | AL100: Diferencia | AM100: Budget | AN100: Real | AO100: Diferencia
AI101: Enero | AJ101: 688440 | AK101: 670354 | AL101: =+AK101-AJ101 -> -18086 | AM101: 100000 | AN101: 108808 | AO101: =+AN101-AM101 -> 8808
AI102: Febrero | AJ102: 594128 | AK102: 578899 | AL102: =+AK102-AJ102 -> -15229 | AM102: 100000 | AN102: 163710 | AO102: =+AN102-AM102 -> 63710
AI103: Marzo | AJ103: 698462 | AK103: 634696 | AL103: =+AK103-AJ103 -> -63766 | AM103: 100000 | AN103: 104094 | AO103: =+AN103-AM103 -> 4094
AI104: Abril | AJ104: 666558 | AK104: 660962 | AL104: =+AK104-AJ104 -> -5596 | AM104: 100000 | AN104: 108628 | AO104: =+AN104-AM104 -> 8628
AI105: Mayo | AJ105: 585575 | AK105: 671051 | AL105: =+AK105-AJ105 -> 85476 | AM105: 100000 | AN105: 143683 | AO105: =+AN105-AM105 -> 43683
AI106: Junio | AJ106: 660185 | AK106: 605790 | AL106: -90468.387 | AM106: 100000 | AN106: 141197 | AO106: 44422.806
AI107: Julio | AJ107: 719467 | AK107: 656288 | AL107: -63179 | AM107: 100000 | AN107: 115970 | AO107: 15970
AI108: Agosto | AJ108: 669573 | AK108: 648721 | AL108: -20852 | AM108: 100000 | AN108: 120088 | AO108: 20088
AI109: Setiembre | AJ109: 696047 | AK109: =+AJ95 -> 542272 | AL109: =+AK109-(AL63*AN63) -> -60968.733 | AM109: 100000 | AN109: =+AK95 -> 93041 | AO109: =+AN109-(AM63*AN63) -> 6374.3333 | AP109: =+AJ109/30 -> 23201.567
AI110: Octubre | AJ110: 715388 | AM110: 100000 | AP110: =+AP109*7 -> 162410.97
AI111: Noviembre | AJ111: 601289 | AM111: 100000
AI112: Diciembre | AJ112: 704902 | AM112: 100000
AI113: Total | AJ113: =SUM(AJ101:AJ112) -> 8000014 | AK113: =SUM(AK101:AK112) -> 5669033 | AL113: =SUM(AL101:AL112) -> -252669.12 | AM113: =SUM(AM101:AM112) -> 1200000 | AN113: =SUM(AN101:AN112) -> 1099219 | AO113: =SUM(AO101:AO112) -> 215778.14
AK114: =+AK113/AJ113 -> 0.70862788 | AL114: =+AL113/AK113 -> -0.044570056

Sheet CONTROL PROD.TORTA
A3: CONTROL DIARIO DE PRODUCCION DE TORTA - ZONA ANTIGUA
A5: DIA | B5: MINERAL (TMS) | C5: TORTA (TMS) | D5: S | E5: RM 1/2/3 DTT-100 S | F5: RM 1/2/3 DTT-100 S/F | G5: RM 5/6/7/8/9 DTT-100 S | H5: RM 5/6/7/8/9 DTT-100 S/F | I5: ESP.Ant Fe | J5: ESP.N Fe Sol | K5: ESP.Ant FeO | L5: ESP.N FeO | M5: Promedio de Fe Sol | N5: Promedio de FeO | O5: H2O | P5: %RECUP. | Q5: RATIO | R5: OBS. MAGNETICA | S5: OBS. FILTROS
A6: 0.375 | B6: 1565 | C6: 1029 | D6: 0.177 | E6: 0.736 | F6: 0.44 | G6: 0.877 | H6: 0.49 | I6: 25.4 | J6: 12.3 | K6: 2 | L6: 1.6 | M6: =I6*0.4+J6*0.6 -> 17.54 | N6: =+(K6*0.4+L6*0.6) -> 1.76 | O6: 8.2 | P6: =+IFERROR(C6/B6,"") -> 0.65750799 | Q6: =IFERROR(1/P6,0) -> 1.5208941
A7: 0.41666667 | B7: 1586 | C7: 1072 | P7: =+IFERROR(C7/B7,"") -> 0.67591425 | Q7: =IFERROR(1/P7,0) -> 1.4794776
A8: 0.45833333 | B8: 1562 | C8: 938 | D8: 0.172 | E8: 0.778 | F8: 0.45 | G8: 0.871 | H8: 0.49 | I8: 25.5 | J8: 14 | K8: 2.5 | L8: 2.2 | M8: =+(I8*0.4+J8*0.6) -> 18.6 | N8: =+(K8*0.4+L8*0.6) -> 2.32 | O8: 8.6 | P8: =+IFERROR(C8/B8,"") -> 0.60051216 | Q8: =IFERROR(1/P8,0) -> 1.6652452
A9: 0.5 | B9: 1559 | C9: 1015 | P9: =+IFERROR(C9/B9,"") -> 0.65105837 | Q9: =IFERROR(1/P9,0) -> 1.5359606
A10: 0.54166667 | B10: 1570 | C10: 1003 | D10: 0.194 | E10: 0.766 | F10: 0.44 | G10: 0.738 | H10: 0.42 | I10: 29.4 | J10: 14.5 | K10: 3.2 | L10: 2.4 | M10: =+(I10*0.4+J10*0.6) -> 20.46 | N10: =+(K10*0.4+L10*0.6) -> 2.72 | O10: 8.3 | P10: =+IFERROR(C10/B10,"") -> 0.6388535 | Q10: =IFERROR(1/P10,0) -> 1.5653041
A11: 0.58333333 | B11: 1583 | C11: 1033 | P11: =+IFERROR(C11/B11,"") -> 0.65255843 | Q11: =IFERROR(1/P11,0) -> 1.5324298
A12: 0.625 | B12: 1594 | C12: 1004 | D12: 0.17 | E12: 0.703 | F12: 0.4 | G12: 0.93 | H12: 0.5 | I12: 24.2 | J12: 13.2 | K12: 1.6 | L12: 2.1 | M12: =+(I12*0.4+J12*0.6) -> 17.6 | N12: =+(K12*0.4+L12*0.6) -> 1.9 | O12: 8.4 | P12: =+IFERROR(C12/B12,"") -> 0.62986198 | Q12: =IFERROR(1/P12,0) -> 1.5876494
A13: 0.66666667 | B13: 1558 | C13: 991 | P13: =+IFERROR(C13/B13,"") -> 0.63607189 | Q13: =IFERROR(1/P13,0) -> 1.5721493
A14: 0.70833333 | B14: 1575 | C14: 1071 | D14: 0.166 | E14: 0.829 | F14: 0.46 | G14: 0.813 | H14: 0.47 | I14: 24.9 | J14: 15.1 | K14: 1.9 | L14: 2.3 | M14: =+(I14*0.4+J14*0.6) -> 19.02 | N14: =+(K14*0.4+L14*0.6) -> 2.14 | O14: 8.3 | P14: =+IFERROR(C14/B14,"") -> 0.68 | Q14: =IFERROR(1/P14,0) -> 1.4705882
A15: 0.75 | B15: 1653 | C15: 1143 | P15: =+IFERROR(C15/B15,"") -> 0.69147005 | Q15: =IFERROR(1/P15,0) -> 1.4461942
A16: 0.79166667 | B16: 1583 | C16: 903 | D16: 0.161 | E16: 0.827 | F16: 0.45 | G16: 0.865 | H16: 0.47 | I16: 31.8 | J16: 15.8 | K16: 2.4 | L16: 2.4 | M16: =+(I16*0.4+J16*0.6) -> 22.2 | N16: =+(K16*0.4+L16*0.6) -> 2.4 | O16: 8.2 | P16: =+IFERROR(C16/B16,"") -> 0.57043588 | Q16: =IFERROR(1/P16,0) -> 1.7530454
A17: 0.83333333 | B17: 1581 | C17: 1076 | P17: =+IFERROR(C17/B17,"") -> 0.68058191 | Q17: =IFERROR(1/P17,0) -> 1.4693309 | R17: Bancos KYF10 trabajando en manual
A18: 0.875 | B18: 1588 | C18: 1183 | D18: 0.179 | E18: 0.72 | F18: 0.44 | G18: 0.531 | H18: 0.36 | I18: 22.2 | J18: 15.9 | K18: 2.1 | L18: 2 | M18: =+(I18*0.4+J18*0.6) -> 18.42 | N18: =+(K18*0.4+L18*0.6) -> 2.04 | O18: 8.4 | P18: =+IFERROR(C18/B18,"") -> 0.74496222 | Q18: =IFERROR(1/P18,0) -> 1.34235 | R18: Rm01 reponen guardas del motor.. /// Se reduce dosificación de acido oxalico | S18: 21:00 a 21:20 hrs paró espesador 053-003 por alto torque, se observa lubricación deficiente en cajas de transmision, se agrega aceite operando con parametros normales
A19: 0.91666667 | B19: 1460 | C19: 1101 | P19: =+IFERROR(C19/B19,"") -> 0.75410959 | Q19: =IFERROR(1/P19,0) -> 1.3260672 | R19: Se realizó agregado de barras molinos 032-082/083/084/085
A20: 0.95833333 | B20: 1320 | C20: 1146 | D20: 0.168 | E20: 0.823 | F20: 0.46 | G20: 0.605 | H20: 0.37 | I20: 24.2 | J20: 15.6 | K20: 2.2 | L20: 2.6 | M20: =+(I20*0.4+J20*0.6) -> 19.04 | N20: =+(K20*0.4+L20*0.6) -> 2.44 | O20: 8.4 | P20: =+IFERROR(C20/B20,"") -> 0.86818182 | Q20: =IFERROR(1/P20,0) -> 1.1518325 | R20: 22:49 hrs arrancó barras 1 en reemplazo del Rm02 | S20: Personal mecánico culmina lubricación de cajas de transmisión lado norte y sur del espesador 053-003
A21: 0 | B21: 1492 | C21: 1007 | P21: =+IFERROR(C21/B21,"") -> 0.67493298 | Q21: =IFERROR(1/P21,0) -> 1.4816286 | R21: Se reduce dosificación de acido oxalico
A22: 0.041666667 | B22: 1585 | C22: 1079 | D22: 0.187 | E22: 0.963 | F22: 0.56 | G22: 0.782 | H22: 0.47 | I22: 34.3 | J22: 15.2 | K22: 3.4 | L22: 2.4 | M22: =+(I22*0.4+J22*0.6) -> 22.84 | N22: =+(K22*0.4+L22*0.6) -> 2.8 | O22: 8.1 | P22: =+IFERROR(C22/B22,"") -> 0.6807571 | Q22: =IFERROR(1/P22,0) -> 1.4689527 | R22: Se inicia agregado de conos
A23: 0.083333333 | B23: 1578 | C23: 874 | P23: =+IFERROR(C23/B23,"") -> 0.55386565 | Q23: =IFERROR(1/P23,0) -> 1.805492 | R23: 210-295A/B.- Limpieza cajón de concentrado PURGA
A24: 0.125 | B24: 1555 | C24: 811 | D24: 0.203 | E24: 0.787 | F24: 0.46 | G24: 0.705 | H24: 0.43 | I24: 32.2 | J24: 20.1 | K24: 4.4 | L24: 4.5 | M24: =+(I24*0.4+J24*0.6) -> 24.94 | N24: =+(K24*0.4+L24*0.6) -> 4.46 | O24: 8.1 | P24: =+IFERROR(C24/B24,"") -> 0.52154341 | Q24: =IFERROR(1/P24,0) -> 1.9173859 | R24: 210-296A/B.- Limpieza cajón de concentrado PURGA. // Se incrementa dosificación de xantato, se reduce colchones celdas grandes
A25: 0.16666667 | B25: 1390 | C25: 794 | P25: =+IFERROR(C25/B25,"") -> 0.57122302 | Q25: =IFERROR(1/P25,0) -> 1.7506297 | R25: Agregado de barras molinos 032-086/088/089
A26: 0.20833333 | B26: 1525 | C26: 1045 | D26: 0.2 | E26: 0.841 | F26: 0.47 | G26: 0.915 | H26: 0.52 | I26: 29.3 | J26: 19.2 | K26: 2.9 | L26: 3.5 | M26: =+(I26*0.4+J26*0.6) -> 23.24 | N26: =+(K26*0.4+L26*0.6) -> 3.26 | O26: 8 | P26: =+IFERROR(C26/B26,"") -> 0.6852459 | Q26: =IFERROR(1/P26,0) -> 1.4593301
A27: 0.25 | B27: 1548 | C27: 994 | P27: =+IFERROR(C27/B27,"") -> 0.64211886 | Q27: =IFERROR(1/P27,0) -> 1.5573441 | R27: Se continua agregado de conos
A28: 0.29166667 | B28: 1551 | C28: 936 | D28: 0.203 | E28: 0.781 | F28: 0.44 | G28: 0.846 | H28: 0.47 | I28: 26.5 | J28: 18.2 | K28: 2.6 | L28: 2.8 | M28: =+(I28*0.4+J28*0.6) -> 21.52 | N28: =+(K28*0.4+L28*0.6) -> 2.72 | O28: 8.4 | P28: =+IFERROR(C28/B28,"") -> 0.60348162 | Q28: =IFERROR(1/P28,0) -> 1.6570513
A29: 0.33333333 | B29: 1588 | C29: 996 | P29: =+IFERROR(C29/B29,"") -> 0.62720403 | Q29: =IFERROR(1/P29,0) -> 1.5943775
A30: 46266 | B30: =+IF(SUM(B6:B29)=0, "", SUM(B6:B29)) -> 37149 | C30: =+IF(SUM(C6:C29)=0, "", SUM(C6:C29)) -> 24244 | D30: =+IFERROR((AVERAGE(D6:D29)),0) -> 0.18166667 | E30: =+IFERROR((AVERAGE(E6:E29)),0) -> 0.79616667 | F30: =+IFERROR((AVERAGE(F6:F29)),0) -> 0.45583333 | G30: =+IFERROR((AVERAGE(G6:G29)),0) -> 0.78983333 | H30: =+IFERROR((AVERAGE(H6:H29)),0) -> 0.455 | I30: =+IFERROR((AVERAGE(I6:I29)),"") -> 27.491667 | J30: =+IFERROR((AVERAGE(J6:J29)),"") -> 15.758333 | K30: =+IFERROR((AVERAGE(K6:K29)),"") -> 2.6 | L30: =+IFERROR((AVERAGE(L6:L29)),"") -> 2.5666667 | M30: =+IFERROR((AVERAGE(M6:M29)),0) -> 20.451667 | N30: =+IFERROR((AVERAGE(N6:N29)),0) -> 2.58 | O30: =+IFERROR((AVERAGE(O6:O29)),0) -> 8.2833333 | P30: =+IFERROR(C30/B30,"") -> 0.65261514 | Q30: =IFERROR(1/P30,0) -> 1.5322967
A31: 0.375 | B31: 1631 | C31: 1143 | D31: 0.199 | E31: 0.991 | F31: 0.53 | G31: 0.818 | H31: 0.46 | I31: 29.6 | J31: 13.4 | K31: 2.6 | L31: 1.7 | M31: =(I31*0.4+J31*0.6) -> 19.88 | N31: =(K31*0.4+L31*0.6) -> 2.06 | O31: 8.4 | P31: =+IFERROR(C31/B31,"") -> 0.70079706 | Q31: =IFERROR(1/P31,0) -> 1.4269466
A32: 0.41666667 | B32: 1603 | C32: 1084 | P32: =+IFERROR(C32/B32,"") -> 0.67623206 | Q32: =IFERROR(1/P32,0) -> 1.4787823
A33: 0.45833333 | B33: 1615 | C33: 922 | D33: 0.191 | E33: 0.787 | F33: 0.44 | G33: 0.73 | H33: 0.43 | I33: 29.3 | J33: 15.9 | K33: 2.7 | L33: 2.5 | M33: =(I33*0.4+J33*0.6) -> 21.26 | N33: =(K33*0.4+L33*0.6) -> 2.58 | O33: 8.4 | P33: =+IFERROR(C33/B33,"") -> 0.57089783 | Q33: =IFERROR(1/P33,0) -> 1.7516269
A34: 0.5 | B34: 1608 | C34: 1044 | P34: =+IFERROR(C34/B34,"") -> 0.64925373 | Q34: =IFERROR(1/P34,0) -> 1.5402299
A35: 0.54166667 | B35: 1612 | C35: 1030 | D35: 0.202 | E35: 0.73 | F35: 0.46 | G35: 0.565 | H35: 0.39 | I35: 29.8 | J35: 15.5 | K35: 2.9 | L35: 2.3 | M35: =(I35*0.4+J35*0.6) -> 21.22 | N35: =(K35*0.4+L35*0.6) -> 2.54 | O35: 8.1 | P35: =+IFERROR(C35/B35,"") -> 0.63895782 | Q35: =IFERROR(1/P35,0) -> 1.5650485
A36: 0.58333333 | B36: 1606 | C36: 1083 | P36: =+IFERROR(C36/B36,"") -> 0.6743462 | Q36: =IFERROR(1/P36,0) -> 1.4829178
A37: 0.625 | B37: 1562 | C37: 1090 | D37: 0.219 | E37: 0.669 | F37: 0.4 | G37: 0.575 | H37: 0.41 | I37: 29.6 | J37: 16.8 | K37: 2.8 | L37: 2.5 | M37: =(I37*0.4+J37*0.6) -> 21.92 | N37: =(K37*0.4+L37*0.6) -> 2.62 | O37: 8.2 | P37: =+IFERROR(C37/B37,"") -> 0.6978233 | Q37: =IFERROR(1/P37,0) -> 1.4330275
A38: 0.66666667 | B38: 1550 | C38: 1081 | P38: =+IFERROR(C38/B38,"") -> 0.69741935 | Q38: =IFERROR(1/P38,0) -> 1.4338575
A39: 0.70833333 | B39: 1610 | C39: 1104 | D39: 0.18 | E39: 0.689 | F39: 0.41 | G39: 0.7 | H39: 0.43 | I39: 26.1 | J39: 14.3 | K39: 2.1 | L39: 1.6 | M39: =(I39*0.4+J39*0.6) -> 19.02 | N39: =(K39*0.4+L39*0.6) -> 1.8 | O39: 8.3 | P39: =+IFERROR(C39/B39,"") -> 0.68571429 | Q39: =IFERROR(1/P39,0) -> 1.4583333
A40: 0.75 | B40: 1605 | C40: 1055 | P40: =+IFERROR(C40/B40,"") -> 0.65732087 | Q40: =IFERROR(1/P40,0) -> 1.521327
A41: 0.79166667 | B41: 1597 | C41: 1067 | D41: 0.2 | E41: 0.773 | F41: 0.44 | G41: 0.605 | H41: 0.4 | I41: 27.9 | J41: 18.1 | K41: 2.4 | L41: 2 | M41: =(I41*0.4+J41*0.6) -> 22.02 | N41: =(K41*0.4+L41*0.6) -> 2.16 | O41: 8.6 | P41: =+IFERROR(C41/B41,"") -> 0.66812774 | Q41: =IFERROR(1/P41,0) -> 1.4967198
A42: 0.83333333 | B42: 1587 | C42: 977 | P42: =+IFERROR(C42/B42,"") -> 0.61562697 | Q42: =IFERROR(1/P42,0) -> 1.6243603
A43: 0.875 | B43: 1590 | C43: 1067 | D43: 0.201 | E43: 0.812 | F43: 0.47 | G43: 0.609 | H43: 0.43 | I43: 22.4 | J43: 15.1 | K43: 1.8 | L43: 2.1 | M43: =(I43*0.4+J43*0.6) -> 18.02 | N43: =(K43*0.4+L43*0.6) -> 1.98 | O43: 8.1 | P43: =+IFERROR(C43/B43,"") -> 0.67106918 | Q43: =IFERROR(1/P43,0) -> 1.4901593
A44: 0.91666667 | B44: 1588 | C44: 1031 | P44: =+IFERROR(C44/B44,"") -> 0.64924433 | Q44: =IFERROR(1/P44,0) -> 1.5402522
A45: 0.95833333 | B45: 1596 | C45: 1100 | D45: 0.198 | E45: 0.751 | F45: 0.41 | G45: 0.583 | H45: 0.38 | I45: 24.7 | J45: 14.8 | K45: 2.8 | L45: 2 | M45: =(I45*0.4+J45*0.6) -> 18.76 | N45: =(K45*0.4+L45*0.6) -> 2.32 | O45: 8.1 | P45: =+IFERROR(C45/B45,"") -> 0.68922306 | Q45: =IFERROR(1/P45,0) -> 1.4509091
A46: 0 | B46: 1544 | C46: 1101 | E46: 📌 ABORDO =8,100 TM | P46: =+IFERROR(C46/B46,"") -> 0.7130829 | Q46: =IFERROR(1/P46,0) -> 1.4023615
A47: 0.041666667 | B47: 1580 | C47: 997 | D47: 0.206 | E47: 0.709 | F47: 0.38 | G47: 0.644 | H47: 0.4 | I47: 23.4 | J47: 20.8 | K47: 2.8 | L47: 4.3 | M47: =(I47*0.4+J47*0.6) -> 21.84 | N47: =(K47*0.4+L47*0.6) -> 3.7 | O47: 8.1 | P47: =+IFERROR(C47/B47,"") -> 0.63101266 | Q47: =IFERROR(1/P47,0) -> 1.5847543
A48: 0.083333333 | B48: 1586 | C48: 957 | P48: =+IFERROR(C48/B48,"") -> 0.60340479 | Q48: =IFERROR(1/P48,0) -> 1.6572623
A49: 0.125 | B49: 1582 | C49: 1053 | D49: 0.21 | E49: 0.65 | F49: 0.34 | G49: 0.761 | H49: 0.43 | I49: 22.5 | J49: 15.2 | K49: 2.2 | L49: 2.3 | M49: =(I49*0.4+J49*0.6) -> 18.12 | N49: =(K49*0.4+L49*0.6) -> 2.26 | O49: 8 | P49: =+IFERROR(C49/B49,"") -> 0.66561315 | Q49: =IFERROR(1/P49,0) -> 1.5023742
A50: 0.16666667 | B50: 1599 | C50: 1039 | P50: =+IFERROR(C50/B50,"") -> 0.64978111 | Q50: =IFERROR(1/P50,0) -> 1.5389798
A51: 0.20833333 | B51: 1589 | C51: 1091 | D51: 0.188 | E51: 0.747 | F51: 0.4 | G51: 0.532 | H51: 0.33 | I51: 25.3 | J51: 18.4 | K51: 3 | L51: 2.3 | M51: =(I51*0.4+J51*0.6) -> 21.16 | N51: =(K51*0.4+L51*0.6) -> 2.58 | O51: 8.1 | P51: =+IFERROR(C51/B51,"") -> 0.68659534 | Q51: =IFERROR(1/P51,0) -> 1.456462
A52: 0.25 | B52: 1600 | C52: 925 | P52: =+IFERROR(C52/B52,"") -> 0.578125 | Q52: =IFERROR(1/P52,0) -> 1.7297297
A53: 0.29166667 | B53: 1605 | C53: 1041 | D53: 0.174 | E53: 0.993 | F53: 0.58 | G53: 0.774 | H53: 0.44 | I53: 24.5 | J53: 15.7 | K53: 3 | L53: 2.4 | M53: =(I53*0.4+J53*0.6) -> 19.22 | N53: =(K53*0.4+L53*0.6) -> 2.64 | O53: 8 | P53: =+IFERROR(C53/B53,"") -> 0.64859813 | Q53: =IFERROR(1/P53,0) -> 1.5417867
A54: 0.33333333 | B54: 1395 | C54: 730 | P54: =+IFERROR(C54/B54,"") -> 0.52329749 | Q54: =IFERROR(1/P54,0) -> 1.9109589
A55: 46267 | B55: =+IF(SUM(B31:B54)=0, "", SUM(B31:B54)) -> 38040 | C55: =+IF(SUM(C31:C54)=0, "", SUM(C31:C54)) -> 24812 | D55: =IFERROR((AVERAGE(D31:D54)),0) -> 0.19733333 | E55: =IFERROR((AVERAGE(E31:E54)),0) -> 0.77508333 | F55: =IFERROR((AVERAGE(F31:F54)),0) -> 0.43833333 | G55: =IFERROR((AVERAGE(G31:G54)),0) -> 0.658 | H55: =+IFERROR((AVERAGE(H31:H54)),0) -> 0.41083333 | I55: =+IFERROR((AVERAGE(I31:I54)),"") -> 26.258333 | J55: =+IFERROR((AVERAGE(J31:J54)),"") -> 16.166667 | K55: =+IFERROR((AVERAGE(K31:K54)),"") -> 2.5916667 | L55: =+IFERROR((AVERAGE(L31:L54)),"") -> 2.3333333 | M55: =+IFERROR((AVERAGE(M31:M54)),0) -> 20.203333 | N55: =+IFERROR((AVERAGE(N31:N54)),0) -> 2.4366667 | O55: =+IFERROR((AVERAGE(O31:O54)),0) -> 8.2 | P55: =+IFERROR(C55/B55,"") -> 0.65226078 | Q55: =IFERROR(1/P55,0) -> 1.5331291
A56: 0.375 | B56: 1399 | C56: 911 | D56: 0.178 | E56: 0.706 | F56: 0.41 | G56: 0.615 | H56: 0.39 | I56: 28.8 | J56: 13 | K56: 2.6 | L56: 1.3 | M56: =(I56*0.4+J56*0.6) -> 19.32 | N56: =(K56*0.4+L56*0.6) -> 1.82 | O56: 8.3 | P56: =+IFERROR(C56/B56,"") -> 0.65117941 | Q56: =IFERROR(1/P56,0) -> 1.5356751 | S56: Desde las 07:00, parada de línea 2 por cambio de reductor de la faja 051-150
A57: 0.41666667 | B57: 1324 | C57: 802 | P57: =+IFERROR(C57/B57,"") -> 0.60574018 | Q57: =IFERROR(1/P57,0) -> 1.6508728
A58: 0.45833333 | B58: 1374 | C58: 899 | D58: 0.171 | E58: 0.706 | F58: 0.41 | G58: 0.73 | H58: 0.44 | I58: 23.9 | J58: 16.4 | K58: 2.5 | L58: 1 | M58: =(I58*0.4+J58*0.6) -> 19.4 | N58: =(K58*0.4+L58*0.6) -> 1.6 | O58: 8.1 | P58: =+IFERROR(C58/B58,"") -> 0.65429403 | Q58: =IFERROR(1/P58,0) -> 1.5283648
A59: 0.5 | B59: 1364 | C59: 941 | P59: =+IFERROR(C59/B59,"") -> 0.6898827 | Q59: =IFERROR(1/P59,0) -> 1.4495218
A60: 0.54166667 | B60: 1356 | C60: 918 | D60: 0.164 | E60: 0.656 | F60: 0.4 | G60: 0.7 | H60: 0.43 | I60: 26.3 | J60: 16.5 | K60: 2.6 | L60: 2.3 | M60: =(I60*0.4+J60*0.6) -> 20.42 | N60: =(K60*0.4+L60*0.6) -> 2.42 | O60: 8.1 | P60: =+IFERROR(C60/B60,"") -> 0.67699115 | Q60: =IFERROR(1/P60,0) -> 1.4771242
A61: 0.58333333 | B61: 1381 | C61: 949 | P61: =+IFERROR(C61/B61,"") -> 0.6871832 | Q61: =IFERROR(1/P61,0) -> 1.455216
A62: 0.625 | B62: 1378 | C62: 981 | D62: 0.166 | E62: 0.804 | F62: 0.47 | G62: 0.683 | H62: 0.41 | I62: 24.1 | J62: 14.2 | K62: 5.6 | L62: 2.2 | M62: =(I62*0.4+J62*0.6) -> 18.16 | N62: =(K62*0.4+L62*0.6) -> 3.56 | O62: 8.1 | P62: =+IFERROR(C62/B62,"") -> 0.71190131 | Q62: =IFERROR(1/P62,0) -> 1.4046891
A63: 0.66666667 | B63: 1361 | C63: 1194 | P63: =+IFERROR(C63/B63,"") -> 0.87729611 | Q63: =IFERROR(1/P63,0) -> 1.139866
A64: 0.70833333 | B64: 1388 | C64: 1167 | D64: 0.16 | E64: 0.81 | F64: 0.49 | G64: 0.818 | H64: 0.46 | I64: 23 | J64: 14.4 | K64: 2.5 | L64: 2.1 | M64: =(I64*0.4+J64*0.6) -> 17.84 | N64: =(K64*0.4+L64*0.6) -> 2.26 | O64: 8.2 | P64: =+IFERROR(C64/B64,"") -> 0.8407781 | Q64: =IFERROR(1/P64,0) -> 1.1893745
A65: 0.75 | B65: 1252 | C65: 931 | P65: =+IFERROR(C65/B65,"") -> 0.74361022 | Q65: =IFERROR(1/P65,0) -> 1.3447905 | R65: Parada de linea 9 por reparación de carrete distribuidor 212-893
A66: 0.79166667 | B66: 1177 | C66: 939 | D66: 0.168 | E66: 0.992 | F66: 0.56 | G66: 0.811 | H66: 0.49 | I66: 22.9 | J66: 14.2 | K66: 2.4 | L66: 2 | M66: =(I66*0.4+J66*0.6) -> 17.68 | N66: =(K66*0.4+L66*0.6) -> 2.16 | O66: 8.2 | P66: =+IFERROR(C66/B66,"") -> 0.79779099 | Q66: =IFERROR(1/P66,0) -> 1.2534611 | R66: Se realiza agregado de barras a Rm01 y 08
A67: 0.83333333 | B67: 1230 | C67: 885 | P67: =+IFERROR(C67/B67,"") -> 0.7195122 | Q67: =IFERROR(1/P67,0) -> 1.3898305 | R67: Se concluye reparación de carrete distribuidor 212-893, arranca linea 9. // Bolas 9 paró por falla en excitación del motor.
A68: 0.875 | B68: 1206 | C68: 839 | D68: 0.165 | E68: 0.75 | F68: 0.44 | G68: 0.908 | H68: 0.55 | I68: 21.9 | J68: 14.9 | K68: 2.9 | L68: 2.7 | M68: =(I68*0.4+J68*0.6) -> 17.7 | N68: =(K68*0.4+L68*0.6) -> 2.78 | O68: 8.1 | P68: =+IFERROR(C68/B68,"") -> 0.69568823 | Q68: =IFERROR(1/P68,0) -> 1.4374255 | R68: Se continua agregado de conos
A69: 0.91666667 | B69: 1211 | C69: 811 | P69: =+IFERROR(C69/B69,"") -> 0.66969447 | Q69: =IFERROR(1/P69,0) -> 1.4932182 | R69: Arrancó bolas 9, Jefatura electricista brindo el soporte
A70: 0.95833333 | B70: 1418 | C70: 761 | D70: 0.18 | E70: 0.752 | F70: 0.44 | G70: 0.781 | H70: 0.47 | I70: 21.5 | J70: 14.3 | K70: 2.1 | L70: 2 | M70: =(I70*0.4+J70*0.6) -> 17.18 | N70: =(K70*0.4+L70*0.6) -> 2.04 | O70: 8 | P70: =+IFERROR(C70/B70,"") -> 0.53667137 | Q70: =IFERROR(1/P70,0) -> 1.8633377
A71: 0 | B71: 1405 | C71: 771 | P71: =+IFERROR(C71/B71,"") -> 0.54875445 | Q71: =IFERROR(1/P71,0) -> 1.8223087
A72: 0.041666667 | B72: 1437 | C72: 914 | D72: 0.188 | E72: 0.726 | F72: 0.41 | G72: 0.772 | H72: 0.43 | I72: 32.5 | J72: 13.4 | K72: 3.1 | L72: 2 | M72: =(I72*0.4+J72*0.6) -> 21.04 | N72: =(K72*0.4+L72*0.6) -> 2.44 | O72: 8 | P72: =+IFERROR(C72/B72,"") -> 0.63604732 | Q72: =IFERROR(1/P72,0) -> 1.5722101
A73: 0.083333333 | B73: 1403 | C73: 736 | P73: =+IFERROR(C73/B73,"") -> 0.52459016 | Q73: =IFERROR(1/P73,0) -> 1.90625
A74: 0.125 | B74: 1421 | C74: 982 | D74: 0.184 | E74: 0.651 | F74: 0.38 | G74: 0.619 | H74: 0.36 | I74: 24.3 | J74: 14.5 | K74: 2.4 | L74: 2.3 | M74: =(I74*0.4+J74*0.6) -> 18.42 | N74: =(K74*0.4+L74*0.6) -> 2.34 | O74: 8 | P74: =+IFERROR(C74/B74,"") -> 0.69106263 | Q74: =IFERROR(1/P74,0) -> 1.4470468
A75: 0.16666667 | B75: 1358 | C75: 845 | P75: =+IFERROR(C75/B75,"") -> 0.62223859 | Q75: =IFERROR(1/P75,0) -> 1.6071006
A76: 0.20833333 | B76: 1402 | C76: 924 | D76: 0.179 | E76: 0.788 | F76: 0.43 | G76: 0.649 | H76: 0.38 | I76: 25 | J76: 13.8 | K76: 2.6 | L76: 2 | M76: =(I76*0.4+J76*0.6) -> 18.28 | N76: =(K76*0.4+L76*0.6) -> 2.24 | O76: 8 | P76: =+IFERROR(C76/B76,"") -> 0.65905849 | Q76: =IFERROR(1/P76,0) -> 1.517316
A77: 0.25 | B77: 1439 | C77: 761 | P77: =+IFERROR(C77/B77,"") -> 0.52883947 | Q77: =IFERROR(1/P77,0) -> 1.890933
A78: 0.29166667 | B78: 1423 | C78: 1031 | D78: 0.189 | E78: 0.62 | G78: 0.637 | K78: 2.7 | L78: 2.2 | M78: =(I78*0.4+J78*0.6) -> 0 | N78: =(K78*0.4+L78*0.6) -> 2.4 | O78: 8.1 | P78: =+IFERROR(C78/B78,"") -> 0.72452565 | Q78: =IFERROR(1/P78,0) -> 1.3802134
A79: 0.33333333 | B79: 1401 | C79: 889 | P79: =+IFERROR(C79/B79,"") -> 0.63454675 | Q79: =IFERROR(1/P79,0) -> 1.575928
A80: 46268 | B80: =+IF(SUM(B56:B79)=0, "", SUM(B56:B79)) -> 32508 | C80: =+IF(SUM(C56:C79)=0, "", SUM(C56:C79)) -> 21781 | D80: =+IFERROR((AVERAGE(D56:D79)),0) -> 0.17433333 | E80: =+IFERROR((AVERAGE(E56:E79)),0) -> 0.74675 | F80: =+IFERROR((AVERAGE(F56:F79)),0) -> 0.44 | G80: =+IFERROR((AVERAGE(G56:G79)),0) -> 0.72691667 | H80: =+IFERROR((AVERAGE(H56:H79)),0) -> 0.43727273 | I80: =+IFERROR((AVERAGE(I56:I79)),"") -> 24.927273 | J80: =+IFERROR((AVERAGE(J56:J79)),"") -> 14.509091 | K80: =+IFERROR((AVERAGE(K56:K79)),"") -> 2.8333333 | L80: =+IFERROR((AVERAGE(L56:L79)),"") -> 2.0083333 | M80: =+IFERROR((AVERAGE(M56:M79)),0) -> 17.12 | N80: =+IFERROR((AVERAGE(N56:N79)),0) -> 2.3383333 | O80: =+IFERROR((AVERAGE(O56:O79)),0) -> 8.1 | P80: =+IFERROR(C80/B80,"") -> 0.67001969 | Q80: =IFERROR(1/P80,0) -> 1.4924935
A81: 0.375 | B81: 1441 | C81: 1028 | D81: 0.174 | E81: 0.358 | F81: 0.3 | G81: 0.461 | H81: 0.34 | I81: 29.8 | J81: 13.9 | K81: 3.2 | L81: 2 | M81: =(I81*0.4+J81*0.6) -> 20.26 | N81: =(K81*0.4+L81*0.6) -> 2.48 | O81: 8.4 | P81: =+IFERROR(C81/B81,"") -> 0.71339348 | Q81: =IFERROR(1/P81,0) -> 1.401751
A82: 0.41666667 | B82: 1357 | C82: 697 | P82: =+IFERROR(C82/B82,"") -> 0.51363301 | Q82: =IFERROR(1/P82,0) -> 1.9469154 | S82: Restricción de carga por mantenimiento programado de L-4. Agitador 053-080: 62%
A83: 0.45833333 | B83: 1343 | C83: 824 | D83: 0.16 | E83: 0.439 | F83: 0.33 | G83: 0.438 | H83: 0.34 | I83: 26.5 | J83: 16.6 | K83: 2.8 | L83: 3.2 | M83: =(I83*0.4+J83*0.6) -> 20.56 | N83: =(K83*0.4+L83*0.6) -> 3.04 | O83: 8.3 | P83: =+IFERROR(C83/B83,"") -> 0.61355175 | Q83: =IFERROR(1/P83,0) -> 1.6298544
A84: 0.5 | B84: 1387 | C84: 684 | P84: =+IFERROR(C84/B84,"") -> 0.49315068 | Q84: =IFERROR(1/P84,0) -> 2.0277778
A85: 0.54166667 | B85: 1411 | C85: 724 | D85: 0.159 | E85: 0.406 | F85: 0.31 | G85: 0.461 | H85: 0.33 | I85: 28.2 | J85: 15.3 | K85: 3.2 | L85: 2.6 | M85: =(I85*0.4+J85*0.6) -> 20.46 | N85: =(K85*0.4+L85*0.6) -> 2.84 | O85: 8.1 | P85: =+IFERROR(C85/B85,"") -> 0.51311127 | Q85: =IFERROR(1/P85,0) -> 1.948895
A86: 0.58333333 | B86: 1416 | C86: 981 | P86: =+IFERROR(C86/B86,"") -> 0.69279661 | Q86: =IFERROR(1/P86,0) -> 1.4434251
A87: 0.625 | B87: 1414 | C87: 827 | D87: 0.16 | E87: 0.489 | F87: 0.33 | G87: 0.534 | H87: 0.36 | I87: 25.5 | J87: 14 | K87: 3.3 | L87: 1.6 | M87: =(I87*0.4+J87*0.6) -> 18.6 | N87: =(K87*0.4+L87*0.6) -> 2.28 | O87: 8.4 | P87: =+IFERROR(C87/B87,"") -> 0.58486563 | Q87: =IFERROR(1/P87,0) -> 1.7097944
A88: 0.66666667 | B88: 1261 | C88: 863 | P88: =+IFERROR(C88/B88,"") -> 0.68437748 | Q88: =IFERROR(1/P88,0) -> 1.4611819 | R88: Rm09 entró en operación 16:16 hrs
A89: 0.70833333 | B89: 1350 | C89: 1026 | D89: 0.136 | E89: 0.516 | F89: 0.34 | G89: 0.72 | H89: 0.4 | I89: 26.3 | J89: 14.1 | K89: 3.5 | L89: 1.7 | M89: =(I89*0.4+J89*0.6) -> 18.98 | N89: =(K89*0.4+L89*0.6) -> 2.42 | O89: 8 | P89: =+IFERROR(C89/B89,"") -> 0.76 | Q89: =IFERROR(1/P89,0) -> 1.3157895
A90: 0.75 | B90: 1325 | C90: 1067 | P90: =+IFERROR(C90/B90,"") -> 0.80528302 | Q90: =IFERROR(1/P90,0) -> 1.2417994 | R90: Agregado de barras al Rm09
A91: 0.79166667 | B91: 1288 | C91: 935 | D91: 0.138 | E91: 1.055 | F91: 0.89 | G91: 1.061 | H91: 0.86 | I91: 24.9 | J91: 16.4 | K91: 3.3 | L91: 2.2 | M91: =(I91*0.4+J91*0.6) -> 19.8 | N91: =(K91*0.4+L91*0.6) -> 2.64 | O91: 8.3 | P91: =+IFERROR(C91/B91,"") -> 0.72593168 | Q91: =IFERROR(1/P91,0) -> 1.3775401 | R91: Agregado de barras al Rm07, arrancó Rm05 en reemplazo. // Se giró bolas 5 sistema de lubricación en manual
A92: 0.83333333 | B92: 1430 | C92: 922 | P92: =+IFERROR(C92/B92,"") -> 0.64475524 | Q92: =IFERROR(1/P92,0) -> 1.5509761 | R92: Se reducen colchones de espumas celdas antiguas y nuevas. Se reduce dosificación de reactivos en planta | S92: 20:00 a 20:20 hrs parada por falla en stacker de transferencia
A93: 0.875 | B93: 1427 | C93: 618 | D93: 0.129 | E93: 0.604 | F93: 0.44 | G93: 0.477 | H93: 0.34 | I93: 27.4 | J93: 14.5 | K93: 3.4 | L93: 2.3 | M93: =(I93*0.4+J93*0.6) -> 19.66 | N93: =(K93*0.4+L93*0.6) -> 2.74 | O93: 8 | P93: =+IFERROR(C93/B93,"") -> 0.43307638 | Q93: =IFERROR(1/P93,0) -> 2.3090615 | R93: Arrancó Rm07, en stand by Rm05 | S93: 21:20 a 21:40 hrs parada por activación de emergencia en stacker de transferencia por electricistas trabajando
A94: 0.91666667 | B94: 1441 | C94: 891 | P94: =+IFERROR(C94/B94,"") -> 0.61832061 | Q94: =IFERROR(1/P94,0) -> 1.617284 | R94: Se incrementa colchones de espumas en celdas de planta | S94: 21:40 hrs arrancó linea 4 por control de nivel de agitadores
A95: 0.95833333 | B95: 1438 | C95: 1270 | D95: 0.138 | E95: 0.445 | F95: 0.33 | G95: 0.414 | H95: 0.34 | I95: 27.6 | J95: 15.1 | K95: 3.5 | L95: 2.7 | M95: =(I95*0.4+J95*0.6) -> 20.1 | N95: =(K95*0.4+L95*0.6) -> 3.02 | O95: 8.6 | P95: =+IFERROR(C95/B95,"") -> 0.88317107 | Q95: =IFERROR(1/P95,0) -> 1.1322835 | R95: Se desatora bomba de xantato a fase 2
A96: 0 | B96: 1445 | C96: 790 | P96: =+IFERROR(C96/B96,"") -> 0.5467128 | Q96: =IFERROR(1/P96,0) -> 1.8291139
A97: 0.041666667 | B97: 1454 | C97: 1174 | D97: 0.151 | E97: 0.445 | F97: 0.32 | G97: 0.474 | H97: 0.36 | I97: 30.5 | J97: 15.3 | K97: 3 | L97: 2.1 | M97: =(I97*0.4+J97*0.6) -> 21.38 | N97: =(K97*0.4+L97*0.6) -> 2.46 | O97: 8.2 | P97: =+IFERROR(C97/B97,"") -> 0.80742779 | Q97: =IFERROR(1/P97,0) -> 1.2385009
A98: 0.083333333 | B98: 1470 | C98: 760 | P98: =+IFERROR(C98/B98,"") -> 0.5170068 | Q98: =IFERROR(1/P98,0) -> 1.9342105
A99: 0.125 | B99: 1418 | C99: 1125 | D99: 0.154 | E99: 0.406 | F99: 0.3 | G99: 0.597 | H99: 0.41 | I99: 27.1 | J99: 15.6 | K99: 2.7 | L99: 2.3 | M99: =(I99*0.4+J99*0.6) -> 20.2 | N99: =(K99*0.4+L99*0.6) -> 2.46 | O99: 8.1 | P99: =+IFERROR(C99/B99,"") -> 0.79337094 | Q99: =IFERROR(1/P99,0) -> 1.2604444 | R99: Agregando barras molino Rm3/4
A100: 0.16666667 | B100: 1398 | C100: 935 | P100: =+IFERROR(C100/B100,"") -> 0.66881259 | Q100: =IFERROR(1/P100,0) -> 1.4951872
A101: 0.20833333 | B101: 1412 | C101: 1032 | D101: 0.165 | E101: 0.433 | F101: 0.37 | G101: 0.511 | H101: 0.38 | I101: 27 | J101: 14.6 | K101: 2.8 | L101: 2.2 | M101: =(I101*0.4+J101*0.6) -> 19.56 | N101: =(K101*0.4+L101*0.6) -> 2.44 | O101: 8.4 | P101: =+IFERROR(C101/B101,"") -> 0.73087819 | Q101: =IFERROR(1/P101,0) -> 1.3682171
A102: 0.25 | B102: 1401 | C102: 919 | P102: =+IFERROR(C102/B102,"") -> 0.65596003 | Q102: =IFERROR(1/P102,0) -> 1.5244831
A103: 0.29166667 | B103: 1405 | C103: 973 | D103: 0.159 | E103: 0.438 | F103: 0.4 | G103: 0.546 | H103: 0.43 | I103: 27 | J103: 14.3 | K103: 2.9 | L103: 2 | M103: =(I103*0.4+J103*0.6) -> 19.38 | N103: =(K103*0.4+L103*0.6) -> 2.36 | O103: 8.3 | P103: =+IFERROR(C103/B103,"") -> 0.69252669 | Q103: =IFERROR(1/P103,0) -> 1.4439877
...

Sheet Fallas
A2: Fecha | B2: Equipo | C2: Inicio de parada | D2: Arranque | E2: Tiempo perdido (hrs) | F2: MIneral no procesado (TM) | G2: Concentrado no producido (TMS) | H2: Falla (mecánica/eléctrica /instrumentación/operaciones) | I2: Motivo
A3: 46266 | B3: 032-081 | C3: 0 | D3: 0.95069444 | E3: 0 | F3: =+E3*200 -> 0 | G3: =+F3/1.5 -> 0 | H3: Operaciones | I3: Arranco en reemplazo Rm02
B4: 032-082 | C4: 0.95347222 | D4: 0 | E4: 0 | F4: =+E4*200 -> 0 | G4: =+F4/1.5 -> 0 | H4: Operaciones | I4: Paró por ajuste de pernos. Stand by
A5: 46268 | B5: 032-089 | C5: 0.72222222 | D5: 0.80138889 | E5: 1.9 | F5: =220*E5 -> 418 | G5: =+F5/1.5 -> 278.66667 | H5: Falla mecanica | I5: Por parada del bolas 9
B6: 032-089 | C6: 0.81111111 | D6: 0.91875 | E6: 2.58 | F6: =220*E6 -> 567.6 | G6: =+F6/1.5 -> 378.4 | H6: Falla electrica | I6: Por parada del bolas 9
B7: 032-209 | C7: 0.72708333 | D7: 0.80069444 | E7: 1.9 | F7: =180*E7 -> 342 | G7: =+F7/1.5 -> 228 | H7: Falla mecanica | I7: Perforacion en distribuidor de ciclones
B8: 032-209 | C8: 0.81041667 | D8: 0.91666667 | E8: 2.5 | F8: =180*E8 -> 450 | G8: =+F8/1.5 -> 300 | H8: Falla electrica | I8: Falla excitación del motor
A9: 46238 | B9: 032-082 | C9: 0 | D9: 0.70625 | E9: 0 | F9: =220*E9 -> 0 | G9: =+F9/1.5 -> 0 | H9: Operaciones | I9: Arranco en reemplazo Rm04
B10: 032-084 | C10: 0.70138889 | D10: 0 | E10: 0 | F10: =220*E10 -> 0 | G10: =+F10/1.5 -> 0 | H10: Operaciones | I10: Paró por limpieza trunnion alimentación. Stand by
B11: 032-085 | C11: 0 | D11: 0.77708333 | E11: 0 | F11: =220*E11 -> 0 | G11: =+F11/1.5 -> 0 | H11: Operaciones | I11: Arranco en reemplazo Rm07
B12: 032-087 | C12: 0.76041667 | D12: 0 | E12: 0 | F12: =220*E12 -> 0 | G12: =+F12/1.5 -> 0 | H12: Operaciones | I12: Paró por arranque Rm05. Stand by
B13: 032-089 | C13: 0.63888889 | D13: 0.67777778 | E13: 0.95 | F13: =220*E13 -> 209 | G13: =+F13/1.5 -> 139.33333 | H13: Falla mecanica | I13: Cambio de manguera descarga 213-135
A14: 46271 | B14: 032-083 | C14: 0.36111111 | D14: 0.42777778 | E14: 1.52 | F14: =150*E14 -> 228 | G14: =+F14/1.5 -> 152 | H14: Falla mecanica | I14: Perforación en brida ciega de manguera alimentación de la bomba 213-802 al Bm10
A15: 46272 | B15: 032-083 | C15: 0.89583333 | D15: 0.97916667 | E15: 2 | F15: =150*E15 -> 300 | G15: =+F15/1.5 -> 200 | H15: Falla mecanica | I15: Perforación en sumidero 213-233
A16: 46273 | B16: 032-204 | C16: 0.88333333 | D16: 0.088194444 | E16: 4.91 | F16: =60*E16 -> 294.6 | G16: =+F16/1.5 -> 196.4 | H16: Falla mecanica | I16: Fuga de carga bomba 213-214- cambio impulsor/cilindro.
A17: 46274 | B17: 032-204 | C17: 0.97638889 | D17: 0.0055555556 | E17: 0.7 | F17: =60*E17 -> 42 | G17: =+F17/1.5 -> 28 | H17: Falla mecanica | I17: Perforación en manguera de descarga de bomba 213-214
A18: 46275 | B18: 032-087 | C18: 0.12013889 | D18: 0.12430556 | E18: 0.1 | F18: =150*E18 -> 15 | G18: =+F18/1.5 -> 10 | H18: Falla mecanica | I18: Retiro de barretilla atravesada en malla trommel.
A19: 46276 | B19: RM01/09 | C19: 0.27777778 | D19: 0.33333333 | E19: 1.33 | F19: =1530*E19 -> 2034.9 | G19: =+F19/1.5 -> 1356.6 | H19: Falla eléctrica | I19: Corte general de energia
B20: BM01/10 | C20: 0.27777778 | D20: 0.33333333 | E20: 1.33 | F20: =1250*E20 -> 1662.5 | G20: =+F20/1.5 -> 1108.3333 | H20: Falla eléctrica | I20: Corte general de energia
A21: 46278 | B21: 032-081 | C21: 0.22916667 | D21: 0.33333333 | E21: 2.5 | F21: =200*E21 -> 500 | G21: =+F21/1.5 -> 333.33333 | H21: Falla mecanica | I21: Falla en bombas de alta del sistema lubricacion
B22: 032-083 | C22: 0.80694444 | D22: 0.99166667 | E22: 4.43 | F22: =150*E22 -> 664.5 | G22: =+F22/1.5 -> 443 | H22: Falla mecanica | I22: por perforación del sumidero 213-651.
B23: 032-083 | C23: 0.034722222 | D23: 0.28125 | E23: 5.92 | F23: =150*E23 -> 888 | G23: =+F23/1.5 -> 592 | H23: Falla mecanica | I23: por perforacion del sumidero 213-233, stand by
B24: 032-086 | C24: 0.89930556 | D24: 0.90763889 | E24: 0.2 | F24: =200*E24 -> 40 | G24: =+F24/1.5 -> 26.666667 | H24: Falla operaciones | I24: atoro en cajón de concentrado descarga sep 210-103/104.
B25: 032-087 | C25: 0.15625 | D25: 0.18402778 | E25: 0.67 | F25: =200*E25 -> 134 | G25: =+F25/1.5 -> 89.333333 | H25: Falla mecanica | I25: por parada del bolas 7
B26: 032-201 | C26: 0.22916667 | D26: 0.26111111 | E26: 0.76 | F26: =150*E26 -> 114 | G26: =+F26/1.5 -> 76 | H26: Falla mecanica | I26: parada por alarma de temperatura lado limpio
B27: 032-207 | C27: 0.15625 | D27: 0.18055556 | E27: 0.58 | F27: =150*E27 -> 87 | G27: =+F27/1.5 -> 58 | H27: Falla mecanica | I27: Falla del sistema hidrostatico bomba alta #2
B28: 032-082 | C28: 0.75347222 | D28: 0.79791667 | E28: 1.07 | F28: =+E28*200 -> 214 | G28: =+F28/1.5 -> 142.66667
B29: 032-201 | C29: 0.76458333 | D29: 0.79722222 | E29: 0.78 | H29: Falla mecanica | I29: Cambio de bomba aceite rductor y acoplr nuevo ventilador.
A30: 46279 | B30: 032-084 | C30: 0.072916667 | D30: 0.10833333 | E30: 0.85 | F30: =150*E30 -> 127.5 | G30: =+F30/1.5 -> 85 | H30: Falla mecanica | I30: Por parada del bolas 10
B31: 032-210 | C31: 0.081944444 | D31: 0.10694444 | E31: 0.77 | F31: =100*E31 -> 77 | G31: =+F31/1.5 -> 51.333333 | H31: Falla mecanica | I31: Por perforacion del canal de alimentacion
A32: 46280 | B32: 032-088 | C32: 0.85972222 | D32: 0.15763889 | E32: 7.2 | F32: =200*E32 -> 1440 | G32: =+F32/1.5 -> 960 | H32: Falla mecanica | I32: por parada del bolas 08
B33: 032-208 | C33: 0.85972222 | D33: 0.15972222 | E33: 7.2 | F33: =150*E33 -> 1080 | G33: =+F33/1.5 -> 720 | H33: Falla mecanica | I33: alta temperatura de pedestal STE
A34: 46281 | B34: 032-087 | C34: 0.21319444 | D34: 0.33333333 | E34: 2.95 | F34: =200*E34 -> 590 | G34: =+F34/1.5 -> 393.33333 | H34: Falla mecanica | I34: por parada del bolas 07
B35: 032-207 | C35: 0.1875 | D35: 0.33333333 | E35: 3.5 | F35: =150*E35 -> 525 | G35: =+F35/1.5 -> 350 | H35: Falla mecanica | I35: Baja presion de aceite bomba de alta #2, bomba #1 fuerte ruido mecanico// salida de malla reten
A36: 46284 | B36: 032-084 | C36: 0.79861111 | D36: 0.86736111 | E36: 1.65 | F36: =150*E36 -> 247.5 | G36: =+F36/1.5 -> 165 | H36: Falla mecanica | I36: por parada del bolas 10
B37: 032-210 | C37: 0.8125 | D37: 0.86319444 | E37: 0.5 | F37: =100*E37 -> 50 | G37: =+F37/1.5 -> 33.333333 | H37: Falla mecanica | I37: Retirar forro caido del interior
B38: 032-210 | C38: 0.83333333 | D38: 0.86319444 | E38: 0.72 | F38: =100*E38 -> 72 | G38: =+F38/1.5 -> 48 | H38: Falla electrica | I38: falla electrica en arranque, se subio factor de potencia
A39: 46285 | B39: 032-083 | C39: 0.4625 | D39: 0.62916667 | E39: 4 | F39: =150*E39 -> 600 | G39: =+F39/1.5 -> 400 | H39: Falla mecanica | I39: alta temperatura de pedestal STE, se rectifico peine
B40: 032-084 | C40: 0.69166667 | D40: 0.75902778 | E40: 1.62 | F40: =150*E40 -> 243 | G40: =+F40/1.5 -> 162 | H40: Falla mecanica | I40: por parada del bolas 10
B41: 032-089 | C41: 0.48611111 | D41: 0.83333333 | E41: 8.33 | F41: =220*E41 -> 1832.6 | G41: =+F41/1.5 -> 1221.7333 | H41: Falla mecanica | I41: Perdida de carga por cuello trommel
B42: 032-210 | C42: 0.70833333 | D42: 0.75555556 | E42: 1.1 | F42: =100*E42 -> 110 | G42: =+F42/1.5 -> 73.333333 | H42: Falla electrica | I42: Fuga de aceite por valvula de retorno sistema hidrostatico, se cambio
A43: 46286 | B43: 032-081 | C43: 0.73402778 | D43: 0.78819444 | E43: 1.3 | F43: =150*E43 -> 195 | G43: =+F43/1.5 -> 130 | H43: Falla mecanica | I43: Por parada del bolas 1
B44: 032-089 | C44: 0.59236111 | D44: 0.81527778 | E44: 5.35 | F44: =220*E44 -> 1177 | G44: =+F44/1.5 -> 784.66667 | H44: Falla mecanica | I44: por parada del bolas 9
B45: 032-201 | C45: 0.73402778 | D45: 0.76180556 | E45: 0.7 | F45: =150*E45 -> 105 | G45: =+F45/1.5 -> 70 | H45: Falla instrumentacion | I45: Falla en sensor de temperatura lado condicional
B46: 032-201 | C46: 0.76180556 | D46: 0.78680556 | E46: 0.6 | F46: =150*E46 -> 90 | G46: =+F46/1.5 -> 60 | H46: Falla mecanica | I46: Bajo flujo y presion de la bomba de alta #1, se cambio a la #2
B47: 032-204 | C47: 0.93263889 | D47: 0.95138889 | E47: 0.45 | F47: =50*E47 -> 22.5 | G47: =+F47/1.5 -> 15 | H47: Falla operaciones | I47: Limpieza de conos de malla trommel
B48: 032-209 | C48: 0.61527778 | D48: 0.80902778 | E48: 4.65 | F48: =180*E48 -> 837 | G48: =+F48/1.5 -> 558 | H48: Falla mecanica | I48: Cambio de reten de alimentacion, pernos del trommel y modificacion de malla descarga
A49: 46287 | B49: 032-085 | C49: 0.65972222 | D49: 0.68402778 | E49: 0.58 | F49: =200*E49 -> 116 | G49: =+F49/1.5 -> 77.333333 | H49: Falla mecanica | I49: Alta temperatura aceite retorno
B50: 032-085 | C50: 0.72916667 | D50: 0.91875 | E50: 4.5 | F50: =200*E50 -> 900 | G50: =+F50/1.5 -> 600 | H50: Falla mecanica | I50: Parada del bolas 5
B51: 032-087 | C51: 0.78472222 | D51: 1 | E51: 5.16 | F51: =200*E51 -> 1032 | G51: =+F51/1.5 -> 688 | H51: Falla mecanica | I51: Por parada del bolas 7
B52: 032-205 | C52: 0.75 | D52: 0.91597222 | E52: 4 | F52: =150*E52 -> 600 | G52: =+F52/1.5 -> 400 | H52: Falla mecanica | I52: Ampliar ranuras de la malla descarga y cambio de reten
B53: 032-207 | C53: 0.80625 | D53: 1 | E53: 4.65 | F53: =150*E53 -> 697.5 | G53: =+F53/1.5 -> 465 | H53: Falla mecanica | I53: Dializado de aceite sistema lubricacion
A54: 46291 | B54: 032-203 | C54: 0.14305556 | D54: 0.19861111 | E54: 1.33 | F54: =50*E54 -> 66.5 | G54: =+F54/1.5 -> 44.333333 | H54: Falla mecanica | I54: Instalar platina en abertura de cajon de descarga
B55: 032-089 | C55: 0.32708333 | D55: 0.33055556 | E55: 0.08 | F55: =220*E55 -> 17.6 | G55: =+F55/1.5 -> 11.733333 | H55: Falla instrumentacion | I55: Falla en sistema hidrostatico, falsa señal bomba de alta
A56: 46293 | B56: 032-084 | C56: 0.074305556 | D56: 0.12777778 | E56: 1.28 | F56: =150*E56 -> 192 | G56: =+F56/1.5 -> 128 | H56: Falla mecanica | I56: Cambio de jebe sello y desatoro manguera de sello 213-651

Sheet CONTROL CONSUMO REACTIVOS
B3: CONSUMO DE ÁCIDO OXÁLICO (KG) | G3: CONSUMO DE XANTATO (KG) | L3: CONSUMO DE ESPUMANTE
H4: Concentracion al 7 %
B5: FECHA | C5: Turno dia (12 hr) | D5: Turno noche (12 hr) | E5: Total | G5: FECHA | H5: Turno dia (12 hr) | I5: Turno noche (12 hr) | J5: Total | L5: FECHA | M5: Consumo por dia
B6: 46266 | C6: ='[1]SEPTIEMBRE 2026'!G5 -> 20000 | D6: ='[1]SEPTIEMBRE 2026'!H5 -> 16000 | E6: =SUM(C6,D6) -> 36000 | G6: =B6 -> 46266 | H6: ='[2]SEPTIEMBRE 2026'!G5 -> 3800 | I6: ='[2]SEPTIEMBRE 2026'!H5 -> 3850 | J6: =SUM(H6,I6) -> 7650 | L6: =G6 -> 46266 | M6: =[3]REACTIVOS!Z610 -> 3000
B7: 46267 | C7: ='[1]SEPTIEMBRE 2026'!G6 -> 14000 | D7: ='[1]SEPTIEMBRE 2026'!H6 -> 18000 | E7: =SUM(C7,D7) -> 32000 | G7: =B7 -> 46267 | H7: ='[2]SEPTIEMBRE 2026'!G6 -> 3850 | I7: ='[2]SEPTIEMBRE 2026'!H6 -> 3850 | J7: =SUM(H7,I7) -> 7700 | L7: =G7 -> 46267 | M7: =[3]REACTIVOS!Z611 -> 3500
B8: 46268 | C8: ='[1]SEPTIEMBRE 2026'!G7 -> 18000 | D8: ='[1]SEPTIEMBRE 2026'!H7 -> 18000 | E8: =SUM(C8,D8) -> 36000 | G8: =B8 -> 46268 | H8: ='[2]SEPTIEMBRE 2026'!G7 -> 3425 | I8: ='[2]SEPTIEMBRE 2026'!H7 -> 4250 | J8: =SUM(H8,I8) -> 7675 | L8: =G8 -> 46268 | M8: =[3]REACTIVOS!Z612 -> 3000
B9: 46269 | C9: ='[1]SEPTIEMBRE 2026'!G8 -> 20000 | D9: ='[1]SEPTIEMBRE 2026'!H8 -> 18000 | E9: =SUM(C9,D9) -> 38000 | G9: =B9 -> 46269 | H9: ='[2]SEPTIEMBRE 2026'!G8 -> 3950 | I9: ='[2]SEPTIEMBRE 2026'!H8 -> 3150 | J9: =SUM(H9,I9) -> 7100 | L9: =G9 -> 46269 | M9: =[3]REACTIVOS!Z613 -> 2500
B10: 46270 | C10: ='[1]SEPTIEMBRE 2026'!G9 -> 14000 | D10: ='[1]SEPTIEMBRE 2026'!H9 -> 14000 | E10: =SUM(C10,D10) -> 28000 | G10: =B10 -> 46270 | H10: ='[2]SEPTIEMBRE 2026'!G9 -> 3950 | I10: ='[2]SEPTIEMBRE 2026'!H9 -> 3400 | J10: =SUM(H10,I10) -> 7350 | L10: =G10 -> 46270 | M10: =[3]REACTIVOS!Z614 -> 2500
B11: 46271 | C11: ='[1]SEPTIEMBRE 2026'!G10 -> 14000 | D11: ='[1]SEPTIEMBRE 2026'!H10 -> 18000 | E11: =SUM(C11,D11) -> 32000 | G11: =B11 -> 46271 | H11: ='[2]SEPTIEMBRE 2026'!G10 -> 3900 | I11: ='[2]SEPTIEMBRE 2026'!H10 -> 3200 | J11: =SUM(H11,I11) -> 7100 | L11: =G11 -> 46271 | M11: =[3]REACTIVOS!Z615 -> 2500
B12: 46272 | C12: ='[1]SEPTIEMBRE 2026'!G11 -> 14000 | D12: ='[1]SEPTIEMBRE 2026'!H11 -> 18000 | E12: =SUM(C12,D12) -> 32000 | G12: =B12 -> 46272 | H12: ='[2]SEPTIEMBRE 2026'!G11 -> 2550 | I12: ='[2]SEPTIEMBRE 2026'!H11 -> 3850 | J12: =SUM(H12,I12) -> 6400 | L12: =G12 -> 46272 | M12: =[3]REACTIVOS!Z616 -> 2000
B13: 46273 | C13: ='[1]SEPTIEMBRE 2026'!G12 -> 16000 | D13: ='[1]SEPTIEMBRE 2026'!H12 -> 18000 | E13: =SUM(C13,D13) -> 34000 | G13: =B13 -> 46273 | H13: ='[2]SEPTIEMBRE 2026'!G12 -> 3400 | I13: ='[2]SEPTIEMBRE 2026'!H12 -> 4050 | J13: =SUM(H13,I13) -> 7450 | L13: =G13 -> 46273 | M13: =[3]REACTIVOS!Z617 -> 2500
B14: 46274 | C14: ='[1]SEPTIEMBRE 2026'!G13 -> 16000 | D14: ='[1]SEPTIEMBRE 2026'!H13 -> 20000 | E14: =SUM(C14,D14) -> 36000 | G14: =B14 -> 46274 | H14: ='[2]SEPTIEMBRE 2026'!G13 -> 4950 | I14: ='[2]SEPTIEMBRE 2026'!H13 -> 4400 | J14: =SUM(H14,I14) -> 9350 | L14: =G14 -> 46274 | M14: =[3]REACTIVOS!Z618 -> 2500
B15: 46275 | C15: ='[1]SEPTIEMBRE 2026'!G14 -> 18000 | D15: ='[1]SEPTIEMBRE 2026'!H14 -> 18000 | E15: =SUM(C15,D15) -> 36000 | G15: =B15 -> 46275 | H15: ='[2]SEPTIEMBRE 2026'!G14 -> 3150 | I15: ='[2]SEPTIEMBRE 2026'!H14 -> 3150 | J15: =SUM(H15,I15) -> 6300 | L15: =G15 -> 46275 | M15: =[3]REACTIVOS!Z619 -> 2500
B16: 46276 | C16: ='[1]SEPTIEMBRE 2026'!G15 -> 18000 | D16: ='[1]SEPTIEMBRE 2026'!H15 -> 18000 | E16: =SUM(C16,D16) -> 36000 | G16: =B16 -> 46276 | H16: ='[2]SEPTIEMBRE 2026'!G15 -> 3500 | I16: ='[2]SEPTIEMBRE 2026'!H15 -> 3150 | J16: =SUM(H16,I16) -> 6650 | L16: =G16 -> 46276 | M16: =[3]REACTIVOS!Z620 -> 2000
B17: 46277 | C17: ='[1]SEPTIEMBRE 2026'!G16 -> 0 | D17: ='[1]SEPTIEMBRE 2026'!H16 -> 18000 | E17: =SUM(C17,D17) -> 18000 | G17: =B17 -> 46277 | H17: ='[2]SEPTIEMBRE 2026'!G16 -> 350 | I17: ='[2]SEPTIEMBRE 2026'!H16 -> 3150 | J17: =SUM(H17,I17) -> 3500 | L17: =G17 -> 46277 | M17: =[3]REACTIVOS!Z621 -> 1500
... B26: 46286 | C26: ='[1]SEPTIEMBRE 2026'!G25 -> 24000 | D26: ='[1]SEPTIEMBRE 2026'!H25 -> 18000 | E26: =SUM(C26,D26) -> 42000 | G26: =B26 -> 46286 | H26: ='[2]SEPTIEMBRE 2026'!G25 -> 4400 | I26: ='[2]SEPTIEMBRE 2026'!H25 -> 3150 | J26: =SUM(H26,I26) -> 7550 | L26: =G26 -> 46286 | M26: =[3]REACTIVOS!Z630 -> 2500
B27: 46287 | C27: 22000 | D27: 18000 | E27: =SUM(C27,D27) -> 40000 | G27: =B27 -> 46287 | H27: 3150 | I27: 3150 | J27: =SUM(H27,I27) -> 6300 | L27: =G27 -> 46287 | M27: =[3]REACTIVOS!Z631 -> 2000
B28: 46288 | C28: ='[1]SEPTIEMBRE 2026'!G27 -> 20000 | D28: ='[1]SEPTIEMBRE 2026'!H27 -> 22000 | E28: =SUM(C28,D28) -> 42000 | G28: =B28 -> 46288 | H28: ='[2]SEPTIEMBRE 2026'!G27 -> 3250 | I28: ='[2]SEPTIEMBRE 2026'!H27 -> 3450 | J28: =SUM(H28,I28) -> 6700 | L28: =G28 -> 46288 | M28: =[3]REACTIVOS!Z632 -> 2000
B29: 46289 | C29: ='[1]SEPTIEMBRE 2026'!G28 -> 30000 | D29: ='[1]SEPTIEMBRE 2026'!H28 -> 24000 | E29: =SUM(C29,D29) -> 54000 | G29: =B29 -> 46289 | H29: ='[2]SEPTIEMBRE 2026'!G28 -> 4150 | I29: ='[2]SEPTIEMBRE 2026'!H28 -> 4800 | J29: =SUM(H29,I29) -> 8950 | L29: =G29 -> 46289 | M29: =[3]REACTIVOS!Z633 -> 2000
B30: 46290 | C30: ='[1]SEPTIEMBRE 2026'!G29 -> 26000 | D30: ='[1]SEPTIEMBRE 2026'!H29 -> 26000 | E30: =SUM(C30,D30) -> 52000 | G30: =B30 -> 46290 | H30: ='[2]SEPTIEMBRE 2026'!G29 -> 4000 | I30: ='[2]SEPTIEMBRE 2026'!H29 -> 4400 | J30: =SUM(H30,I30) -> 8400 | L30: =G30 -> 46290 | M30: =[3]REACTIVOS!Z634 -> 2000
B31: 46291 | C31: ='[1]SEPTIEMBRE 2026'!G30 -> 20000 | D31: ='[1]SEPTIEMBRE 2026'!H30 -> 16000 | E31: =SUM(C31,D31) -> 36000 | G31: =B31 -> 46291 | H31: ='[2]SEPTIEMBRE 2026'!G30 -> 3850 | I31: ='[2]SEPTIEMBRE 2026'!H30 -> 3150 | J31: =SUM(H31,I31) -> 7000 | L31: =G31 -> 46291 | M31: =[3]REACTIVOS!Z635 -> 2500
B32: 46292 | C32: ='[1]SEPTIEMBRE 2026'!G31 -> 24000 | D32: ='[1]SEPTIEMBRE 2026'!H31 -> 20000 | E32: =SUM(C32,D32) -> 44000 | G32: =B32 -> 46292 | H32: ='[2]SEPTIEMBRE 2026'!G31 -> 3450 | I32: ='[2]SEPTIEMBRE 2026'!H31 -> 3600 | J32: =SUM(H32,I32) -> 7050 | L32: =G32 -> 46292 | M32: =[3]REACTIVOS!Z636 -> 2500
B33: 46293 | C33: ='[1]SEPTIEMBRE 2026'!G32 -> 24000 | D33: ='[1]SEPTIEMBRE 2026'!H32 -> 20000 | E33: =SUM(C33,D33) -> 44000 | G33: =B33 -> 46293 | H33: ='[2]SEPTIEMBRE 2026'!G32 -> 3250 | I33: ='[2]SEPTIEMBRE 2026'!H32 -> 3800 | J33: =SUM(H33,I33) -> 7050 | L33: =G33 -> 46293 | M33: =[3]REACTIVOS!Z637 -> 3000
B34: 46294 | C34: ='[1]SEPTIEMBRE 2026'!G33 -> 20000 | D34: ='[1]SEPTIEMBRE 2026'!H33 -> 16000 | E34: =SUM(C34,D34) -> 36000 | G34: =B34 -> 46294 | H34: ='[2]SEPTIEMBRE 2026'!G33 -> 3600 | I34: ='[2]SEPTIEMBRE 2026'!H33 -> 3350 | J34: =SUM(H34,I34) -> 6950 | L34: =G34 -> 46294 | M34: =[3]REACTIVOS!Z638 -> 3000
B35: 46295 | C35: ='[1]SEPTIEMBRE 2026'!G34 -> 0 | D35: ='[1]SEPTIEMBRE 2026'!H34 -> 0 | E35: =SUM(C35,D35) -> 0 | G35: =B35 -> 46295 | H35: ='[2]SEPTIEMBRE 2026'!G34 -> 0 | I35: ='[2]SEPTIEMBRE 2026'!H34 -> 0 | J35: =SUM(H35,I35) -> 0 | L35: =G35 -> 46295 | M35: =[3]REACTIVOS!Z639 -> 0
B36: TOTAL | C36: =SUM(C6:C35) -> 532000 | D36: =SUM(D6:D35) -> 544000 | E36: =SUM(E6:E35) -> 1076000 | G36: TOTAL | H36: =SUM(H6:H35) -> 106075 | I36: =SUM(I6:I35) -> 107150 | J36: =SUM(J6:J35) -> 213225 | L36: TOTAL | M36: =SUM(M6:M35) -> 78000

Sheet Filtros de H20
D2: PROGRAMA DE LIMPIEZA DIARIA DE FILTROS DE H20 (CHOROS)
D4: MES: | E4: AGOSTO | F4: 2026
C6: N° | D6: FILTRO | E6: 46235 | I6: FILTRO | J6: 46267 | N6: 46268 | R6: 46269 | V6: FILTRO | W6: 46270 | AA6: 46271 | AE6: 46272
E7: 1 TURNO | F7: 2 TURNO | G7: 3 TURNO | H7: Observacion | J7: 1 TURNO | K7: 2 TURNO | L7: 3 TURNO | M7: Observacion | N7: 1 TURNO | O7: 2 TURNO | P7: 3 TURNO | Q7: Observacion | R7: 1 TURNO | S7: 2 TURNO | T7: 3 TURNO | U7: Observacion | W7: 1 TURNO | X7: 2 TURNO | Y7: 3 TURNO | Z7: Observacion | AA7: 1 TURNO | AB7: 2 TURNO | AC7: 3 TURNO | AD7: Observacion | AE7: 1 TURNO | AF7: 2 TURNO | AG7: 3 TURNO | AH7: Observacion
C8: 1 | D8: Filtro # 1 | F8: ✔ | I8: Filtro # 1 | O8: ✔ | T8: ✔ | V8: Filtro # 1 | X8: ✔ | AC8: ✔
C9: 2 | D9: Filtro # 2 | F9: ✔ | I9: Filtro # 2 | O9: ✔ | T9: ✔ | V9: Filtro # 2 | X9: ✔ | AC9: ✔
C10: 3 | D10: Filtro # 3 | F10: ✔ | I10: Filtro # 3 | O10: ✔ | T10: ✔ | V10: Filtro # 3 | X10: ✔ | AC10: ✔
C11: 4 | D11: Filtro # 4 | F11: ✖ | I11: Filtro # 4 | O11: ✖ | T11: ✖ | V11: Filtro # 4 | X11: ✖ | AC11: ✖
C12: 5 | D12: Filtro # 5 | F12: ✔ | I12: Filtro # 5 | O12: ✔ | T12: ✔ | V12: Filtro # 5 | X12: ✔ | AC12: ✔
C13: 6 | D13: Filtro Linea # 5 | F13: ✔ | I13: Filtro Linea # 5 | O13: ✔ | T13: ✔ | V13: Filtro Linea # 5 | X13: ✔ | AC13: ✔
C14: 7 | D14: Filtro Linea # 6 | F14: ✔ | I14: Filtro Linea # 6 | O14: ✔ | T14: ✔ | V14: Filtro Linea # 6 | X14: ✔ | AC14: ✔
C15: 8 | D15: Filtro Linea # 7 | F15: ✔ | I15: Filtro Linea # 7 | O15: ✔ | T15: ✔ | V15: Filtro Linea # 7 | X15: ✔ | AC15: ✔
C16: 9 | D16: Filtro Linea # 8 | F16: ✖ | I16: Filtro Linea # 8 | O16: ✖ | T16: ✖ | V16: Filtro Linea # 8 | X16: ✖ | AC16: ✖
C17: 10 | D17: Filtro Linea # 9 (01) | F17: ✔ | I17: Filtro Linea # 9 (01) | O17: ✔ | T17: ✔ | V17: Filtro Linea # 9 (01) | X17: ✔ | AC17: ✔
C18: 11 | D18: Filtro Linea # 9 (02) | F18: ✖ | I18: Filtro Linea # 9 (02) | O18: ✖ | T18: ✖ | V18: Filtro Linea # 9 (02) | X18: ✖ | AC18: ✖
D19: RESUMEN OPERACIONAL | I19: RESUMEN OPERACIONAL
D20: Filtros operativos: | F20: 8 | I20: Filtros operativos: | N20: Filtros operativos: | P20: 8 | R20: Filtros operativos: | T20: 8 | V20: Filtros operativos: | X20: 8 | AA20: Filtros operativos: | AC20: 8 | AE20: Filtros operativos:
D21: Filtros críticos: | F21: 3 | I21: Filtros críticos: | N21: Filtros críticos: | P21: 3 | R21: Filtros críticos: | T21: 3 | V21: Filtros críticos: | X21: 3 | AA21: Filtros críticos: | AC21: 3 | AE21: Filtros críticos:
D22: % CUMPLIMIENTO | F22: =F20/(F20+F21) -> 0.72727273 | I22: % CUMPLIMIENTO | N22: % CUMPLIMIENTO | P22: =+P20/11 -> 0.72727273 | R22: % CUMPLIMIENTO | T22: =+T20/11 -> 0.72727273 | V22: % CUMPLIMIENTO | X22: =+X20/11 -> 0.72727273 | AA22: % CUMPLIMIENTO | AC22: =+AC20/11 -> 0.72727273 | AE22: % CUMPLIMIENTO | AG22: =+AG20/11 -> 0
D23: Causa principal: Falla mecánica en válvulas | I23: Causa principal: Falla mecánica en válvulas | N23: Causa principal: Falla mecánica en válvulas | R23: Causa principal: Falla mecánica en válvulas | V23: Causa principal: Falla mecánica en válvulas | AA23: Causa principal: Falla mecánica en válvulas | AE23: Causa principal: Falla mecánica en válvulas
D24: Acción: Realizar mantenimiento correctivo | I24: Acción: Realizar mantenimiento correctivo | N24: Acción: Realizar mantenimiento correctivo | R24: Acción: Realizar mantenimiento correctivo | V24: Acción: Realizar mantenimiento correctivo | AA24: Acción: Realizar mantenimiento correctivo | AE24: Acción: Realizar mantenimiento correctivo
D25: Realizado por: | I25: Realizado por: | N25: Realizado por: BRIAN SALINAS | R25: Realizado por: Luis Bendezu | V25: Realizado por: Brian Salinas | AA25: Realizado por: Luis Bendezu | AE25: Realizado por:
C27: N° | D27: FILTRO | E27: 46273 | J27: 46274 | N27: 46275 | R27: 46276 | W27: 46277 | AA27: 46278 | AE27: 46279
E28: 1 TURNO | F28: 2 TURNO | G28: 3 TURNO | H28: Observacion | J28: 1 TURNO | K28: 2 TURNO | L28: 3 TURNO | M28: Observacion | N28: 1 TURNO | O28: 2 TURNO | P28: 3 TURNO | Q28: Observacion | R28: 1 TURNO | S28: 2 TURNO | T28: 3 TURNO | U28: Observacion | W28: 1 TURNO | X28: 2 TURNO | Y28: 3 TURNO | Z28: Observacion | AA28: 1 TURNO | AB28: 2 TURNO | AC28: 3 TURNO | AD28: Observacion | AE28: 1 TURNO | AF28: 2 TURNO | AG28: 3 TURNO | AH28: Observacion
C29: 1 | D29: Filtro # 1 | L29: ✔ | P29: ✔ | Z29: ✔ | AB29: ✔ | AG29: ✔
C30: 2 | D30: Filtro # 2 | L30: ✔ | P30: ✔ | Z30: ✔ | AB30: ✔ | AG30: ✔
C31: 3 | D31: Filtro # 3 | L31: ✔ | P31: ✔ | Z31: ✔ | AB31: ✔ | AG31: ✔
C32: 4 | D32: Filtro # 4 | L32: ✖ | P32: ✖ | Z32: ✖ | AB32: ✖ | AG32: ✖
C33: 5 | D33: Filtro # 5 | L33: ✔ | P33: ✔ | Z33: ✔ | AB33: ✔ | AG33: ✔
C34: 6 | D34: Filtro Linea # 5 | L34: ✔ | P34: ✔ | Z34: ✔ | AB34: ✔ | AG34: ✔
C35: 7 | D35: Filtro Linea # 6 | L35: ✔ | P35: ✔ | Z35: ✔ | AB35: ✔ | AG35: ✔
C36: 8 | D36: Filtro Linea # 7 | L36: ✔ | P36: ✔ | Z36: ✔ | AB36: ✔ | AG36: ✔
C37: 9 | D37: Filtro Linea # 8 | L37: ✖ | P37: ✖ | Z37: ✖ | AB37: ✖ | AG37: ✖
C38: 10 | D38: Filtro Linea # 9 (01) | L38: ✔ | P38: ✔ | Z38: ✔ | AB38: ✔ | AG38: ✔
C39: 11 | D39: Filtro Linea # 9 (02) | L39: ✖ | P39: ✖ | Z39: ✖ | AB39: ✖ | AG39: ✖
D40: RESUMEN OPERACIONAL
D41: Filtros operativos: | J41: Filtros operativos: | L41: 8 | N41: Filtros operativos: | P41: 8 | R41: Filtros operativos: | W41: Filtros operativos: | Y41: 8 | AA41: Filtros operativos: | AC41: 8 | AE41: Filtros operativos: | AG41: 8
D42: Filtros críticos: | J42: Filtros críticos: | L42: 3 | N42: Filtros críticos: | P42: 3 | R42: Filtros críticos: | W42: Filtros críticos: | Y42: 3 | AA42: Filtros críticos: | AC42: 3 | AE42: Filtros críticos: | AG42: 3
D43: % CUMPLIMIENTO | F43: =+F41/11 -> 0 | J43: % CUMPLIMIENTO | L43: =+L41/11 -> 0.72727273 | N43: % CUMPLIMIENTO | P43: =+P41/11 -> 0.72727273 | R43: % CUMPLIMIENTO | T43: =+T41/11 -> 0 | W43: % CUMPLIMIENTO | Y43: =+Y41/11 -> 0.72727273 | AA43: % CUMPLIMIENTO | AC43: =+AC41/11 -> 0.72727273 | AE43: % CUMPLIMIENTO | AG43: =+AG41/11 -> 0.72727273
D44: Causa principal: Falla mecánica en válvulas | J44: Causa principal: Falla mecánica en válvulas | N44: Causa principal: Falla mecánica en válvulas | R44: Causa principal: Falla mecánica en válvulas | W44: Causa principal: Falla mecánica en válvulas | AA44: Causa principal: Falla mecánica en válvulas | AE44: Causa principal: Falla mecánica en válvulas
D45: Acción: Realizar mantenimiento correctivo | J45: Acción: Realizar mantenimiento correctivo | N45: Acción: Realizar mantenimiento correctivo | R45: Acción: Realizar mantenimiento correctivo | W45: Acción: Realizar mantenimiento correctivo | AA45: Acción: Realizar mantenimiento correctivo | AE45: Acción: Realizar mantenimiento correctivo
D46: Realizado por:Luis Bendezu | J46: Realizado por: BRIAN SALINAS | N46: Realizado por: BRIAN SALINAS | R46: Realizado por: | W46: Realizado por: BRIAN SALINAS | AA46: Realizado por: Luis Bendezu | AE46: Realizado por: BRIAN SALINAS
C48: N° | D48: FILTRO | E48: 46280 | J48: 46281 | N48: 46282 | R48: 46283 | W48: 46284 | AA48: 46285 | AE48: 46286
E49: 1 TURNO | F49: 2 TURNO | G49: 3 TURNO | H49: Observacion | J49: 1 TURNO | K49: 2 TURNO | L49: 3 TURNO | M49: Observacion | N49: 1 TURNO | O49: 2 TURNO | P49: 3 TURNO | Q49: Observacion | R49: 1 TURNO | S49: 2 TURNO | T49: 3 TURNO | U49: Observacion | W49: 1 TURNO | X49: 2 TURNO | Y49: 3 TURNO | Z49: Observacion | AA49: 1 TURNO | AB49: 2 TURNO | AC49: 3 TURNO | AD49: Observacion | AE49: 1 TURNO | AF49: 2 TURNO | AG49: 3 TURNO | AH49: Observacion
C50: 1 | D50: Filtro # 1 | F50: ✔ | G50: ✔ | S50: ✔ | AF50: ✔
C51: 2 | D51: Filtro # 2 | F51: ✔ | G51: ✔ | S51: ✔ | AF51: ✔
C52: 3 | D52: Filtro # 3 | F52: ✔ | G52: ✔ | S52: ✔ | AF52: ✔
C53: 4 | D53: Filtro # 4 | F53: ✖ | G53: ✖ | S53: ✖ | AF53: ✖
C54: 5 | D54: Filtro # 5 | F54: ✔ | G54: ✔ | S54: ✔ | AF54: ✔
C55: 6 | D55: Filtro Linea # 5 | F55: ✔ | G55: ✔ | S55: ✔ | AF55: ✔
C56: 7 | D56: Filtro Linea # 6 | F56: ✔ | G56: ✔ | S56: ✔ | AF56: ✔
C57: 8 | D57: Filtro Linea # 7 | F57: ✖ | G57: ✖ | S57: ✖ | AF57: ✖
C58: 9 | D58: Filtro Linea # 8 | F58: ✖ | G58: ✖ | S58: ✖ | AF58: ✖
C59: 10 | D59: Filtro Linea # 9 (01) | F59: ✔ | G59: ✔ | S59: ✔ | AF59: ✔
C60: 11 | D60: Filtro Linea # 9 (02) | F60: ✖ | G60: ✖ | S60: ✖ | AF60: ✖
D61: RESUMEN OPERACIONAL | R61: RESUMEN OPERACIONAL
D62: Filtros operativos: | F62: 7 | J62: Filtros operativos: | N62: Filtros operativos: | P62: 9 | R62: Filtros operativos: | T62: 7 | W62: Filtros operativos: | Y62: 9 | AA62: Filtros operativos: | AE62: Filtros operativos: | AG62: 7
D63: Filtros críticos: | F63: 4 | J63: Filtros críticos: | N63: Filtros críticos: | P63: 2 | R63: Filtros críticos: | T63: 4 | W63: Filtros críticos: | Y63: 2 | AA63: Filtros críticos: | AE63: Filtros críticos: | AG63: 4
D64: % CUMPLIMIENTO | F64: =+F62/11 -> 0.63636364 | J64: % CUMPLIMIENTO | L64: =+L62/11 -> 0 | N64: % CUMPLIMIENTO | P64: =+P62/11 -> 0.81818182 | R64: % CUMPLIMIENTO | T64: =+T62/11 -> 0.63636364 | W64: % CUMPLIMIENTO | Y64: =+Y62/11 -> 0.81818182 | AA64: % CUMPLIMIENTO | AC64: =+AC62/11 -> 0 | AE64: % CUMPLIMIENTO | AG64: =+AG62/11 -> 0.63636364
D65: Causa principal: Falla mecánica en válvulas | J65: Causa principal: Falla mecánica en válvulas | N65: Causa principal: Falla mecánica en válvulas | R65: Causa principal: Falla mecánica en válvulas | W65: Causa principal: Falla mecánica en válvulas | AA65: Causa principal: Falla mecánica en válvulas | AE65: Causa principal: Falla mecánica en válvulas
D66: Acción: Realizar mantenimiento correctivo | J66: Acción: Realizar mantenimiento correctivo | N66: Acción: Realizar mantenimiento correctivo | R66: Acción: Realizar mantenimiento correctivo | W66: Acción: Realizar mantenimiento correctivo | AA66: Acción: Realizar mantenimiento correctivo | AE66: Acción: Realizar mantenimiento correctivo
D67: Realizado por: Luis Bendezu /Brian Salinas | J67: Realizado por: | N67: Realizado por: BRIAN SALINAS | R67: Realizado por: BRIAN SALINAS | W67: Realizado por: BRIAN SALINAS | AA67: Realizado por: | AE67: Realizado por: BRIAN SALINAS
C70: N° | D70: FILTRO | E70: 46287 | I70: FILTRO | J70: 46288 | N70: 46289 | R70: 46290 | W70: 46291 | AA70: 46292 | AE70: 46293
E71: 1 TURNO | F71: 2 TURNO | G71: 3 TURNO | H71: Observacion | J71: 1 TURNO | K71: 2 TURNO | L71: 3 TURNO | M71: Observacion | N71: 1 TURNO | O71: 2 TURNO | P71: 3 TURNO | Q71: Observacion | R71: 1 TURNO | S71: 2 TURNO | T71: 3 TURNO | U71: Observacion | W71: 1 TURNO | X71: 2 TURNO | Y71: 3 TURNO | Z71: Observacion | AA71: 1 TURNO | AB71: 2 TURNO | AC71: 3 TURNO | AD71: Observacion | AE71: 1 TURNO | AF71: 2 TURNO | AG71: 3 TURNO | AH71: Observacion
C72: 1 | D72: Filtro # 1 | F72: ✔ | G72: ✔ | I72: Filtro # 1 | L72: ✔ | P72: ✔ | S72: ✔ | T72: ✔ | V72: Filtro # 1 | Y72: ✔ | Z72: ✔ | AB72: ✔ | AC72: ✔ | AG72: ✔
C73: 2 | D73: Filtro # 2 | F73: ✔ | G73: ✔ | I73: Filtro # 2 | L73: ✔ | P73: ✔ | S73: ✔ | T73: ✔ | V73: Filtro # 2 | Y73: ✔ | Z73: ✔ | AB73: ✔ | AC73: ✔ | AG73: ✔
C74: 3 | D74: Filtro # 3 | F74: ✔ | G74: ✔ | I74: Filtro # 3 | L74: ✔ | P74: ✔ | S74: ✔ | T74: ✔ | V74: Filtro # 3 | Y74: ✔ | Z74: ✔ | AB74: ✔ | AC74: ✔ | AG74: ✔
C75: 4 | D75: Filtro # 4 | F75: ✖ | G75: ✖ | I75: Filtro # 4 | L75: ✖ | P75: ✖ | S75: ✖ | T75: ✖ | V75: Filtro # 4 | Y75: ✖ | Z75: ✖ | AB75: ✖ | AC75: ✖ | AG75: ✖
C76: 5 | D76: Filtro # 5 | F76: ✔ | G76: ✔ | I76: Filtro # 5 | L76: ✔ | P76: ✔ | S76: ✔ | T76: ✔ | V76: Filtro # 5 | Y76: ✔ | Z76: ✔ | AB76: ✔ | AC76: ✔ | AG76: ✔
C77: 6 | D77: Filtro Linea # 5 | F77: ✔ | G77: ✔ | I77: Filtro Linea # 5 | L77: ✔ | P77: ✔ | S77: ✔ | T77: ✔ | V77: Filtro Linea # 5 | Y77: ✔ | Z77: ✔ | AB77: ✔ | AC77: ✔ | AG77: ✔
C78: 7 | D78: Filtro Linea # 6 | F78: ✔ | G78: ✔ | I78: Filtro Linea # 6 | L78: ✔ | P78: ✔ | S78: ✔ | T78: ✔ | V78: Filtro Linea # 6 | Y78: ✔ | Z78: ✔ | AB78: ✔ | AC78: ✔ | AG78: ✔
C79: 8 | D79: Filtro Linea # 7 | F79: ✖ | G79: ✔ | I79: Filtro Linea # 7 | L79: ✔ | P79: ✔ | S79: ✔ | T79: ✔ | V79: Filtro Linea # 7 | Y79: ✔ | Z79: ✔ | AB79: ✖ | AC79: ✔ | AG79: ✔
C80: 9 | D80: Filtro Linea # 8 | F80: ✖ | G80: ✖ | I80: Filtro Linea # 8 | L80: ✖ | P80: ✖ | S80: ✖ | T80: ✖ | V80: Filtro Linea # 8 | Y80: ✖ | Z80: ✖ | AB80: ✖ | AC80: ✖ | AG80: ✖
C81: 10 | D81: Filtro Linea # 9 (01) | F81: ✔ | G81: ✔ | I81: Filtro Linea # 9 (01) | L81: ✔ | P81: ✔ | S81: ✔ | T81: ✔ | V81: Filtro Linea # 9 (01) | Y81: ✔ | Z81: ✔ | AB81: ✔ | AC81: ✔ | AG81: ✔
C82: 11 | D82: Filtro Linea # 9 (02) | F82: ✖ | G82: ✖ | I82: Filtro Linea # 9 (02) | L82: ✖ | P82: ✖ | S82: ✖ | T82: ✖ | V82: Filtro Linea # 9 (02) | Y82: ✖ | Z82: ✖ | AB82: ✖ | AC82: ✖ | AG82: ✖
D83: RESUMEN OPERACIONAL
D84: Filtros operativos: | F84: 7 | J84: Filtros operativos: | L84: 7 | N84: Filtros operativos: | P84: 7 | R84: Filtros operativos: | T84: 8 | W84: Filtros operativos: | Y84: 8 | AA84: Filtros operativos: | AC84: 8 | AE84: Filtros operativos: | AG84: 8
D85: Filtros críticos: | F85: 4 | J85: Filtros críticos: | L85: 4 | N85: Filtros críticos: | P85: 4 | R85: Filtros críticos: | T85: 3 | W85: Filtros críticos: | Y85: 3 | AA85: Filtros críticos: | AC85: 3 | AE85: Filtros críticos: | AG85: 3
D86: % CUMPLIMIENTO | F86: =+F84/11 -> 0.63636364 | J86: % CUMPLIMIENTO | L86: =+L84/11 -> 0.63636364 | N86: % CUMPLIMIENTO | P86: =+P84/11 -> 0.63636364 | R86: % CUMPLIMIENTO | T86: =+T84/11 -> 0.72727273 | W86: % CUMPLIMIENTO | Y86: =+Y84/11 -> 0.72727273 | AA86: % CUMPLIMIENTO | AC86: =+AC84/11 -> 0.72727273 | AE86: % CUMPLIMIENTO | AG86: =+AG84/11 -> 0.72727273
D87: Causa principal: Falla mecánica en válvulas | J87: Causa principal: Falla mecánica en válvulas | N87: Causa principal: Falla mecánica en válvulas | R87: Causa principal: Falla mecánica en válvulas | W87: Causa principal: Falla mecánica en válvulas | AA87: Causa principal: Falla mecánica en válvulas | AE87: Causa principal: Falla mecánica en válvulas
D88: Acción: Realizar mantenimiento correctivo | J88: Acción: Realizar mantenimiento correctivo | N88: Acción: Realizar mantenimiento correctivo | R88: Acción: Realizar mantenimiento correctivo | W88: Acción: Realizar mantenimiento correctivo | AA88: Acción: Realizar mantenimiento correctivo | AE88: Acción: Realizar mantenimiento correctivo
D89: Realizado por: BRIAN SALINAS/L. Bendezu | J89: Realizado por: Luis Bendezu | N89: Realizado por: BRIAN SALINAS | R89: Realizado por: Luis Bendezu / Brian Salinas | W89: Realizado por: Luis Bendezu / Brian Salinas | AA89: Realizado por: BRIAN SALINAS | AE89: Realizado por: BRIAN SALINAS
C92: N° | D92: FILTRO | E92: 46294 | J92: 46264 | N92: 46265
E93: 1 TURNO | F93: 2 TURNO | G93: 3 TURNO | H93: Observacion | J93: 1 TURNO | K93: 2 TURNO | L93: 3 TURNO | M93: Observacion | N93: 1 TURNO | O93: 2 TURNO | P93: 3 TURNO | Q93: Observacion
C94: 1 | D94: Filtro # 1 | G94: ✔
C95: 2 | D95: Filtro # 2 | G95: ✔
C96: 3 | D96: Filtro # 3 | G96: ✔
C97: 4 | D97: Filtro # 4 | G97: ✖
C98: 5 | D98: Filtro # 5 | G98: ✔
C99: 6 | D99: Filtro Linea # 5 | G99: ✔
C100: 7 | D100: Filtro Linea # 6 | G100: ✔
C101: 8 | D101: Filtro Linea # 7 | G101: ✔
C102: 9 | D102: Filtro Linea # 8 | G102: ✖
C103: 10 | D103: Filtro Linea # 9 (01) | G103: ✔
C104: 11 | D104: Filtro Linea # 9 (02) | G104: ✖
D105: RESUMEN OPERACIONAL
D106: Filtros operativos: | F106: 8 | J106: Filtros operativos: | N106: Filtros operativos:
D107: Filtros críticos: | F107: 3 | J107: Filtros críticos: | N107: Filtros críticos:
D108: % CUMPLIMIENTO | F108: =+F106/11 -> 0.72727273 | J108: % CUMPLIMIENTO | L108: =+L106/11 -> 0 | N108: % CUMPLIMIENTO | P108: =+P106/11 -> 0
D109: Causa principal: Falla mecánica en válvulas | J109: Causa principal: Falla mecánica en válvulas | N109: Causa principal: Falla mecánica en válvulas
...

Sheet CONTROL PURGA TKS AIRE 
B1: PURGA TANQUES DE AIRE COMPRIMIDO-PLANTA MAGNETICA
B3: MES: | C3: SETIEMBRE
D4: 46275 | G4: 46276 | J4: 46277 | M4: 46278
A5: I.- | B5: ID. TK. PRINCIPAL | C5: UBICACIÓN | D5: 1er Turno | E5: 2do Turno | F5: 3er Turno | G5: 1er Turno | H5: 2do Turno | I5: 3er Turno | J5: 1er Turno | K5: 2do Turno | L5: 3er Turno | M5: 1er Turno | N5: 2do Turno | O5: 3er Turno
B6: TK-MG-S. ROTULO | C6: Linea 1 | E6: ✔ | F6: ✔ | H6: ✔ | I6: ✔ | L6: ✔ | M6: ✔ | O6: ✔
B7: TK-MG-001 | C7: Linea 5 | E7: ✔ | F7: ✔ | H7: ✔ | I7: ✔ | L7: ✔ | M7: ✔ | O7: ✔
B8: TK-MG-002 | C8: Linea 8 | E8: ✔ | F8: ✔ | H8: ✔ | I8: ✔ | L8: ✔ | M8: ✔ | O8: ✔
B9: TK-MG-003 | C9: Linea 10 | E9: ✔ | F9: ✔ | H9: ✔ | I9: ✔ | L9: ✔ | M9: ✔ | O9: ✔
B10: TK-MG-005 | C10: Linea 7 | E10: X | F10: X | H10: X | I10: X | L10: X | M10: X | O10: X
B11: TK-MG-006 | C11: Linea 8 | E11: ✔ | F11: ✔ | H11: ✔ | I11: ✔ | L11: ✔ | M11: ✔ | O11: ✔
A12: II.- | B12: ID. TK. AUXILIARES | C12: UBICACIÓN
B13: TK-MG-007 | C13: MB-1 | E13: ✔ | F13: ✔ | H13: ✔ | I13: ✔ | L13: ✔ | M13: ✔ | O13: ✔
B14: TK-MG-004 | C14: MB-4 | E14: ✔ | F14: ✔ | H14: ✔ | I14: ✔ | L14: ✔ | M14: ✔ | O14: ✔
B15: TK-MG-008 | C15: MB-5 | E15: ✔ | F15: ✔ | H15: ✔ | I15: ✔ | L15: ✔ | M15: ✔ | O15: ✔
B16: TK-MG-009 | C16: MB-6 | E16: ✔ | F16: ✔ | H16: ✔ | I16: ✔ | L16: ✔ | M16: ✔ | O16: ✔
B17: TK-MG-010 | C17: MB-7 | E17: ✔ | F17: ✔ | H17: ✔ | I17: ✔ | L17: ✔ | M17: ✔ | O17: ✔
B18: TK-MG-011 | C18: MB-8 | E18: ✔ | F18: ✔ | H18: ✔ | I18: ✔ | L18: ✔ | M18: ✔ | O18: ✔
B19: TK-MG-012 | C19: MB-9 | E19: ✔ | F19: ✔ | H19: ✔ | I19: ✔ | L19: ✔ | M19: ✔ | O19: ✔
B20: TK-MG-013 | C20: RM-9 | E20: ✔ | F20: ✔ | H20: ✔ | I20: ✔ | L20: ✔ | M20: ✔ | O20: ✔
B21: TK-MG-014 | C21: MB-10 | E21: ✔ | F21: ✔ | H21: ✔ | I21: ✔ | L21: ✔ | M21: ✔ | O21: ✔
B23: * La purga de los tanques se realizara al inicio de cada guardia.
D26: 46279 | G26: 46280 | J26: 46281 | M26: 46282 | P26: 46283 | S26: 46284 | V26: 46285
A27: I.- | B27: ID. TK. PRINCIPAL | C27: UBICACIÓN | D27: 1er Turno | E27: 2do Turno | F27: 3er Turno | G27: 1er Turno | H27: 2do Turno | I27: 3er Turno | J27: 1er Turno | K27: 2do Turno | L27: 3er Turno | M27: 1er Turno | N27: 2do Turno | O27: 3er Turno | P27: 1er Turno | Q27: 2do Turno | R27: 3er Turno | S27: 1er Turno | T27: 2do Turno | U27: 3er Turno | V27: 1er Turno | W27: 2do Turno | X27: 3er Turno
A28: 1 | B28: TK-MG-S. ROTULO | C28: Linea 1 | E28: ✔ | F28: ✔ | H28: ✔ | I28: ✔ | L28: ✔ | O28: ✔ | Q28: ✔ | R28: ✔ | T28: ✔ | U28: ✔ | V28: ✔
A29: 2 | B29: TK-MG-001 | C29: Linea 5 | E29: ✔ | F29: ✔ | H29: ✔ | I29: ✔ | L29: ✔ | O29: ✔ | Q29: ✔ | R29: ✔ | T29: ✔ | U29: ✔ | V29: ✔
A30: 3 | B30: TK-MG-002 | C30: Linea 8 | E30: ✔ | F30: ✔ | H30: ✔ | I30: ✔ | L30: ✔ | O30: ✔ | Q30: ✔ | R30: ✔ | T30: ✔ | U30: ✔ | V30: ✔
A31: 4 | B31: TK-MG-003 | C31: Linea 10 | E31: ✔ | F31: ✔ | H31: ✔ | I31: ✔ | L31: ✔ | O31: ✔ | Q31: ✔ | R31: ✔ | T31: ✔ | U31: ✔ | V31: ✔
A32: 5 | B32: TK-MG-005 | C32: Linea 7 | E32: X | F32: X | H32: X | I32: X | L32: X | O32: X | Q32: X | R32: X | T32: X | U32: X | V32: X
A33: 6 | B33: TK-MG-006 | C33: Linea 8 | E33: ✔ | F33: ✔ | H33: ✔ | I33: ✔ | L33: ✔ | O33: ✔ | Q33: ✔ | R33: ✔ | T33: ✔ | U33: ✔ | V33: ✔
A34: II.- | B34: ID. TK. AUXILIARES | C34: UBICACIÓN
A35: 1 | B35: TK-MG-007 | C35: MB-1 | E35: ✔ | F35: ✔ | H35: ✔ | I35: ✔ | L35: ✔ | O35: ✔ | Q35: ✔ | R35: ✔ | T35: ✔ | U35: ✔ | V35: ✔
A36: 2 | B36: TK-MG-004 | C36: MB-4 | E36: ✔ | F36: ✔ | H36: ✔ | I36: ✔ | L36: ✔ | O36: ✔ | Q36: ✔ | R36: ✔ | T36: ✔ | U36: ✔ | V36: ✔
A37: 3 | B37: TK-MG-008 | C37: MB-5 | E37: ✔ | F37: ✔ | H37: ✔ | I37: ✔ | L37: ✔ | O37: ✔ | Q37: ✔ | R37: ✔ | T37: ✔ | U37: ✔ | V37: ✔
A38: 4 | B38: TK-MG-009 | C38: MB-6 | E38: ✔ | F38: ✔ | H38: ✔ | I38: ✔ | L38: ✔ | O38: ✔ | Q38: ✔ | R38: ✔ | T38: ✔ | U38: ✔ | V38: ✔
A39: 5 | B39: TK-MG-010 | C39: MB-7 | E39: ✔ | F39: ✔ | H39: ✔ | I39: ✔ | L39: ✔ | O39: ✔ | Q39: ✔ | R39: ✔ | T39: ✔ | U39: ✔ | V39: ✔
A40: 6 | B40: TK-MG-011 | C40: MB-8 | E40: ✔ | F40: ✔ | H40: ✔ | I40: ✔ | L40: ✔ | O40: ✔ | Q40: ✔ | R40: ✔ | T40: ✔ | U40: ✔ | V40: ✔
A41: 7 | B41: TK-MG-012 | C41: MB-9 | E41: ✔ | F41: ✔ | H41: ✔ | I41: ✔ | L41: ✔ | O41: ✔ | Q41: ✔ | R41: ✔ | T41: ✔ | U41: ✔ | V41: ✔
A42: 8 | B42: TK-MG-013 | C42: RM-9 | E42: ✔ | F42: ✔ | H42: ✔ | I42: ✔ | L42: ✔ | O42: ✔ | Q42: ✔ | R42: ✔ | T42: ✔ | U42: ✔ | V42: ✔
A43: 9 | B43: TK-MG-014 | C43: MB-10 | E43: ✔ | F43: ✔ | H43: ✔ | I43: ✔ | L43: ✔ | O43: ✔ | Q43: ✔ | R43: ✔ | T43: ✔ | U43: ✔ | V43: ✔
D46: 46286 | G46: 46287 | J46: 46288 | M46: 46289 | P46: 46290 | S46: 46291 | V46: 46292
A47: I.- | B47: ID. TK. PRINCIPAL | C47: UBICACIÓN | D47: 1er Turno | E47: 2do Turno | F47: 3er Turno | G47: 1er Turno | H47: 2do Turno | I47: 3er Turno | J47: 1er Turno | K47: 2do Turno | L47: 3er Turno | M47: 1er Turno | N47: 2do Turno | O47: 3er Turno | P47: 1er Turno | Q47: 2do Turno | R47: 3er Turno | S47: 1er Turno | T47: 2do Turno | U47: 3er Turno | V47: 1er Turno | W47: 2do Turno | X47: 3er Turno
B48: TK-MG-S. ROTULO | C48: Linea 1 | E48: ✔ | H48: ✔ | L48: ✔ | O48: ✔ | Q48: ✔ | R48: ✔ | T48: ✔ | U48: ✔ | V48: ✔ | X48: ✔
B49: TK-MG-001 | C49: Linea 5 | E49: ✔ | H49: ✔ | L49: ✔ | O49: ✔ | Q49: ✔ | R49: ✔ | T49: ✔ | U49: ✔ | V49: ✔ | X49: ✔
B50: TK-MG-002 | C50: Linea 8 | E50: ✔ | H50: ✔ | L50: ✔ | O50: ✔ | Q50: ✔ | R50: ✔ | T50: ✔ | U50: ✔ | V50: ✔ | X50: ✔
B51: TK-MG-003 | C51: Linea 10 | E51: ✔ | H51: ✔ | L51: ✔ | O51: ✔ | Q51: ✔ | R51: ✔ | T51: ✔ | U51: ✔ | V51: ✔ | X51: ✔
B52: TK-MG-005 | C52: Linea 7 | E52: X | H52: X | L52: X | O52: X | Q52: X | R52: X | T52: X | U52: X | V52: X | X52: X
B53: TK-MG-006 | C53: Linea 8 | E53: ✔ | H53: ✔ | L53: ✔ | O53: ✔ | Q53: ✔ | R53: ✔ | T53: ✔ | U53: ✔ | V53: ✔ | X53: ✔
A54: II.- | B54: ID. TK. AUXILIARES | C54: UBICACIÓN
B55: TK-MG-007 | C55: MB-1 | E55: ✔ | H55: ✔ | L55: ✔ | O55: ✔ | Q55: ✔ | R55: ✔ | T55: ✔ | U55: ✔ | V55: ✔ | X55: ✔
B56: TK-MG-04 | C56: MB-4 | E56: ✔ | H56: ✔ | L56: ✔ | O56: ✔ | Q56: ✔ | R56: ✔ | T56: ✔ | U56: ✔ | V56: ✔ | X56: ✔
B57: TK-MG-008 | C57: MB-5 | E57: ✔ | H57: ✔ | L57: ✔ | O57: ✔ | Q57: ✔ | R57: ✔ | T57: ✔ | U57: ✔ | V57: ✔ | X57: ✔
B58: TK-MG-009 | C58: MB-6 | E58: ✔ | H58: ✔ | L58: ✔ | O58: ✔ | Q58: ✔ | R58: ✔ | T58: ✔ | U58: ✔ | V58: ✔ | X58: ✔
B59: TK-MG-010 | C59: MB-7 | E59: ✔ | H59: ✔ | L59: ✔ | O59: ✔ | Q59: ✔ | R59: ✔ | T59: ✔ | U59: ✔ | V59: ✔ | X59: ✔
B60: TK-MG-011 | C60: MB-8 | E60: ✔ | H60: ✔ | L60: ✔ | O60: ✔ | Q60: ✔ | R60: ✔ | T60: ✔ | U60: ✔ | V60: ✔ | X60: ✔
B61: TK-MG-012 | C61: MB-9 | E61: ✔ | H61: ✔ | L61: ✔ | O61: ✔ | Q61: ✔ | R61: ✔ | T61: ✔ | U61: ✔ | V61: ✔ | X61: ✔
B62: TK-MG-013 | C62: RM-9 | E62: ✔ | H62: ✔ | L62: ✔ | O62: ✔ | Q62: ✔ | R62: ✔ | T62: ✔ | U62: ✔ | V62: ✔ | X62: ✔
B63: TK-MG-014 | C63: MB-10 | E63: ✔ | H63: ✔ | L63: ✔ | O63: ✔ | Q63: ✔ | R63: ✔ | T63: ✔ | U63: ✔ | V63: ✔ | X63: ✔
D67: 46293 | G67: 46294 | J67: 46295
A68: I.- | B68: ID. TK. PRINCIPAL | C68: UBICACIÓN | D68: 1er Turno | E68: 2do Turno | F68: 3er Turno | G68: 1er Turno | H68: 2do Turno | I68: 3er Turno | J68: 1er Turno | K68: 2do Turno | L68: 3er Turno
B69: TK-MG-S. ROTULO | C69: Linea 1 | E69: ✔ | F69: ✔ | I69: ✔
B70: TK-MG-001 | C70: Linea 5 | E70: ✔ | F70: ✔ | I70: ✔
B71: TK-MG-002 | C71: Linea 8 | E71: ✔ | F71: ✔ | I71: ✔
B72: TK-MG-003 | C72: Linea 10 | E72: ✔ | F72: ✔ | I72: ✔
B73: TK-MG-005 | C73: Linea 7 | E73: X | F73: X | I73: X
B74: TK-MG-006 | C74: Linea 8 | E74: ✔ | F74: ✔ | I74: ✔
A75: II.- | B75: ID. TK. AUXILIARES | C75: UBICACIÓN
B76: TK-MG-007 | C76: MB-1 | E76: ✔ | F76: ✔ | I76: ✔
B77: TK-MG-04 | C77: MB-4 | E77: ✔ | F77: ✔ | I77: ✔
B78: TK-MG-008 | C78: MB-5 | E78: ✔ | F78: ✔ | I78: ✔
B79: TK-MG-009 | C79: MB-6 | E79: ✔ | F79: ✔ | I79: ✔
B80: TK-MG-010 | C80: MB-7 | E80: ✔ | F80: ✔ | I80: ✔
B81: TK-MG-011 | C81: MB-8 | E81: ✔ | F81: ✔ | I81: ✔
B82: TK-MG-012 | C82: MB-9 | E82: ✔ | F82: ✔ | I82: ✔
B83: TK-MG-013 | C83: RM-9 | E83: ✔ | F83: ✔ | I83: ✔
B84: TK-MG-014 | C84: MB-10 | E84: ✔ | F84: ✔ | I84: ✔

Sheet LIMPIEZA SEP.MAG. COBBER
B1: CONTROL DE CUMPLIMIENTO DE LIMPIEZA INTERDIARIO DE CAJON DE ALIMENTACION – SEPARADOR MAGNETICO COBBER
B2: MES | C2: AGOSTO | D2: 2026
B3: Fecha | C3: DIA | D3: Turno | E3: 210-097 | F3: 210-098 | G3: 210-099 | H3: 210-100 | I3: 210-114 | J3: 210-115 | K3: 210-101 | L3: 210-102 | M3: 210-103 | N3: 210-104 | O3: 210-105 | P3: 210-106 | Q3: 210-107 | R3: 210-108 | S3: 210-268 | T3: 210-269 | U3: Ejecutados | V3: No ejecutados | W3: Cumplimiento | X3: Estado | Y3: Observacion
B4: 46030 | C4: Sabado | D4: 1° Turno | U4: 0 | V4: 16 | W4: 0 | X4: DEFICIENTE
B5: 46061 | C5: Domingo | D5: 1° Turno | U5: 8 | V5: 8 | W5: 0.5 | X5: DEFICIENTE
B6: 46089 | C6: Lunes | D6: 1° Turno | U6: 0 | V6: 16 | W6: 0 | X6: DEFICIENTE
B7: 46120 | C7: Martes | D7: 1° Turno | U7: 12 | V7: 4 | W7: =+U7/16 -> 0.75
B8: 46150 | C8: Miercoles | D8: 1° Turno | U8: 0 | V8: 16 | W8: 0 | X8: DEFICIENTE
B9: 46181 | C9: Jueves | D9: 1° Turno | U9: 0 | V9: 16 | W9: 0 | X9: DEFICIENTE
B10: 46211 | C10: Viernes | D10: 1° Turno | U10: 13 | V10: 3 | W10: =+U10/16 -> 0.8125
B11: 46242 | C11: Sabado | D11: 1° Turno | U11: 0 | V11: 16 | W11: 0 | X11: DEFICIENTE
B12: 46273 | C12: Domingo | D12: 1° Turno | U12: 0 | V12: 16 | W12: 0 | X12: DEFICIENTE
B13: 46303 | C13: Lunes | D13: 1° Turno | U13: 13 | V13: 3 | W13: =+U13/16 -> 0.8125
B14: 46334 | C14: Martes | D14: 1° Turno | U14: 0 | V14: 16 | W14: =+U14/16 -> 0 | X14: DEFICIENTE
B15: 46364 | C15: Miercoles | D15: 1° Turno | U15: 0 | V15: 16 | W15: 0 | X15: DEFICIENTE
B16: 13/8/2027 | C16: Jueves | D16: 1° Turno | U16: 13 | V16: 3 | W16: =+U16/16 -> 0.8125
B17: 14/8/2027 | C17: Viernes | D17: 1° Turno | U17: 0 | V17: 16 | W17: =+U17/16 -> 0 | X17: DEFICIENTE
B18: 15/8/2027 | C18: Sabado | D18: 1° Turno | U18: 0 | V18: 16 | W18: 0 | X18: DEFICIENTE
B19: 16/8/2027 | C19: Domingo | D19: 1° Turno | U19: 3 | V19: 13 | W19: =+U19/16 -> 0.1875 | X19: DEFICIENTE
B20: 17/8/2027 | C20: Lunes | D20: 1° Turno | U20: 0 | V20: 16 | W20: =+U20/16 -> 0 | X20: DEFICIENTE
B21: 18/8/2027 | C21: Martes | D21: 1° Turno | U21: 0 | V21: 16 | W21: =+U21/16 -> 0 | X21: DEFICIENTE
B22: 19/8/2027 | C22: Miercoles | D22: 1° Turno | U22: 0 | V22: 16 | W22: =+U22/16 -> 0 | X22: DEFICIENTE
B23: 20/8/2027 | C23: Jueves | D23: 1° Turno | U23: 14 | V23: 2 | W23: =+U23/16 -> 0.875
B24: 21/8/2027 | C24: Viernes | D24: 1° Turno | U24: 0 | V24: 16 | W24: =+U24/16 -> 0 | X24: DEFICIENTE
B25: 22/8/2028 | C25: Sabado | D25: 1° Turno | U25: 14 | V25: =16-U25 -> 2 | W25: =+U25/16 -> 0.875
B26: 23/8/2028 | C26: Domingo | D26: 2° Turno | U26: 0 | V26: 0 | W26: 0 | X26: DEFICIENTE
B27: 24/8/2028 | C27: Lunes | D27: 1° Turno
B28: 25/8/2028 | C28: Martes | D28: 1° Turno
B29: 26/8/2028 | C29: Miercoles | D29: 1° Turno
B30: 27/8/2027 | C30: Jueves | D30: 1° Turno
B31: 28/8/2027 | C31: Viernes | D31: 1° Turno
B32: 29/8/2028 | C32: Sabado | D32: 1° Turno
B33: 30/8/2028 | C33: Domingo | D33: 1° Turno
B34: 31/8/2028 | C34: Lunes | D34: 1° Turno

Sheet TONELADAS X TURNO
B1: Molino barras 1 | E1: Molino barras 2 | H1: Molino barras 3 | K1: Molino barras 4 | N1: Molino barras 5 | Q1: Molino barras 6 | T1: Molino barras 7 | W1: Molino barras 8 | Z1: Molino barras 9
A2: Fecha | B2: 1° turno | C2: 2° turno | D2: 3° turno | E2: 1° turno | F2: 2° turno | G2: 3° turno | H2: 1° turno | I2: 2° turno | J2: 3° turno | K2: 1° turno | L2: 2° turno | M2: 3° turno | N2: 1° turno | O2: 2° turno | P2: 3° turno | Q2: 1° turno | R2: 2° turno | S2: 3° turno | T2: 1° turno | U2: 2° turno | V2: 3° turno | W2: 1° turno | X2: 2° turno | Y2: 3° turno | Z2: 1° turno | AA2: 2° turno | AB2: 3° turno
A3: 46266 | B3: ='[4]MOLINOS DE BARRAS'!C7 -> 495 | C3: ='[4]MOLINOS DE BARRAS'!D7 -> 156 | D3: ='[4]MOLINOS DE BARRAS'!E7 -> 1554 | E3: ='[4]MOLINOS DE BARRAS'!I7 -> 1230 | F3: ='[4]MOLINOS DE BARRAS'!J7 -> 1170 | G3: ='[4]MOLINOS DE BARRAS'!K7 -> 0 | H3: ='[4]MOLINOS DE BARRAS'!O7 -> 1620 | I3: ='[4]MOLINOS DE BARRAS'!P7 -> 1370 | J3: ='[4]MOLINOS DE BARRAS'!Q7 -> 1540 | K3: ='[4]MOLINOS DE BARRAS'!U7 -> 1306 | L3: ='[4]MOLINOS DE BARRAS'!V7 -> 1051 | M3: ='[4]MOLINOS DE BARRAS'!W7 -> 1186 | N3: ='[4]MOLINOS DE BARRAS'!AA7 -> 1566 | O3: ='[4]MOLINOS DE BARRAS'!AB7 -> 1581 | P3: ='[4]MOLINOS DE BARRAS'!AC7 -> 1568 | Q3: ='[4]MOLINOS DE BARRAS'!AG7 -> 1582 | R3: ='[4]MOLINOS DE BARRAS'!AH7 -> 1648 | S3: ='[4]MOLINOS DE BARRAS'!AI7 -> 1482 | T3: ='[4]MOLINOS DE BARRAS'!AM7 -> 1532 | U3: ='[4]MOLINOS DE BARRAS'!AN7 -> 1618 | V3: ='[4]MOLINOS DE BARRAS'!AO7 -> 1573 | W3: ='[4]MOLINOS DE BARRAS'!AS7 -> 1573 | X3: ='[4]MOLINOS DE BARRAS'!AT7 -> 1719 | Y3: ='[4]MOLINOS DE BARRAS'!AU7 -> 1519 | Z3: ='[4]MOLINOS DE BARRAS'!AY7 -> 2010 | AA3: ='[4]MOLINOS DE BARRAS'!AZ7 -> 1680 | AB3: ='[4]MOLINOS DE BARRAS'!BA7 -> 1883
A4: 46267 | B4: ='[4]MOLINOS DE BARRAS'!C8 -> 1671 | C4: ='[4]MOLINOS DE BARRAS'!D8 -> 1469 | D4: ='[4]MOLINOS DE BARRAS'!E8 -> 1412 | E4: ='[4]MOLINOS DE BARRAS'!I8 -> 154 | F4: ='[4]MOLINOS DE BARRAS'!J8 -> 0 | G4: ='[4]MOLINOS DE BARRAS'!K8 -> 0 | H4: ='[4]MOLINOS DE BARRAS'!O8 -> 1519 | I4: ='[4]MOLINOS DE BARRAS'!P8 -> 1436 | J4: ='[4]MOLINOS DE BARRAS'!Q8 -> 1445 | K4: ='[4]MOLINOS DE BARRAS'!U8 -> 1304 | L4: ='[4]MOLINOS DE BARRAS'!V8 -> 1212 | M4: ='[4]MOLINOS DE BARRAS'!W8 -> 1227 | N4: ='[4]MOLINOS DE BARRAS'!AA8 -> 1676 | O4: ='[4]MOLINOS DE BARRAS'!AB8 -> 1721 | P4: ='[4]MOLINOS DE BARRAS'!AC8 -> 1658 | Q4: ='[4]MOLINOS DE BARRAS'!AG8 -> 1674 | R4: ='[4]MOLINOS DE BARRAS'!AH8 -> 1705 | S4: ='[4]MOLINOS DE BARRAS'!AI8 -> 1595 | T4: ='[4]MOLINOS DE BARRAS'!AM8 -> 1529 | U4: ='[4]MOLINOS DE BARRAS'!AN8 -> 1698 | V4: ='[4]MOLINOS DE BARRAS'!AO8 -> 1656 | W4: ='[4]MOLINOS DE BARRAS'!AS8 -> 1596 | X4: ='[4]MOLINOS DE BARRAS'!AT8 -> 1700 | Y4: ='[4]MOLINOS DE BARRAS'!AU8 -> 1535 | Z4: ='[4]MOLINOS DE BARRAS'!AY8 -> 1839 | AA4: ='[4]MOLINOS DE BARRAS'!AZ8 -> 1723 | AB4: ='[4]MOLINOS DE BARRAS'!BA8 -> 1870
A5: 46268 | B5: ='[4]MOLINOS DE BARRAS'!C9 -> 1376 | C5: ='[4]MOLINOS DE BARRAS'!D9 -> 1530 | D5: ='[4]MOLINOS DE BARRAS'!E9 -> 1772 | E5: ='[4]MOLINOS DE BARRAS'!I9 -> 0 | F5: ='[4]MOLINOS DE BARRAS'!J9 -> 0 | G5: ='[4]MOLINOS DE BARRAS'!K9 -> 0 | H5: ='[4]MOLINOS DE BARRAS'!O9 -> 1670 | I5: ='[4]MOLINOS DE BARRAS'!P9 -> 1510 | J5: ='[4]MOLINOS DE BARRAS'!Q9 -> 1620 | K5: ='[4]MOLINOS DE BARRAS'!U9 -> 1335 | L5: ='[4]MOLINOS DE BARRAS'!V9 -> 1166 | M5: ='[4]MOLINOS DE BARRAS'!W9 -> 1215 | N5: ='[4]MOLINOS DE BARRAS'!AA9 -> 529 | O5: ='[4]MOLINOS DE BARRAS'!AB9 -> 0 | P5: ='[4]MOLINOS DE BARRAS'!AC9 -> 0 | Q5: ='[4]MOLINOS DE BARRAS'!AG9 -> 1660 | R5: ='[4]MOLINOS DE BARRAS'!AH9 -> 1745 | S5: ='[4]MOLINOS DE BARRAS'!AI9 -> 1703 | T5: ='[4]MOLINOS DE BARRAS'!AM9 -> 1373 | U5: ='[4]MOLINOS DE BARRAS'!AN9 -> 1776 | V5: ='[4]MOLINOS DE BARRAS'!AO9 -> 1726 | W5: ='[4]MOLINOS DE BARRAS'!AS9 -> 1442 | X5: ='[4]MOLINOS DE BARRAS'!AT9 -> 1621 | Y5: ='[4]MOLINOS DE BARRAS'!AU9 -> 1496 | Z5: ='[4]MOLINOS DE BARRAS'!AY9 -> 1802 | AA5: ='[4]MOLINOS DE BARRAS'!AZ9 -> 728 | AB5: ='[4]MOLINOS DE BARRAS'!BA9 -> 1813
A6: 46269 | B6: ='[4]MOLINOS DE BARRAS'!C10 -> 1696 | C6: ='[4]MOLINOS DE BARRAS'!D10 -> 1722 | D6: ='[4]MOLINOS DE BARRAS'!E10 -> 1794 | E6: ='[4]MOLINOS DE BARRAS'!I10 -> 0 | F6: ='[4]MOLINOS DE BARRAS'!J10 -> 1390 | G6: ='[4]MOLINOS DE BARRAS'!K10 -> 1786 | H6: ='[4]MOLINOS DE BARRAS'!O10 -> 1580 | I6: ='[4]MOLINOS DE BARRAS'!P10 -> 1408 | J6: ='[4]MOLINOS DE BARRAS'!Q10 -> 1292 | K6: ='[4]MOLINOS DE BARRAS'!U10 -> 1215 | L6: ='[4]MOLINOS DE BARRAS'!V10 -> 182 | M6: ='[4]MOLINOS DE BARRAS'!W10 -> 0 | N6: ='[4]MOLINOS DE BARRAS'!AA10 -> 0 | O6: ='[4]MOLINOS DE BARRAS'!AB10 -> 388 | P6: ='[4]MOLINOS DE BARRAS'!AC10 -> 0 | Q6: ='[4]MOLINOS DE BARRAS'!AG10 -> 1775 | R6: ='[4]MOLINOS DE BARRAS'!AH10 -> 1659 | S6: ='[4]MOLINOS DE BARRAS'!AI10 -> 1630 | T6: ='[4]MOLINOS DE BARRAS'!AM10 -> 1726 | U6: ='[4]MOLINOS DE BARRAS'!AN10 -> 1151 | V6: ='[4]MOLINOS DE BARRAS'!AO10 -> 1641 | W6: ='[4]MOLINOS DE BARRAS'!AS10 -> 1534 | X6: ='[4]MOLINOS DE BARRAS'!AT10 -> 1515 | Y6: ='[4]MOLINOS DE BARRAS'!AU10 -> 1560 | Z6: ='[4]MOLINOS DE BARRAS'!AY10 -> 1346 | AA6: ='[4]MOLINOS DE BARRAS'!AZ10 -> 1571 | AB6: ='[4]MOLINOS DE BARRAS'!BA10 -> 1909
A7: 46270 | B7: ='[4]MOLINOS DE BARRAS'!C11 -> 1861 | C7: ='[4]MOLINOS DE BARRAS'!D11 -> 1635 | D7: ='[4]MOLINOS DE BARRAS'!E11 -> 1765 | E7: ='[4]MOLINOS DE BARRAS'!I11 -> 1750 | F7: ='[4]MOLINOS DE BARRAS'!J11 -> 1570 | G7: ='[4]MOLINOS DE BARRAS'!K11 -> 1750 | H7: ='[4]MOLINOS DE BARRAS'!O11 -> 1450 | I7: ='[4]MOLINOS DE BARRAS'!P11 -> 1130 | J7: ='[4]MOLINOS DE BARRAS'!Q11 -> 1300 | K7: ='[4]MOLINOS DE BARRAS'!U11 -> 0 | L7: ='[4]MOLINOS DE BARRAS'!V11 -> 0 | M7: ='[4]MOLINOS DE BARRAS'!W11 -> 0 | N7: ='[4]MOLINOS DE BARRAS'!AA11 -> 0 | O7: ='[4]MOLINOS DE BARRAS'!AB11 -> 0 | P7: ='[4]MOLINOS DE BARRAS'!AC11 -> 0 | Q7: ='[4]MOLINOS DE BARRAS'!AG11 -> 1672 | R7: ='[4]MOLINOS DE BARRAS'!AH11 -> 1620 | S7: ='[4]MOLINOS DE BARRAS'!AI11 -> 1701 | T7: ='[4]MOLINOS DE BARRAS'!AM11 -> 1651 | U7: ='[4]MOLINOS DE BARRAS'!AN11 -> 1683 | V7: ='[4]MOLINOS DE BARRAS'!AO11 -> 1628 | W7: ='[4]MOLINOS DE BARRAS'!AS11 -> 1519 | X7: ='[4]MOLINOS DE BARRAS'!AT11 -> 1552 | Y7: ='[4]MOLINOS DE BARRAS'!AU11 -> 1647 | Z7: ='[4]MOLINOS DE BARRAS'!AY11 -> 1836 | AA7: ='[4]MOLINOS DE BARRAS'!AZ11 -> 1679 | AB7: ='[4]MOLINOS DE BARRAS'!BA11 -> 1890
A8: 46271 | B8: ='[4]MOLINOS DE BARRAS'!C12 -> 1759 | C8: ='[4]MOLINOS DE BARRAS'!D12 -> 1514 | D8: ='[4]MOLINOS DE BARRAS'!E12 -> 1722 | E8: ='[4]MOLINOS DE BARRAS'!I12 -> 1689 | F8: ='[4]MOLINOS DE BARRAS'!J12 -> 1470 | G8: ='[4]MOLINOS DE BARRAS'!K12 -> 1617 | H8: ='[4]MOLINOS DE BARRAS'!O12 -> 1046 | I8: ='[4]MOLINOS DE BARRAS'!P12 -> 1188 | J8: ='[4]MOLINOS DE BARRAS'!Q12 -> 1327 | K8: ='[4]MOLINOS DE BARRAS'!U12 -> 0 | L8: ='[4]MOLINOS DE BARRAS'!V12 -> 0 | M8: ='[4]MOLINOS DE BARRAS'!W12 -> 0 | N8: ='[4]MOLINOS DE BARRAS'!AA12 -> 0 | O8: ='[4]MOLINOS DE BARRAS'!AB12 -> 0 | P8: ='[4]MOLINOS DE BARRAS'!AC12 -> 0 | Q8: ='[4]MOLINOS DE BARRAS'!AG12 -> 1789 | R8: ='[4]MOLINOS DE BARRAS'!AH12 -> 1563 | S8: ='[4]MOLINOS DE BARRAS'!AI12 -> 1600 | T8: ='[4]MOLINOS DE BARRAS'!AM12 -> 1758 | U8: ='[4]MOLINOS DE BARRAS'!AN12 -> 1652 | V8: ='[4]MOLINOS DE BARRAS'!AO12 -> 1508 | W8: ='[4]MOLINOS DE BARRAS'!AS12 -> 1586 | X8: ='[4]MOLINOS DE BARRAS'!AT12 -> 1497 | Y8: ='[4]MOLINOS DE BARRAS'!AU12 -> 1525 | Z8: ='[4]MOLINOS DE BARRAS'!AY12 -> 1843 | AA8: ='[4]MOLINOS DE BARRAS'!AZ12 -> 1752 | AB8: ='[4]MOLINOS DE BARRAS'!BA12 -> 1823
A9: 46272 | B9: ='[4]MOLINOS DE BARRAS'!C13 -> 1782 | C9: ='[4]MOLINOS DE BARRAS'!D13 -> 1317 | D9: ='[4]MOLINOS DE BARRAS'!E13 -> 1551 | E9: ='[4]MOLINOS DE BARRAS'!I13 -> 1917 | F9: ='[4]MOLINOS DE BARRAS'!J13 -> 1283 | G9: ='[4]MOLINOS DE BARRAS'!K13 -> 1444 | H9: ='[4]MOLINOS DE BARRAS'!O13 -> 1393 | I9: ='[4]MOLINOS DE BARRAS'!P13 -> 1210 | J9: ='[4]MOLINOS DE BARRAS'!Q13 -> 826 | K9: ='[4]MOLINOS DE BARRAS'!U13 -> 0 | L9: ='[4]MOLINOS DE BARRAS'!V13 -> 0 | M9: ='[4]MOLINOS DE BARRAS'!W13 -> 0 | N9: ='[4]MOLINOS DE BARRAS'!AA13 -> 420 | O9: ='[4]MOLINOS DE BARRAS'!AB13 -> 0 | P9: ='[4]MOLINOS DE BARRAS'!AC13 -> 0 | Q9: ='[4]MOLINOS DE BARRAS'!AG13 -> 1668 | R9: ='[4]MOLINOS DE BARRAS'!AH13 -> 1471 | S9: ='[4]MOLINOS DE BARRAS'!AI13 -> 1519 | T9: ='[4]MOLINOS DE BARRAS'!AM13 -> 1636 | U9: ='[4]MOLINOS DE BARRAS'!AN13 -> 1413 | V9: ='[4]MOLINOS DE BARRAS'!AO13 -> 1577 | W9: ='[4]MOLINOS DE BARRAS'!AS13 -> 1043 | X9: ='[4]MOLINOS DE BARRAS'!AT13 -> 1442 | Y9: ='[4]MOLINOS DE BARRAS'!AU13 -> 1597 | Z9: ='[4]MOLINOS DE BARRAS'!AY13 -> 1765 | AA9: ='[4]MOLINOS DE BARRAS'!AZ13 -> 1673 | AB9: ='[4]MOLINOS DE BARRAS'!BA13 -> 1897
A10: 46273 | B10: ='[4]MOLINOS DE BARRAS'!C14 -> 1730 | C10: ='[4]MOLINOS DE BARRAS'!D14 -> 1612 | D10: ='[4]MOLINOS DE BARRAS'!E14 -> 1736 | E10: ='[4]MOLINOS DE BARRAS'!I14 -> 1695 | F10: ='[4]MOLINOS DE BARRAS'!J14 -> 1465 | G10: ='[4]MOLINOS DE BARRAS'!K14 -> 1580 | H10: ='[4]MOLINOS DE BARRAS'!O14 -> 1240 | I10: ='[4]MOLINOS DE BARRAS'!P14 -> 1130 | J10: ='[4]MOLINOS DE BARRAS'!Q14 -> 1200 | K10: ='[4]MOLINOS DE BARRAS'!U14 -> 0 | L10: ='[4]MOLINOS DE BARRAS'!V14 -> 0 | M10: ='[4]MOLINOS DE BARRAS'!W14 -> 0 | N10: ='[4]MOLINOS DE BARRAS'!AA14 -> 0 | O10: ='[4]MOLINOS DE BARRAS'!AB14 -> 655 | P10: ='[4]MOLINOS DE BARRAS'!AC14 -> 1445 | Q10: ='[4]MOLINOS DE BARRAS'!AG14 -> 1558 | R10: ='[4]MOLINOS DE BARRAS'!AH14 -> 1472 | S10: ='[4]MOLINOS DE BARRAS'!AI14 -> 1435 | T10: ='[4]MOLINOS DE BARRAS'!AM14 -> 1652 | U10: ='[4]MOLINOS DE BARRAS'!AN14 -> 1732 | V10: ='[4]MOLINOS DE BARRAS'!AO14 -> 1676 | W10: ='[4]MOLINOS DE BARRAS'!AS14 -> 1643 | X10: ='[4]MOLINOS DE BARRAS'!AT14 -> 1659 | Y10: ='[4]MOLINOS DE BARRAS'!AU14 -> 1587 | Z10: ='[4]MOLINOS DE BARRAS'!AY14 -> 1900 | AA10: ='[4]MOLINOS DE BARRAS'!AZ14 -> 1639 | AB10: ='[4]MOLINOS DE BARRAS'!BA14 -> 1756
A11: 46274 | B11: ='[4]MOLINOS DE BARRAS'!C15 -> 1477 | C11: ='[4]MOLINOS DE BARRAS'!D15 -> 1645 | D11: ='[4]MOLINOS DE BARRAS'!E15 -> 1625 | E11: ='[4]MOLINOS DE BARRAS'!I15 -> 1575 | F11: ='[4]MOLINOS DE BARRAS'!J15 -> 1420 | G11: ='[4]MOLINOS DE BARRAS'!K15 -> 1425 | H11: ='[4]MOLINOS DE BARRAS'!O15 -> 1395 | I11: ='[4]MOLINOS DE BARRAS'!P15 -> 1328 | J11: ='[4]MOLINOS DE BARRAS'!Q15 -> 1477 | K11: ='[4]MOLINOS DE BARRAS'!U15 -> 259 | L11: ='[4]MOLINOS DE BARRAS'!V15 -> 0 | M11: ='[4]MOLINOS DE BARRAS'!W15 -> 0 | N11: ='[4]MOLINOS DE BARRAS'!AA15 -> 1281 | O11: ='[4]MOLINOS DE BARRAS'!AB15 -> 1047 | P11: ='[4]MOLINOS DE BARRAS'!AC15 -> 1539 | Q11: ='[4]MOLINOS DE BARRAS'!AG15 -> 1263 | R11: ='[4]MOLINOS DE BARRAS'!AH15 -> 1413 | S11: ='[4]MOLINOS DE BARRAS'!AI15 -> 1445 | T11: ='[4]MOLINOS DE BARRAS'!AM15 -> 1556 | U11: ='[4]MOLINOS DE BARRAS'!AN15 -> 1596 | V11: ='[4]MOLINOS DE BARRAS'!AO15 -> 1692 | W11: ='[4]MOLINOS DE BARRAS'!AS15 -> 1562 | X11: ='[4]MOLINOS DE BARRAS'!AT15 -> 1730 | Y11: ='[4]MOLINOS DE BARRAS'!AU15 -> 1692 | Z11: ='[4]MOLINOS DE BARRAS'!AY15 -> 1566 | AA11: ='[4]MOLINOS DE BARRAS'!AZ15 -> 1601 | AB11: ='[4]MOLINOS DE BARRAS'!BA15 -> 1810
A12: 46275 | B12: ='[4]MOLINOS DE BARRAS'!C16 -> 1775 | C12: ='[4]MOLINOS DE BARRAS'!D16 -> 1612 | D12: ='[4]MOLINOS DE BARRAS'!E16 -> 1585 | E12: ='[4]MOLINOS DE BARRAS'!I16 -> 1645 | F12: ='[4]MOLINOS DE BARRAS'!J16 -> 1546 | G12: ='[4]MOLINOS DE BARRAS'!K16 -> 1519 | H12: ='[4]MOLINOS DE BARRAS'!O16 -> 1680 | I12: ='[4]MOLINOS DE BARRAS'!P16 -> 1589 | J12: ='[4]MOLINOS DE BARRAS'!Q16 -> 1561 | K12: ='[4]MOLINOS DE BARRAS'!U16 -> 498 | L12: ='[4]MOLINOS DE BARRAS'!V16 -> 1395 | M12: ='[4]MOLINOS DE BARRAS'!W16 -> 215 | N12: ='[4]MOLINOS DE BARRAS'!AA16 -> 1582 | O12: ='[4]MOLINOS DE BARRAS'!AB16 -> 1579 | P12: ='[4]MOLINOS DE BARRAS'!AC16 -> 1546 | Q12: ='[4]MOLINOS DE BARRAS'!AG16 -> 1423 | R12: ='[4]MOLINOS DE BARRAS'!AH16 -> 1425 | S12: ='[4]MOLINOS DE BARRAS'!AI16 -> 1538 | T12: ='[4]MOLINOS DE BARRAS'!AM16 -> 1662 | U12: ='[4]MOLINOS DE BARRAS'!AN16 -> 1660 | V12: ='[4]MOLINOS DE BARRAS'!AO16 -> 1621 | W12: ='[4]MOLINOS DE BARRAS'!AS16 -> 555 | X12: ='[4]MOLINOS DE BARRAS'!AT16 -> 0 | Y12: ='[4]MOLINOS DE BARRAS'!AU16 -> 1341 | Z12: ='[4]MOLINOS DE BARRAS'!AY16 -> 0 | AA12: ='[4]MOLINOS DE BARRAS'!AZ16 -> 0 | AB12: ='[4]MOLINOS DE BARRAS'!BA16 -> 1541
A13: 46276 | B13: ='[4]MOLINOS DE BARRAS'!C17 -> 1813 | C13: ='[4]MOLINOS DE BARRAS'!D17 -> 1671 | D13: ='[4]MOLINOS DE BARRAS'!E17 -> 1429 | E13: ='[4]MOLINOS DE BARRAS'!I17 -> 1656 | F13: ='[4]MOLINOS DE BARRAS'!J17 -> 1427 | G13: ='[4]MOLINOS DE BARRAS'!K17 -> 1397 | H13: ='[4]MOLINOS DE BARRAS'!O17 -> 1695 | I13: ='[4]MOLINOS DE BARRAS'!P17 -> 1553 | J13: ='[4]MOLINOS DE BARRAS'!Q17 -> 1352 | K13: ='[4]MOLINOS DE BARRAS'!U17 -> 457 | L13: ='[4]MOLINOS DE BARRAS'!V17 -> 0 | M13: ='[4]MOLINOS DE BARRAS'!W17 -> 0 | N13: ='[4]MOLINOS DE BARRAS'!AA17 -> 1501 | O13: ='[4]MOLINOS DE BARRAS'!AB17 -> 1566 | P13: ='[4]MOLINOS DE BARRAS'!AC17 -> 1279 | Q13: ='[4]MOLINOS DE BARRAS'!AG17 -> 1548 | R13: ='[4]MOLINOS DE BARRAS'!AH17 -> 1558 | S13: ='[4]MOLINOS DE BARRAS'!AI17 -> 1232 | T13: ='[4]MOLINOS DE BARRAS'!AM17 -> 1415 | U13: ='[4]MOLINOS DE BARRAS'!AN17 -> 1748 | V13: ='[4]MOLINOS DE BARRAS'!AO17 -> 1270 | W13: ='[4]MOLINOS DE BARRAS'!AS17 -> 1226 | X13: ='[4]MOLINOS DE BARRAS'!AT17 -> 1600 | Y13: ='[4]MOLINOS DE BARRAS'!AU17 -> 1274 | Z13: ='[4]MOLINOS DE BARRAS'!AY17 -> 1468 | AA13: ='[4]MOLINOS DE BARRAS'!AZ17 -> 2017 | AB13: ='[4]MOLINOS DE BARRAS'!BA17 -> 1514
A14: 46277 | B14: ='[4]MOLINOS DE BARRAS'!C18 -> 0 | C14: ='[4]MOLINOS DE BARRAS'!D18 -> 675 | D14: ='[4]MOLINOS DE BARRAS'!E18 -> 1502 | E14: ='[4]MOLINOS DE BARRAS'!I18 -> 0 | F14: ='[4]MOLINOS DE BARRAS'!J18 -> 590 | G14: ='[4]MOLINOS DE BARRAS'!K18 -> 1260 | H14: ='[4]MOLINOS DE BARRAS'!O18 -> 0 | I14: ='[4]MOLINOS DE BARRAS'!P18 -> 520 | J14: ='[4]MOLINOS DE BARRAS'!Q18 -> 1170 | K14: ='[4]MOLINOS DE BARRAS'!U18 -> 0 | L14: ='[4]MOLINOS DE BARRAS'!V18 -> 0 | M14: ='[4]MOLINOS DE BARRAS'!W18 -> 0 | N14: ='[4]MOLINOS DE BARRAS'!AA18 -> 0 | O14: ='[4]MOLINOS DE BARRAS'!AB18 -> 840 | P14: ='[4]MOLINOS DE BARRAS'!AC18 -> 1540 | Q14: ='[4]MOLINOS DE BARRAS'!AG18 -> 0 | R14: ='[4]MOLINOS DE BARRAS'!AH18 -> 863 | S14: ='[4]MOLINOS DE BARRAS'!AI18 -> 1487 | T14: ='[4]MOLINOS DE BARRAS'!AM18 -> 0 | U14: ='[4]MOLINOS DE BARRAS'!AN18 -> 896 | V14: ='[4]MOLINOS DE BARRAS'!AO18 -> 1583 | W14: ='[4]MOLINOS DE BARRAS'!AS18 -> 0 | X14: ='[4]MOLINOS DE BARRAS'!AT18 -> 891 | Y14: ='[4]MOLINOS DE BARRAS'!AU18 -> 1539 | Z14: ='[4]MOLINOS DE BARRAS'!AY18 -> 0 | AA14: ='[4]MOLINOS DE BARRAS'!AZ18 -> 829 | AB14: ='[4]MOLINOS DE BARRAS'!BA18 -> 1904
... A32: 46295 | B32: ='[4]MOLINOS DE BARRAS'!C36 -> 0 | C32: ='[4]MOLINOS DE BARRAS'!D36 -> 0 | D32: ='[4]MOLINOS DE BARRAS'!E36 -> 0 | E32: ='[4]MOLINOS DE BARRAS'!I36 -> 0 | F32: ='[4]MOLINOS DE BARRAS'!J36 -> 0 | G32: ='[4]MOLINOS DE BARRAS'!K36 -> 0 | H32: ='[4]MOLINOS DE BARRAS'!O36 -> 0 | I32: ='[4]MOLINOS DE BARRAS'!P36 -> 0 | J32: ='[4]MOLINOS DE BARRAS'!Q36 -> 0 | K32: ='[4]MOLINOS DE BARRAS'!U36 -> 0 | L32: ='[4]MOLINOS DE BARRAS'!V36 -> 0 | M32: ='[4]MOLINOS DE BARRAS'!W36 -> 0 | N32: ='[4]MOLINOS DE BARRAS'!AA36 -> 0 | O32: ='[4]MOLINOS DE BARRAS'!AB36 -> 0 | P32: ='[4]MOLINOS DE BARRAS'!AC36 -> 0 | Q32: ='[4]MOLINOS DE BARRAS'!AG36 -> 0 | R32: ='[4]MOLINOS DE BARRAS'!AH36 -> 0 | S32: ='[4]MOLINOS DE BARRAS'!AI36 -> 0 | T32: ='[4]MOLINOS DE BARRAS'!AM36 -> 0 | U32: ='[4]MOLINOS DE BARRAS'!AN36 -> 0 | V32: ='[4]MOLINOS DE BARRAS'!AO36 -> 0 | W32: ='[4]MOLINOS DE BARRAS'!AS36 -> 0 | X32: ='[4]MOLINOS DE BARRAS'!AT36 -> 0 | Y32: ='[4]MOLINOS DE BARRAS'!AU36 -> 0 | Z32: ='[4]MOLINOS DE BARRAS'!AY36 -> 0 | AA32: ='[4]MOLINOS DE BARRAS'!AZ36 -> 0 | AB32: ='[4]MOLINOS DE BARRAS'!BA36 -> 0
A33: TOTAL | B33: =SUBTOTAL(9,B3:B32) -> 42453 | C33: =SUBTOTAL(9,C3:C32) -> 41623 | D33: =SUBTOTAL(9,D3:D32) -> 46035 | E33: =SUBTOTAL(9,E3:E32) -> 28557 | F33: =SUBTOTAL(9,F3:F32) -> 27956 | G33: =SUBTOTAL(9,G3:G32) -> 28651 | H33: =SUBTOTAL(9,H3:H32) -> 30590 | I33: =SUBTOTAL(9,I3:I32) -> 29580 | ... AB33: =SUBTOTAL(9,AB3:AB32) -> 50341

Sheet LIMPIEZA CANALETAS
C2: PROGRAMA SEMANAL DE LIMPIEZA DE PISOS Y CANALETAS - PLANTA MAGNÉTICA
B4: MES | C4: MAYO 2026
B5: PISO | C5: CANALETA | D5: TIPO | E5: PUNTO REFERENCIA | F5: LUNES 04 | H5: MARTES 05 | J5: MIÉRCOLES 06 | L5: JUEVES 07 | N5: VIERNES 08 | P5: SÁBADO 09 | R5: DOMINGO 10 | T5: RESPONSABLE | U5: OBSERVACIÓN
B6: P2 | C6: T1 | D6: Transversal | E6: BM 032-201 / 202-202 | F6: ❌ | G6: Solo cuentan con 7 personas de limpieza. Se da prioridad a limpieza de area de bombas 213-431 / 213-243 / 213-817 /213-818
B7: P2 | C7: H1 | D7: Horizontal | E7: 213-394 / 032-202 | F7: ❌
B8: P2 | C8: H2 | D8: Horizontal | E8: 213-233 / 032-203 | F8: ❌ | M8: ✔
B9: P2 | C9: H3 | D9: Horizontal | E9: 213-104 / 032-204 | H9: ❌ | I9: Solo cuentan con 7 personas de limpieza. Se da prioridad a limpieza debajo RM1/RM2
B10: P2 | C10: H4 | D10: Horizontal | E10: 213-311 / 032-205 | H10: ❌
B11: P2 | C11: H5 | D11: Horizontal | E11: 032-206
B12: P2 | C12: H6 | D12: Horizontal | E12: 032-207
B13: P2 | C13: H7 | D13: Horizontal | E13: 032-208
B14: P2 | C14: H8 | D14: Horizontal | E14: 032-209-210
B15: P2 | C15: T2 | D15: Transversal | E15: Colector BM | F15: ❌ | G15: ❌
B16: P2 | C16: T3 | D16: Transversal | E16: Transferencia BM | H16: ❌ | I16: ❌
B17: P2 | C17: T4 | D17: Transversal | E17: Descarga BM
B18: P2 | C18: T5 | D18: Transversal | E18: Canal principal
B19: P3 | C19: T6 | D19: Transversal | E19: 213-800 / 231
B20: P3 | C20: T7 | D20: Transversal | E20: 213-653 / 654
B21: P3 | C21: T8 | D21: Transversal | E21: 213-477-480
B22: P3 | C22: H9 | D22: Horizontal | E22: 213-243 / 242 | L22: ✔ | M22: Avanze de manguereo . | N22: ✔ | O22: Avanze de manguereo .
B23: P3 | C23: CANAL C | D23: Transversal | E23: Canal general | G23: ✔ | M23: ✔
B24: P3 | C24: T9 | D24: Transversal | E24: 213-818 / 817
B26: PISO | C26: CANALETA | D26: TIPO | E26: PUNTO REFERENCIA | G26: LUNES 11 | I26: MARTES 12 | K26: MIÉRCOLES 13 | M26: JUEVES 14 | O26: VIERNES 15 | Q26: SÁBADO 16 | S26: DOMINGO 17 | T26: RESPONSABLE | U26: OBSERVACIÓN
B27: P2 | C27: T1 | D27: Transversal | E27: BM 032-201 / 202-202
B28: P2 | C28: H1 | D28: Horizontal | E28: 213-394 / 032-202
B29: P2 | C29: H2 | D29: Horizontal | E29: 213-233 / 032-203
B30: P2 | C30: H3 | D30: Horizontal | E30: 213-104 / 032-204
B31: P2 | C31: H4 | D31: Horizontal | E31: 213-311 / 032-205
B32: P2 | C32: H5 | D32: Horizontal | E32: 032-206
B33: P2 | C33: H6 | D33: Horizontal | E33: 032-207
B34: P2 | C34: H7 | D34: Horizontal | E34: 032-208
B35: P2 | C35: H8 | D35: Horizontal | E35: 032-209-210
B36: P2 | C36: T2 | D36: Transversal | E36: Colector BM
B37: P2 | C37: T3 | D37: Transversal | E37: Transferencia BM
B38: P2 | C38: T4 | D38: Transversal | E38: Descarga BM
... B45: P3 | C45: T9 | D45: Transversal | E45: 213-818 / 817
B47: PISO | C47: CANALETA | D47: TIPO | E47: PUNTO REFERENCIA | G47: LUNES 18 | I47: MARTES 19 | K47: MIÉRCOLES 20 | M47: JUEVES 21 | O47: VIERNES 22 | Q47: SÁBADO 23 | S47: DOMINGO 24 | T47: RESPONSABLE | U47: OBSERVACIÓN
B48: P2 | C48: T1 | D48: Transversal | E48: BM 032-201 / 202-202
B49: P2 | C49: H1 | D49: Horizontal | E49: 213-394 / 032-202
B50: P2 | C50: H2 | D50: Horizontal | E50: 213-233 / 032-203
B51: P2 | C51: H3 | D51: Horizontal | E51: 213-104 / 032-204
B52: P2 | C52: H4 | D52: Horizontal | E52: 213-311 / 032-205
B53: P2 | C53: H5 | D53: Horizontal | E53: 032-206
B54: P2 | C54: H6 | D54: Horizontal | E54: 032-207
B55: P2 | C55: H7 | D55: Horizontal | E55: 032-208
B56: P2 | C56: H8 | D56: Horizontal | E56: 032-209-210
B57: P2 | C57: T2 | D57: Transversal | E57: Colector BM
B58: P2 | C58: T3 | D58: Transversal | E58: Transferencia BM
B59: P2 | C59: T4 | D59: Transversal | E59: Descarga BM
... B66: P3 | C66: T9 | D66: Transversal | E66: 213-818 / 817
B68: PISO | C68: CANALETA | D68: TIPO | E68: PUNTO REFERENCIA | G68: LUNES 25 | I68: MARTES 26 | K68: MIÉRCOLES 27 | M68: JUEVES 28 | O68: VIERNES 29 | Q68: SÁBADO 30 | S68: DOMINGO 31 | T68: RESPONSABLE | U68: OBSERVACIÓN
B69: P2 | C69: T1 | D69: Transversal | E69: BM 032-201 / 202-202
B70: P2 | C70: H1 | D70: Horizontal | E70: 213-394 / 032-202
B71: P2 | C71: H2 | D71: Horizontal | E71: 213-233 / 032-203
B72: P2 | C72: H3 | D72: Horizontal | E72: 213-104 / 032-204
B73: P2 | C73: H4 | D73: Horizontal | E73: 213-311 / 032-205
B74: P2 | C74: H5 | D74: Horizontal | E74: 032-206
B75: P2 | C75: H6 | D75: Horizontal | E75: 032-207
B76: P2 | C76: H7 | D76: Horizontal | E76: 032-208
B77: P2 | C77: H8 | D77: Horizontal | E77: 032-209-210
B78: P2 | C78: T2 | D78: Transversal | E78: Colector BM
B79: P2 | C79: T3 | D79: Transversal | E79: Transferencia BM
B80: P2 | C80: T4 | D80: Transversal | E80: Descarga BM
... B87: P3 | C87: T9 | D87: Transversal | E87: 213-818 / 817

Sheet AGREGADO MEDIOS MOLEDORES
B1: FECHA | C1: BARRAS RM1 | D1: BARRAS RM2 | E1: BARRAS RM3 | F1: BARRAS RM4 | G1: BARRAS RM5 | H1: BARRAS RM6 | I1: BARRAS RM7 | J1: BARRAS RM8 | K1: BARRAS 1-8 | L1: BARRAS 9 RM9 | M1: TOTAL BARRAS | N1: CONOS 40X50 BM1 | O1: CONOS 40X50 BM2 | P1: CONOS 40X50 BM3 | Q1: CONOS 40X50 BM4 | R1: CONOS 30X35 BM5 | S1: CONOS 40X50 BM6 | T1: CONOS 40X50 BM7 | U1: CONOS 40X50 | V1: CONOS 30X35 | W1: BOLAS BM8 | X1: BOLAS BM9 | Y1: BOLAS BM10 | Z1: BOLAS ALTO CROM | AA1: TOTAL CON+BOL
B2: 46266 | C2: ='[3]CONS.ACEROS'!E610 -> 0 | D2: ='[3]CONS.ACEROS'!F610 -> 18 | E2: ='[3]CONS.ACEROS'!G610 -> 18 | F2: ='[3]CONS.ACEROS'!H610 -> 18 | G2: ='[3]CONS.ACEROS'!I610 -> 11 | H2: ='[3]CONS.ACEROS'!J610 -> 20 | I2: ='[3]CONS.ACEROS'!K610 -> 0 | J2: ='[3]CONS.ACEROS'!L610 -> 22 | K2: =SUM(C2:J2) -> 107 | L2: ='[3]CONS.ACEROS'!N610 -> 15 | M2: =+K2+L2 -> 122 | N2: ='[3]CONS.ACEROS'!P610 -> 6 | O2: ='[3]CONS.ACEROS'!Q610 -> 6 | P2: ='[3]CONS.ACEROS'!R610 -> 6 | Q2: ='[3]CONS.ACEROS'!S610 -> 0 | R2: ='[3]CONS.ACEROS'!T610 -> 4 | S2: ='[3]CONS.ACEROS'!U610 -> 4 | T2: ='[3]CONS.ACEROS'!V610 -> 0 | U2: =N2 -> 6 | V2: =SUM(O2:T2) -> 20 | W2: ='[3]CONS.ACEROS'!Y610 -> 0 | X2: ='[3]CONS.ACEROS'!Z610 -> 0 | Y2: ='[3]CONS.ACEROS'!AA610 -> 0 | Z2: =SUM(W2:Y2) -> 0 | AA2: =+Z2+U2+V2 -> 26
B3: 46267 | C3: ='[3]CONS.ACEROS'!E611 -> 0 | D3: ='[3]CONS.ACEROS'!F611 -> 0 | E3: ='[3]CONS.ACEROS'!G611 -> 0 | F3: ='[3]CONS.ACEROS'!H611 -> 0 | G3: ='[3]CONS.ACEROS'!I611 -> 0 | H3: ='[3]CONS.ACEROS'!J611 -> 0 | I3: ='[3]CONS.ACEROS'!K611 -> 16 | J3: ='[3]CONS.ACEROS'!L611 -> 0 | K3: =SUM(C3:J3) -> 16 | L3: ='[3]CONS.ACEROS'!N611 -> 0 | M3: =+K3+L3 -> 16 | N3: ='[3]CONS.ACEROS'!P611 -> 4 | O3: ='[3]CONS.ACEROS'!Q611 -> 4 | P3: ='[3]CONS.ACEROS'!R611 -> 0 | Q3: ='[3]CONS.ACEROS'!S611 -> 4 | R3: ='[3]CONS.ACEROS'!T611 -> 4 | S3: ='[3]CONS.ACEROS'!U611 -> 2 | T3: ='[3]CONS.ACEROS'!V611 -> 6 | U3: =N3 -> 4 | V3: =SUM(O3:T3) -> 20 | W3: ='[3]CONS.ACEROS'!Y611 -> 4 | X3: ='[3]CONS.ACEROS'!Z611 -> 6 | Y3: ='[3]CONS.ACEROS'!AA611 -> 8 | Z3: =SUM(W3:Y3) -> 18 | AA3: =+Z3+U3+V3 -> 42
B4: 46268 | C4: ='[3]CONS.ACEROS'!E612 -> 9 | D4: ='[3]CONS.ACEROS'!F612 -> 0 | E4: ='[3]CONS.ACEROS'!G612 -> 0 | F4: ='[3]CONS.ACEROS'!H612 -> 0 | G4: ='[3]CONS.ACEROS'!I612 -> 0 | H4: ='[3]CONS.ACEROS'!J612 -> 0 | I4: ='[3]CONS.ACEROS'!K612 -> 0 | J4: ='[3]CONS.ACEROS'!L612 -> 14 | K4: =SUM(C4:J4) -> 23 | L4: ='[3]CONS.ACEROS'!N612 -> 12 | M4: =+K4+L4 -> 35 | N4: ='[3]CONS.ACEROS'!P612 -> 6 | O4: ='[3]CONS.ACEROS'!Q612 -> 0 | P4: ='[3]CONS.ACEROS'!R612 -> 0 | Q4: ='[3]CONS.ACEROS'!S612 -> 6 | R4: ='[3]CONS.ACEROS'!T612 -> 0 | S4: ='[3]CONS.ACEROS'!U612 -> 6 | T4: ='[3]CONS.ACEROS'!V612 -> 6 | U4: =N4 -> 6 | V4: =SUM(O4:T4) -> 18 | W4: ='[3]CONS.ACEROS'!Y612 -> 4 | X4: ='[3]CONS.ACEROS'!Z612 -> 8 | Y4: ='[3]CONS.ACEROS'!AA612 -> 6 | Z4: =SUM(W4:Y4) -> 18 | AA4: =+Z4+U4+V4 -> 42
B5: 46269 | C5: ='[3]CONS.ACEROS'!E613 -> 0 | D5: ='[3]CONS.ACEROS'!F613 -> 0 | E5: ='[3]CONS.ACEROS'!G613 -> 12 | F5: ='[3]CONS.ACEROS'!H613 -> 12 | G5: ='[3]CONS.ACEROS'!I613 -> 0 | H5: ='[3]CONS.ACEROS'!J613 -> 9 | I5: ='[3]CONS.ACEROS'!K613 -> 6 | J5: ='[3]CONS.ACEROS'!L613 -> 0 | K5: =SUM(C5:J5) -> 39 | L5: ='[3]CONS.ACEROS'!N613 -> 9 | M5: =+K5+L5 -> 48 | N5: ='[3]CONS.ACEROS'!P613 -> 8 | O5: ='[3]CONS.ACEROS'!Q613 -> 0 | P5: ='[3]CONS.ACEROS'!R613 -> 0 | Q5: ='[3]CONS.ACEROS'!S613 -> 4 | R5: ='[3]CONS.ACEROS'!T613 -> 0 | S5: ='[3]CONS.ACEROS'!U613 -> 6 | T5: ='[3]CONS.ACEROS'!V613 -> 2 | U5: =N5 -> 8 | V5: =SUM(O5:T5) -> 12 | W5: ='[3]CONS.ACEROS'!Y613 -> 6 | X5: ='[3]CONS.ACEROS'!Z613 -> 6 | Y5: ='[3]CONS.ACEROS'!AA613 -> 0 | Z5: =SUM(W5:Y5) -> 12 | AA5: =+Z5+U5+V5 -> 32
B6: 46270 | C6: ='[3]CONS.ACEROS'!E614 -> 0 | D6: ='[3]CONS.ACEROS'!F614 -> 0 | E6: ='[3]CONS.ACEROS'!G614 -> 0 | F6: ='[3]CONS.ACEROS'!H614 -> 0 | G6: ='[3]CONS.ACEROS'!I614 -> 0 | H6: ='[3]CONS.ACEROS'!J614 -> 0 | I6: ='[3]CONS.ACEROS'!K614 -> 0 | J6: ='[3]CONS.ACEROS'!L614 -> 0 | K6: =SUM(C6:J6) -> 0 | L6: ='[3]CONS.ACEROS'!N614 -> 0 | M6: =+K6+L6 -> 0 | N6: ='[3]CONS.ACEROS'!P614 -> 4 | O6: ='[3]CONS.ACEROS'!Q614 -> 0 | P6: ='[3]CONS.ACEROS'!R614 -> 4 | Q6: ='[3]CONS.ACEROS'!S614 -> 0 | R6: ='[3]CONS.ACEROS'!T614 -> 0 | S6: ='[3]CONS.ACEROS'!U614 -> 0 | T6: ='[3]CONS.ACEROS'!V614 -> 0 | U6: =N6 -> 4 | V6: =SUM(O6:T6) -> 4 | W6: ='[3]CONS.ACEROS'!Y614 -> 10 | X6: ='[3]CONS.ACEROS'!Z614 -> 10 | Y6: ='[3]CONS.ACEROS'!AA614 -> 10 | Z6: =SUM(W6:Y6) -> 30 | AA6: =+Z6+U6+V6 -> 38
B7: 46271 | C7: ='[3]CONS.ACEROS'!E615 -> 0 | D7: ='[3]CONS.ACEROS'!F615 -> 0 | E7: ='[3]CONS.ACEROS'!G615 -> 0 | F7: ='[3]CONS.ACEROS'!H615 -> 0 | G7: ='[3]CONS.ACEROS'!I615 -> 0 | H7: ='[3]CONS.ACEROS'!J615 -> 0 | I7: ='[3]CONS.ACEROS'!K615 -> 0 | J7: ='[3]CONS.ACEROS'!L615 -> 0 | K7: =SUM(C7:J7) -> 0 | L7: ='[3]CONS.ACEROS'!N615 -> 0 | M7: =+K7+L7 -> 0 | N7: ='[3]CONS.ACEROS'!P615 -> 0 | O7: ='[3]CONS.ACEROS'!Q615 -> 0 | P7: ='[3]CONS.ACEROS'!R615 -> 0 | Q7: ='[3]CONS.ACEROS'!S615 -> 0 | R7: ='[3]CONS.ACEROS'!T615 -> 0 | S7: ='[3]CONS.ACEROS'!U615 -> 0 | T7: ='[3]CONS.ACEROS'!V615 -> 0 | U7: =N7 -> 0 | V7: =SUM(O7:T7) -> 0 | W7: ='[3]CONS.ACEROS'!Y615 -> 0 | X7: ='[3]CONS.ACEROS'!Z615 -> 0 | Y7: ='[3]CONS.ACEROS'!AA615 -> 0 | Z7: =SUM(W7:Y7) -> 0 | AA7: =+Z7+U7+V7 -> 0
B8: 46272 | C8: ='[3]CONS.ACEROS'!E616 -> 18 | D8: ='[3]CONS.ACEROS'!F616 -> 0 | E8: ='[3]CONS.ACEROS'!G616 -> 0 | F8: ='[3]CONS.ACEROS'!H616 -> 0 | G8: ='[3]CONS.ACEROS'!I616 -> 0 | H8: ='[3]CONS.ACEROS'!J616 -> 9 | I8: ='[3]CONS.ACEROS'!K616 -> 12 | J8: ='[3]CONS.ACEROS'!L616 -> 9 | K8: =SUM(C8:J8) -> 48 | L8: ='[3]CONS.ACEROS'!N616 -> 0 | M8: =+K8+L8 -> 48 | N8: ='[3]CONS.ACEROS'!P616 -> 4 | O8: ='[3]CONS.ACEROS'!Q616 -> 4 | P8: ='[3]CONS.ACEROS'!R616 -> 0 | Q8: ='[3]CONS.ACEROS'!S616 -> 0 | R8: ='[3]CONS.ACEROS'!T616 -> 0 | S8: ='[3]CONS.ACEROS'!U616 -> 2 | T8: ='[3]CONS.ACEROS'!V616 -> 4 | U8: =N8 -> 4 | V8: =SUM(O8:T8) -> 10 | W8: ='[3]CONS.ACEROS'!Y616 -> 0 | X8: ='[3]CONS.ACEROS'!Z616 -> 4 | Y8: ='[3]CONS.ACEROS'!AA616 -> 0 | Z8: =SUM(W8:Y8) -> 4 | AA8: =+Z8+U8+V8 -> 18
B9: 46273 | C9: ='[3]CONS.ACEROS'!E617 -> 0 | D9: ='[3]CONS.ACEROS'!F617 -> 18 | E9: ='[3]CONS.ACEROS'!G617 -> 15 | F9: ='[3]CONS.ACEROS'!H617 -> 0 | G9: ='[3]CONS.ACEROS'!I617 -> 0 | H9: ='[3]CONS.ACEROS'!J617 -> 0 | I9: ='[3]CONS.ACEROS'!K617 -> 0 | J9: ='[3]CONS.ACEROS'!L617 -> 9 | K9: =SUM(C9:J9) -> 42 | L9: ='[3]CONS.ACEROS'!N617 -> 18 | M9: =+K9+L9 -> 60 | N9: ='[3]CONS.ACEROS'!P617 -> 0 | O9: ='[3]CONS.ACEROS'!Q617 -> 0 | P9: ='[3]CONS.ACEROS'!R617 -> 0 | Q9: ='[3]CONS.ACEROS'!S617 -> 0 | R9: ='[3]CONS.ACEROS'!T617 -> 8 | S9: ='[3]CONS.ACEROS'!U617 -> 0 | T9: ='[3]CONS.ACEROS'!V617 -> 8 | U9: =N9 -> 0 | V9: =SUM(O9:T9) -> 16 | W9: ='[3]CONS.ACEROS'!Y617 -> 0 | X9: ='[3]CONS.ACEROS'!Z617 -> 6 | Y9: ='[3]CONS.ACEROS'!AA617 -> 0 | Z9: =SUM(W9:Y9) -> 6 | AA9: =+Z9+U9+V9 -> 22
B10: 46274 | C10: ='[3]CONS.ACEROS'!E618 -> 9 | D10: ='[3]CONS.ACEROS'!F618 -> 0 | E10: ='[3]CONS.ACEROS'!G618 -> 0 | F10: ='[3]CONS.ACEROS'!H618 -> 0 | G10: ='[3]CONS.ACEROS'!I618 -> 18 | H10: ='[3]CONS.ACEROS'!J618 -> 14 | I10: ='[3]CONS.ACEROS'!K618 -> 9 | J10: ='[3]CONS.ACEROS'!L618 -> 0 | K10: =SUM(C10:J10) -> 50 | L10: ='[3]CONS.ACEROS'!N618 -> 9 | M10: =+K10+L10 -> 59 | N10: ='[3]CONS.ACEROS'!P618 -> 6 | O10: ='[3]CONS.ACEROS'!Q618 -> 0 | P10: ='[3]CONS.ACEROS'!R618 -> 4 | Q10: ='[3]CONS.ACEROS'!S618 -> 0 | R10: ='[3]CONS.ACEROS'!T618 -> 6 | S10: ='[3]CONS.ACEROS'!U618 -> 0 | T10: ='[3]CONS.ACEROS'!V618 -> 4 | U10: =N10 -> 6 | V10: =SUM(O10:T10) -> 14 | W10: ='[3]CONS.ACEROS'!Y618 -> 4 | X10: ='[3]CONS.ACEROS'!Z618 -> 4 | Y10: ='[3]CONS.ACEROS'!AA618 -> 4 | Z10: =SUM(W10:Y10) -> 12 | AA10: =+Z10+U10+V10 -> 32
B11: 46275 | C11: ='[3]CONS.ACEROS'!E619 -> 0 | D11: ='[3]CONS.ACEROS'!F619 -> 7 | E11: ='[3]CONS.ACEROS'!G619 -> 0 | F11: ='[3]CONS.ACEROS'!H619 -> 0 | G11: ='[3]CONS.ACEROS'!I619 -> 0 | H11: ='[3]CONS.ACEROS'!J619 -> 0 | I11: ='[3]CONS.ACEROS'!K619 -> 7 | J11: ='[3]CONS.ACEROS'!L619 -> 5 | K11: =SUM(C11:J11) -> 19 | L11: ='[3]CONS.ACEROS'!N619 -> 0 | M11: =+K11+L11 -> 19 | N11: ='[3]CONS.ACEROS'!P619 -> 4 | O11: ='[3]CONS.ACEROS'!Q619 -> 0 | P11: ='[3]CONS.ACEROS'!R619 -> 0 | Q11: ='[3]CONS.ACEROS'!S619 -> 0 | R11: ='[3]CONS.ACEROS'!T619 -> 6 | S11: ='[3]CONS.ACEROS'!U619 -> 0 | T11: ='[3]CONS.ACEROS'!V619 -> 2 | U11: =N11 -> 4 | V11: =SUM(O11:T11) -> 8 | W11: ='[3]CONS.ACEROS'!Y619 -> 0 | X11: ='[3]CONS.ACEROS'!Z619 -> 0 | Y11: ='[3]CONS.ACEROS'!AA619 -> 2 | Z11: =SUM(W11:Y11) -> 2 | AA11: =+Z11+U11+V11 -> 14
B12: 46276 | C12: ='[3]CONS.ACEROS'!E620 -> 0 | D12: ='[3]CONS.ACEROS'!F620 -> 9 | E12: ='[3]CONS.ACEROS'!G620 -> 0 | F12: ='[3]CONS.ACEROS'!H620 -> 0 | G12: ='[3]CONS.ACEROS'!I620 -> 0 | H12: ='[3]CONS.ACEROS'!J620 -> 0 | I12: ='[3]CONS.ACEROS'!K620 -> 0 | J12: ='[3]CONS.ACEROS'!L620 -> 7 | K12: =SUM(C12:J12) -> 16 | L12: ='[3]CONS.ACEROS'!N620 -> 7 | M12: =+K12+L12 -> 23 | N12: ='[3]CONS.ACEROS'!P620 -> 6 | O12: ='[3]CONS.ACEROS'!Q620 -> 0 | P12: ='[3]CONS.ACEROS'!R620 -> 0 | Q12: ='[3]CONS.ACEROS'!S620 -> 0 | R12: ='[3]CONS.ACEROS'!T620 -> 6 | S12: ='[3]CONS.ACEROS'!U620 -> 0 | T12: ='[3]CONS.ACEROS'!V620 -> 2 | U12: =N12 -> 6 | V12: =SUM(O12:T12) -> 8 | W12: ='[3]CONS.ACEROS'!Y620 -> 0 | X12: ='[3]CONS.ACEROS'!Z620 -> 4 | Y12: ='[3]CONS.ACEROS'!AA620 -> 0 | Z12: =SUM(W12:Y12) -> 4 | AA12: =+Z12+U12+V12 -> 18
B13: 46277 | C13: ='[3]CONS.ACEROS'!E621 -> 0 | D13: ='[3]CONS.ACEROS'!F621 -> 0 | E13: ='[3]CONS.ACEROS'!G621 -> 0 | F13: ='[3]CONS.ACEROS'!H621 -> 0 | G13: ='[3]CONS.ACEROS'!I621 -> 0 | H13: ='[3]CONS.ACEROS'!J621 -> 0 | I13: ='[3]CONS.ACEROS'!K621 -> 0 | J13: ='[3]CONS.ACEROS'!L621 -> 0 | K13: =SUM(C13:J13) -> 0 | L13: ='[3]CONS.ACEROS'!N621 -> 0 | M13: =+K13+L13 -> 0 | N13: ='[3]CONS.ACEROS'!P621 -> 0 | O13: ='[3]CONS.ACEROS'!Q621 -> 0 | P13: ='[3]CONS.ACEROS'!R621 -> 0 | Q13: ='[3]CONS.ACEROS'!S621 -> 0 | R13: ='[3]CONS.ACEROS'!T621 -> 0 | S13: ='[3]CONS.ACEROS'!U621 -> 0 | T13: ='[3]CONS.ACEROS'!V621 -> 0 | U13: =N13 -> 0 | V13: =SUM(O13:T13) -> 0 | W13: ='[3]CONS.ACEROS'!Y621 -> 0 | X13: ='[3]CONS.ACEROS'!Z621 -> 0 | Y13: ='[3]CONS.ACEROS'!AA621 -> 0 | Z13: =SUM(W13:Y13) -> 0 | AA13: =+Z13+U13+V13 -> 0
... B16: 46280 | C16: ='[3]CONS.ACEROS'!E624 -> 0 | D16: ='[3]CONS.ACEROS'!F624 -> 0 | E16: ='[3]CONS.ACEROS'!G624 -> 0 | F16: ='[3]CONS.ACEROS'!H624 -> 0 | G16: ='[3]CONS.ACEROS'!I624 -> 0 | H16: ='[3]CONS.ACEROS'!J624 -> 9 | I16: ='[3]CONS.ACEROS'!K624 -> 0 | J16: ='[3]CONS.ACEROS'!L624 -> 0 | K16: =SUM(C16:J16) -> 9 | L16: ='[3]CONS.ACEROS'!N624 -> 0 | M16: =+K16+L16 -> 9 | N16: ='[3]CONS.ACEROS'!P624 -> 2 | O16: ='[3]CONS.ACEROS'!Q624 -> 0 | P16: ='[3]CONS.ACEROS'!R624 -> 4 | Q16: ='[3]CONS.ACEROS'!S624 -> 0 | R16: ='[3]CONS.ACEROS'!T624 -> 8 | S16: ='[3]CONS.ACEROS'!U624 -> 4 | T16: ='[3]CONS.ACEROS'!V624 -> 8 | U16: =N16 -> 2 | V16: =SUM(O16:T16) -> 24 | W16: ='[3]CONS.ACEROS'!Y624 -> 0 | X16: ='[3]CONS.ACEROS'!Z624 -> 0 | Y16: ='[3]CONS.ACEROS'!AA624 -> 0 | Z16: =SUM(W16:Y16) -> 0 | AA16: =+Z16+U16+V16 -> 26
B17: 46281 | C17: ='[3]CONS.ACEROS'!E625 -> 9 | D17: ='[3]CONS.ACEROS'!F625 -> 9 | E17: ='[3]CONS.ACEROS'!G625 -> 0 | F17: ='[3]CONS.ACEROS'!H625 -> 0 | G17: ='[3]CONS.ACEROS'!I625 -> 0 | H17: ='[3]CONS.ACEROS'!J625 -> 0 | I17: ='[3]CONS.ACEROS'!K625 -> 11 | J17: ='[3]CONS.ACEROS'!L625 -> 0 | K17: =SUM(C17:J17) -> 29 | L17: ='[3]CONS.ACEROS'!N625 -> 9 | N17: ='[3]CONS.ACEROS'!P625 -> 2 | O17: ='[3]CONS.ACEROS'!Q625 -> 0 | P17: ='[3]CONS.ACEROS'!R625 -> 0 | Q17: ='[3]CONS.ACEROS'!S625 -> 0 | R17: ='[3]CONS.ACEROS'!T625 -> 6 | S17: ='[3]CONS.ACEROS'!U625 -> 4 | T17: ='[3]CONS.ACEROS'!V625 -> 6 | U17: =N17 -> 2 | V17: =SUM(O17:T17) -> 16 | W17: ='[3]CONS.ACEROS'!Y625 -> 0 | X17: ='[3]CONS.ACEROS'!Z625 -> 6 | Y17: ='[3]CONS.ACEROS'!AA625 -> 0 | Z17: =SUM(W17:Y17) -> 6 | AA17: =+Z17+U17+V17 -> 24
B18: 46282 | C18: ='[3]CONS.ACEROS'!E626 -> 0 | D18: ='[3]CONS.ACEROS'!F626 -> 0 | E18: ='[3]CONS.ACEROS'!G626 -> 0 | F18: ='[3]CONS.ACEROS'!H626 -> 0 | G18: ='[3]CONS.ACEROS'!I626 -> 0 | H18: ='[3]CONS.ACEROS'!J626 -> 0 | I18: ='[3]CONS.ACEROS'!K626 -> 0 | J18: ='[3]CONS.ACEROS'!L626 -> 0 | K18: =SUM(C18:J18) -> 0 | L18: ='[3]CONS.ACEROS'!N626 -> 0 | M18: =+K18+L18 -> 0 | N18: ='[3]CONS.ACEROS'!P626 -> 4 | O18: ='[3]CONS.ACEROS'!Q626 -> 2 | P18: ='[3]CONS.ACEROS'!R626 -> 0 | Q18: ='[3]CONS.ACEROS'!S626 -> 4 | R18: ='[3]CONS.ACEROS'!T626 -> 4 | S18: ='[3]CONS.ACEROS'!U626 -> 6 | T18: ='[3]CONS.ACEROS'!V626 -> 0 | U18: =N18 -> 4 | V18: =SUM(O18:T18) -> 16 | W18: ='[3]CONS.ACEROS'!Y626 -> 0 | X18: ='[3]CONS.ACEROS'!Z626 -> 7 | Y18: ='[3]CONS.ACEROS'!AA626 -> 0 | Z18: =SUM(W18:Y18) -> 7 | AA18: =+Z18+U18+V18 -> 27
B19: 46283 | C19: ='[3]CONS.ACEROS'!E627 -> 10 | D19: ='[3]CONS.ACEROS'!F627 -> 0 | E19: ='[3]CONS.ACEROS'!G627 -> 0 | F19: ='[3]CONS.ACEROS'!H627 -> 0 | G19: ='[3]CONS.ACEROS'!I627 -> 18 | H19: ='[3]CONS.ACEROS'!J627 -> 9 | I19: ='[3]CONS.ACEROS'!K627 -> 0 | J19: ='[3]CONS.ACEROS'!L627 -> 15 | K19: =SUM(C19:J19) -> 52 | L19: ='[3]CONS.ACEROS'!N627 -> 9 | M19: =+K19+L19 -> 61 | N19: ='[3]CONS.ACEROS'!P627 -> 4 | O19: ='[3]CONS.ACEROS'!Q627 -> 0 | P19: ='[3]CONS.ACEROS'!R627 -> 0 | Q19: ='[3]CONS.ACEROS'!S627 -> 0 | R19: ='[3]CONS.ACEROS'!T627 -> 6 | S19: ='[3]CONS.ACEROS'!U627 -> 6 | T19: ='[3]CONS.ACEROS'!V627 -> 0 | U19: =N19 -> 4 | V19: =SUM(O19:T19) -> 12 | W19: ='[3]CONS.ACEROS'!Y627 -> 2 | X19: ='[3]CONS.ACEROS'!Z627 -> 6 | Y19: ='[3]CONS.ACEROS'!AA627 -> 0 | Z19: =SUM(W19:Y19) -> 8 | AA19: =+Z19+U19+V19 -> 24
B20: 46284 | C20: ='[3]CONS.ACEROS'!E628 -> 0 | D20: ='[3]CONS.ACEROS'!F628 -> 0 | E20: ='[3]CONS.ACEROS'!G628 -> 0 | F20: ='[3]CONS.ACEROS'!H628 -> 0 | G20: ='[3]CONS.ACEROS'!I628 -> 0 | H20: ='[3]CONS.ACEROS'!J628 -> 0 | I20: ='[3]CONS.ACEROS'!K628 -> 0 | J20: ='[3]CONS.ACEROS'!L628 -> 0 | K20: =SUM(C20:J20) -> 0 | L20: ='[3]CONS.ACEROS'!N628 -> 0 | M20: =+K20+L20 -> 0 | N20: ='[3]CONS.ACEROS'!P628 -> 2 | O20: ='[3]CONS.ACEROS'!Q628 -> 0 | P20: ='[3]CONS.ACEROS'!R628 -> 0 | Q20: ='[3]CONS.ACEROS'!S628 -> 0 | R20: ='[3]CONS.ACEROS'!T628 -> 0 | S20: ='[3]CONS.ACEROS'!U628 -> 4 | T20: ='[3]CONS.ACEROS'!V628 -> 0 | U20: =N20 -> 2 | V20: =SUM(O20:T20) -> 4 | W20: ='[3]CONS.ACEROS'!Y628 -> 0 | X20: ='[3]CONS.ACEROS'!Z628 -> 2 | Y20: ='[3]CONS.ACEROS'!AA628 -> 0 | Z20: =SUM(W20:Y20) -> 2 | AA20: =+Z20+U20+V20 -> 8
B21: 46285 | C21: ='[3]CONS.ACEROS'!E629 -> 0 | D21: ='[3]CONS.ACEROS'!F629 -> 0 | E21: ='[3]CONS.ACEROS'!G629 -> 0 | F21: ='[3]CONS.ACEROS'!H629 -> 0 | G21: ='[3]CONS.ACEROS'!I629 -> 0 | H21: ='[3]CONS.ACEROS'!J629 -> 0 | I21: ='[3]CONS.ACEROS'!K629 -> 0 | J21: ='[3]CONS.ACEROS'!L629 -> 0 | K21: =SUM(C21:J21) -> 0 | L21: ='[3]CONS.ACEROS'!N629 -> 0 | M21: =+K21+L21 -> 0 | N21: ='[3]CONS.ACEROS'!P629 -> 0 | O21: ='[3]CONS.ACEROS'!Q629 -> 0 | P21: ='[3]CONS.ACEROS'!R629 -> 0 | Q21: ='[3]CONS.ACEROS'!S629 -> 0 | R21: ='[3]CONS.ACEROS'!T629 -> 0 | S21: ='[3]CONS.ACEROS'!U629 -> 0 | T21: ='[3]CONS.ACEROS'!V629 -> 0 | U21: =N21 -> 0 | V21: =SUM(O21:T21) -> 0 | W21: ='[3]CONS.ACEROS'!Y629 -> 0 | X21: ='[3]CONS.ACEROS'!Z629 -> 0 | Y21: ='[3]CONS.ACEROS'!AA629 -> 0 | Z21: =SUM(W21:Y21) -> 0 | AA21: =+Z21+U21+V21 -> 0
B22: 46286 | C22: ='[3]CONS.ACEROS'!E630 -> 0 | D22: ='[3]CONS.ACEROS'!F630 -> 0 | E22: ='[3]CONS.ACEROS'!G630 -> 0 | F22: ='[3]CONS.ACEROS'!H630 -> 0 | G22: ='[3]CONS.ACEROS'!I630 -> 0 | H22: ='[3]CONS.ACEROS'!J630 -> 0 | I22: ='[3]CONS.ACEROS'!K630 -> 0 | J22: ='[3]CONS.ACEROS'!L630 -> 0 | K22: =SUM(C22:J22) -> 0 | L22: ='[3]CONS.ACEROS'!N630 -> 0 | M22: =+K22+L22 -> 0 | N22: ='[3]CONS.ACEROS'!P630 -> 4 | O22: ='[3]CONS.ACEROS'!Q630 -> 0 | P22: ='[3]CONS.ACEROS'!R630 -> 0 | Q22: ='[3]CONS.ACEROS'!S630 -> 6 | R22: ='[3]CONS.ACEROS'!T630 -> 0 | S22: ='[3]CONS.ACEROS'!U630 -> 6 | T22: ='[3]CONS.ACEROS'!V630 -> 0 | U22: =N22 -> 4 | V22: =SUM(O22:T22) -> 12 | W22: ='[3]CONS.ACEROS'!Y630 -> 0 | X22: ='[3]CONS.ACEROS'!Z630 -> 0 | Y22: ='[3]CONS.ACEROS'!AA630 -> 0 | Z22: =SUM(W22:Y22) -> 0 | AA22: =+Z22+U22+V22 -> 16
B23: 46287 | C23: ='[3]CONS.ACEROS'!E631 -> 0 | D23: ='[3]CONS.ACEROS'!F631 -> 0 | E23: ='[3]CONS.ACEROS'!G631 -> 0 | F23: ='[3]CONS.ACEROS'!H631 -> 0 | G23: ='[3]CONS.ACEROS'!I631 -> 0 | H23: ='[3]CONS.ACEROS'!J631 -> 0 | I23: ='[3]CONS.ACEROS'!K631 -> 0 | J23: ='[3]CONS.ACEROS'!L631 -> 0 | K23: =SUM(C23:J23) -> 0 | L23: ='[3]CONS.ACEROS'!N631 -> 0 | M23: =+K23+L23 -> 0 | N23: ='[3]CONS.ACEROS'!P631 -> 0 | O23: ='[3]CONS.ACEROS'!Q631 -> 2 | P23: ='[3]CONS.ACEROS'!R631 -> 0 | Q23: ='[3]CONS.ACEROS'!S631 -> 0 | R23: ='[3]CONS.ACEROS'!T631 -> 0 | S23: ='[3]CONS.ACEROS'!U631 -> 0 | T23: ='[3]CONS.ACEROS'!V631 -> 0 | U23: =N23 -> 0 | V23: =SUM(O23:T23) -> 2 | W23: ='[3]CONS.ACEROS'!Y631 -> 0 | X23: ='[3]CONS.ACEROS'!Z631 -> 0 | Y23: ='[3]CONS.ACEROS'!AA631 -> 0 | Z23: =SUM(W23:Y23) -> 0 | AA23: =+Z23+U23+V23 -> 2
B24: 46288 | C24: ='[3]CONS.ACEROS'!E632 -> 9 | D24: ='[3]CONS.ACEROS'!F632 -> 0 | E24: ='[3]CONS.ACEROS'!G632 -> 9 | F24: ='[3]CONS.ACEROS'!H632 -> 12 | G24: ='[3]CONS.ACEROS'!I632 -> 6 | H24: ='[3]CONS.ACEROS'!J632 -> 9 | I24: ='[3]CONS.ACEROS'!K632 -> 0 | J24: ='[3]CONS.ACEROS'!L632 -> 7 | K24: =SUM(C24:J24) -> 52 | L24: ='[3]CONS.ACEROS'!N632 -> 8 | M24: =+K24+L24 -> 60 | N24: ='[3]CONS.ACEROS'!P632 -> 0 | O24: ='[3]CONS.ACEROS'!Q632 -> 8 | P24: ='[3]CONS.ACEROS'!R632 -> 10 | Q24: ='[3]CONS.ACEROS'!S632 -> 0 | R24: ='[3]CONS.ACEROS'!T632 -> 0 | S24: ='[3]CONS.ACEROS'!U632 -> 0 | T24: ='[3]CONS.ACEROS'!V632 -> 0 | U24: =N24 -> 0 | V24: =SUM(O24:T24) -> 18 | W24: ='[3]CONS.ACEROS'!Y632 -> 0 | X24: ='[3]CONS.ACEROS'!Z632 -> 0 | Y24: ='[3]CONS.ACEROS'!AA632 -> 8 | Z24: =SUM(W24:Y24) -> 8 | AA24: =+Z24+U24+V24 -> 26
B25: 46289 | C25: ='[3]CONS.ACEROS'!E633 -> 9 | D25: ='[3]CONS.ACEROS'!F633 -> 12 | E25: ='[3]CONS.ACEROS'!G633 -> 7 | F25: ='[3]CONS.ACEROS'!H633 -> 0 | G25: ='[3]CONS.ACEROS'!I633 -> 9 | H25: ='[3]CONS.ACEROS'!J633 -> 11 | I25: ='[3]CONS.ACEROS'!K633 -> 9 | J25: ='[3]CONS.ACEROS'!L633 -> 11 | K25: =SUM(C25:J25) -> 68 | L25: ='[3]CONS.ACEROS'!N633 -> 10 | M25: =+K25+L25 -> 78 | N25: ='[3]CONS.ACEROS'!P633 -> 0 | O25: ='[3]CONS.ACEROS'!Q633 -> 0 | P25: ='[3]CONS.ACEROS'!R633 -> 0 | Q25: ='[3]CONS.ACEROS'!S633 -> 0 | R25: ='[3]CONS.ACEROS'!T633 -> 0 | S25: ='[3]CONS.ACEROS'!U633 -> 0 | T25: ='[3]CONS.ACEROS'!V633 -> 0 | U25: =N25 -> 0 | V25: =SUM(O25:T25) -> 0 | W25: ='[3]CONS.ACEROS'!Y633 -> 0 | X25: ='[3]CONS.ACEROS'!Z633 -> 0 | Y25: ='[3]CONS.ACEROS'!AA633 -> 0 | Z25: =SUM(W25:Y25) -> 0 | AA25: =+Z25+U25+V25 -> 0
B26: 46290 | C26: ='[3]CONS.ACEROS'!E634 -> 18 | D26: ='[3]CONS.ACEROS'!F634 -> 18 | E26: ='[3]CONS.ACEROS'!G634 -> 14 | F26: ='[3]CONS.ACEROS'!H634 -> 10 | G26: ='[3]CONS.ACEROS'!I634 -> 14 | H26: ='[3]CONS.ACEROS'!J634 -> 18 | I26: ='[3]CONS.ACEROS'!K634 -> 0 | J26: ='[3]CONS.ACEROS'!L634 -> 9 | K26: =SUM(C26:J26) -> 101 | L26: ='[3]CONS.ACEROS'!N634 -> 0 | M26: =+K26+L26 -> 101 | N26: ='[3]CONS.ACEROS'!P634 -> 4 | O26: ='[3]CONS.ACEROS'!Q634 -> 0 | P26: ='[3]CONS.ACEROS'!R634 -> 0 | Q26: ='[3]CONS.ACEROS'!S634 -> 0 | R26: ='[3]CONS.ACEROS'!T634 -> 0 | S26: ='[3]CONS.ACEROS'!U634 -> 4 | T26: ='[3]CONS.ACEROS'!V634 -> 4 | U26: =N26 -> 4 | V26: =SUM(O26:T26) -> 8 | W26: ='[3]CONS.ACEROS'!Y634 -> 0 | X26: ='[3]CONS.ACEROS'!Z634 -> 4 | Y26: ='[3]CONS.ACEROS'!AA634 -> 0 | Z26: =SUM(W26:Y26) -> 4 | AA26: =+Z26+U26+V26 -> 16
B27: 46291 | C27: ='[3]CONS.ACEROS'!E635 -> 18 | D27: ='[3]CONS.ACEROS'!F635 -> 15 | E27: ='[3]CONS.ACEROS'!G635 -> 0 | F27: ='[3]CONS.ACEROS'!H635 -> 0 | G27: ='[3]CONS.ACEROS'!I635 -> 0 | H27: ='[3]CONS.ACEROS'!J635 -> 0 | I27: ='[3]CONS.ACEROS'!K635 -> 0 | J27: ='[3]CONS.ACEROS'!L635 -> 0 | K27: =SUM(C27:J27) -> 33 | L27: ='[3]CONS.ACEROS'!N635 -> 0 | M27: =+K27+L27 -> 33 | N27: ='[3]CONS.ACEROS'!P635 -> 2 | O27: ='[3]CONS.ACEROS'!Q635 -> 0 | P27: ='[3]CONS.ACEROS'!R635 -> 0 | Q27: ='[3]CONS.ACEROS'!S635 -> 4 | R27: ='[3]CONS.ACEROS'!T635 -> 0 | S27: ='[3]CONS.ACEROS'!U635 -> 6 | T27: ='[3]CONS.ACEROS'!V635 -> 6 | U27: =N27 -> 2 | V27: =SUM(O27:T27) -> 16 | W27: ='[3]CONS.ACEROS'!Y635 -> 2 | X27: ='[3]CONS.ACEROS'!Z635 -> 4 | Y27: ='[3]CONS.ACEROS'!AA635 -> 6 | Z27: =SUM(W27:Y27) -> 12 | AA27: =+Z27+U27+V27 -> 30
B28: 46292 | C28: ='[3]CONS.ACEROS'!E636 -> 0 | D28: ='[3]CONS.ACEROS'!F636 -> 0 | E28: ='[3]CONS.ACEROS'!G636 -> 0 | F28: ='[3]CONS.ACEROS'!H636 -> 0 | G28: ='[3]CONS.ACEROS'!I636 -> 0 | H28: ='[3]CONS.ACEROS'!J636 -> 0 | I28: ='[3]CONS.ACEROS'!K636 -> 0 | J28: ='[3]CONS.ACEROS'!L636 -> 0 | K28: =SUM(C28:J28) -> 0 | L28: ='[3]CONS.ACEROS'!N636 -> 0 | M28: =+K28+L28 -> 0 | N28: ='[3]CONS.ACEROS'!P636 -> 0 | O28: ='[3]CONS.ACEROS'!Q636 -> 0 | P28: ='[3]CONS.ACEROS'!R636 -> 0 | Q28: ='[3]CONS.ACEROS'!S636 -> 0 | R28: ='[3]CONS.ACEROS'!T636 -> 0 | S28: ='[3]CONS.ACEROS'!U636 -> 0 | T28: ='[3]CONS.ACEROS'!V636 -> 0 | U28: =N28 -> 0 | V28: =SUM(O28:T28) -> 0 | W28: ='[3]CONS.ACEROS'!Y636 -> 0 | X28: ='[3]CONS.ACEROS'!Z636 -> 0 | Y28: ='[3]CONS.ACEROS'!AA636 -> 0 | Z28: =SUM(W28:Y28) -> 0 | AA28: =+Z28+U28+V28 -> 0
B29: 46293 | C29: ='[3]CONS.ACEROS'!E637 -> 0 | D29: ='[3]CONS.ACEROS'!F637 -> 0 | E29: ='[3]CONS.ACEROS'!G637 -> 0 | F29: ='[3]CONS.ACEROS'!H637 -> 0 | G29: ='[3]CONS.ACEROS'!I637 -> 0 | H29: ='[3]CONS.ACEROS'!J637 -> 0 | I29: ='[3]CONS.ACEROS'!K637 -> 0 | J29: ='[3]CONS.ACEROS'!L637 -> 0 | K29: =SUM(C29:J29) -> 0 | L29: ='[3]CONS.ACEROS'!N637 -> 0 | M29: =+K29+L29 -> 0 | N29: ='[3]CONS.ACEROS'!P637 -> 0 | O29: ='[3]CONS.ACEROS'!Q637 -> 0 | P29: ='[3]CONS.ACEROS'!R637 -> 0 | Q29: ='[3]CONS.ACEROS'!S637 -> 0 | R29: ='[3]CONS.ACEROS'!T637 -> 0 | S29: ='[3]CONS.ACEROS'!U637 -> 6 | T29: ='[3]CONS.ACEROS'!V637 -> 6 | U29: =N29 -> 0 | V29: =SUM(O29:T29) -> 12 | W29: ='[3]CONS.ACEROS'!Y637 -> 0 | X29: ='[3]CONS.ACEROS'!Z637 -> 0 | Y29: ='[3]CONS.ACEROS'!AA637 -> 0 | Z29: =SUM(W29:Y29) -> 0 | AA29: =+Z29+U29+V29 -> 12
... B31: 46295 | C31: ='[3]CONS.ACEROS'!E639 -> 0 | D31: ='[3]CONS.ACEROS'!F639 -> 0 | E31: ='[3]CONS.ACEROS'!G639 -> 0 | F31: ='[3]CONS.ACEROS'!H639 -> 0 | G31: ='[3]CONS.ACEROS'!I639 -> 0 | H31: ='[3]CONS.ACEROS'!J639 -> 0 | I31: ='[3]CONS.ACEROS'!K639 -> 0 | J31: ='[3]CONS.ACEROS'!L639 -> 0 | K31: =SUM(C31:J31) -> 0 | L31: ='[3]CONS.ACEROS'!N639 -> 0 | M31: =+K31+L31 -> 0 | N31: ='[3]CONS.ACEROS'!P639 -> 0 | O31: ='[3]CONS.ACEROS'!Q639 -> 0 | P31: ='[3]CONS.ACEROS'!R639 -> 0 | Q31: ='[3]CONS.ACEROS'!S639 -> 0 | R31: ='[3]CONS.ACEROS'!T639 -> 0 | S31: ='[3]CONS.ACEROS'!U639 -> 0 | T31: ='[3]CONS.ACEROS'!V639 -> 0 | U31: =N31 -> 0 | V31: =SUM(O31:T31) -> 0 | W31: ='[3]CONS.ACEROS'!Y639 -> 0 | X31: ='[3]CONS.ACEROS'!Z639 -> 0 | Y31: ='[3]CONS.ACEROS'!AA639 -> 0 | Z31: =SUM(W31:Y31) -> 0 | AA31: =+Z31+U31+V31 -> 0
B33: Agregado de barras en unidades barra 1-8 peso 241kg / 9 peso 236kg
B34: Agregado de conos y bolas en Toneladas
B36: STD | C36: CARGA NOMINAL MOLINO DE BARRAS | M36: CARGA NOMINAL MOLINO DE BOLAS
C37: 92 | D37: 90 | E37: 90 | F37: 90 | G37: 92 | H37: 92 | I37: 92 | J37: 92 | K37: 65 | L37: STD | M37: 92 | N37: 90 | O37: 90 | P37: 90 | Q37: 92 | R37: 92 | S37: 92 | T37: 89 | U37: 79 | V37: 88
B38: FECHA | C38: RM - 1 | D38: RM - 2 | E38: RM - 3 | F38: RM - 4 | G38: RM - 5 | H38: RM - 6 | I38: RM - 7 | J38: RM - 8 | K38: RM - 9 | M38: BM - 1 | N38: BM - 2 | O38: BM - 3 | P38: BM - 4 | Q38: BM - 5 | R38: BM - 6 | S38: BM - 7 | T38: BM - 8 | U38: BM - 9 | V38: BM - 10
B39: 46266 | D39: 88.3 | E39: 87.5 | F39: 88.2 | G39: 87.4 | H39: 88.5 | I39: 92.1 | J39: 85.6 | K39: 63.7 | M39: 89.7 | N39: 85.7 | O39: 84.8 | P39: 91.7 | Q39: 90.6 | R39: 91.2 | S39: 96.2 | T39: 89.3 | U39: 74.9 | V39: 82.1
B40: 46267 | C40: 94.6 | E40: 93.1 | F40: 92.7 | G40: 92.3 | H40: 96.4 | I40: 89.3 | J40: 93.5 | K40: 65.1 | M40: 90.9 | N40: 87.4 | O40: 91 | P40: 87.2 | Q40: 90.9 | R40: 91.9 | S40: 87.7 | T40: 88.8 | U40: 73.5 | V40: 81.2
B41: 46268 | C41: 91.5 | E41: 90 | F41: 91.5 | G41: 91.8 | H41: 93.7 | J41: 90.6 | K41: 63.1 | M41: 90 | N41: 93.5 | O41: 91.4 | P41: 82.8 | Q41: 93.6 | R41: 89.8 | S41: 90.2 | T41: 87.7 | U41: 73.2 | V41: 85.6
B42: 46269 | C42: 94.9 | E42: 89.8 | F42: 90 | H42: 90.8 | I42: 92.1 | J42: 95 | M42: 90.8 | N42: 95.9 | O42: 93 | P42: 86.9 | R42: 90.3 | S42: 92.7 | T42: 86.3 | U42: 77.4 | V42: 85.4
B43: 46270 | C43: 93.7 | D43: 93.3 | E43: 95.4 | H43: 93.9 | I43: 95.8 | J43: 94.1 | K43: 66.8 | M43: 92.9 | N43: 93.5 | O43: 87.1 | P43: 94.4 | R43: 95.2 | S43: 95 | T43: 87.9 | U43: 76.6 | V43: 84.8
B44: 46271
B45: 46272 | C45: 90 | D45: 90.2 | E45: 91.6 | H45: 91.8 | I45: 90.4 | J45: 91.4 | K45: 64.7 | M45: 91.6 | N45: 88 | O45: 91 | P45: 95.5 | R45: 90.3 | S45: 90.3 | T45: 89.5 | U45: 78.9 | V45: 90.4
B46: 46273 | C46: 93.2 | D46: 88.7 | E46: 88.7 | H46: 93.1 | I46: 94.1 | J46: 92.1 | K46: 63.6 | M46: 91 | N46: 91.1 | O46: 88 | P46: 95.9 | R46: 94.4 | S46: 87.8 | T46: 90.8 | U46: 77.7 | V46: 89.2
B47: 46274 | C47: 91.4 | D47: 92.5 | E47: 93.9 | G47: 88.9 | H47: 90.6 | I47: 90 | J47: 93.5 | K47: 64.9 | M47: 90.9 | N47: 91.8 | O47: 89.8 | P47: 95.4 | Q47: 88.3 | R47: 94.2 | S47: 91.9 | T47: 90.2 | U47: 79.1 | V47: 87.4
B48: 46275 | C48: 95 | D48: 89.5 | E48: 91.8 | G48: 93.9 | H48: 94.8 | I48: 92.5 | J48: 92 | M48: 90.9 | N48: 91 | O48: 93.8 | P48: 93.4 | Q48: 87.3 | R48: 94.2 | S48: 92.1 | T48: 91.2 | V48: 88.9
B49: 46276 | C49: 92.3 | D49: 88.7 | E49: 86.2 | G49: 92.3 | H49: 93.1 | I49: 94.4 | J49: 93.1 | K49: 65.4 | M49: 92.6 | N49: 88.9 | O49: 91.7 | P49: 90.5 | Q49: 90.3 | R49: 91.9 | S49: 91.7 | T49: 90.9 | U49: 78.7 | V49: 88.9
B50: 46277
B51: 46278
B52: 46279 | D52: 91.4 | E52: 90 | F52: 93.7 | G52: 91.4 | H52: 93.1 | I52: 94.8 | J52: 95.4 | K52: 62.7 | M52: 92.9 | N52: 90 | O52: 88.9 | Q52: 87.7 | R52: 89.7 | S52: 87.5 | T52: 90 | U52: 76 | V52: 88.8 | W52: .
B53: 46280 | C53: 92.5 | D53: 90.8 | G53: 94.4 | H53: 91 | I53: 93.1 | J53: 95.2 | K53: 67.7 | M53: 91.3 | N53: 92.2 | O53: 94.9 | Q53: 87.9 | R53: 90 | S53: 88.9 | T53: 91.7 | U53: 76.3
B54: 46281 | C54: 91.8 | D54: 89.8 | G54: 92.5 | H54: 92.9 | I54: 91.8 | J54: 92.7 | K54: 64.4 | M54: 92.5 | N54: 92.3 | O54: 92.5 | P54: 91.2 | Q54: 89.1 | R54: 90.4 | S54: 88.2 | T54: 90.9 | U54: 75.8
B55: 46282 | C55: 90.9 | D55: 93.3 | G55: 90.2 | H55: 90.8 | J55: 92.1 | K55: 66.3 | M55: 92.1 | N55: 90.7 | O55: 92.2 | P55: 85 | Q55: 91.2 | R55: 87.1 | T55: 90.1 | U55: 76.8
B56: 46283 | C56: 90.5 | D56: 90.2 | F56: 91.4 | G56: 87.5 | H56: 90.2 | J56: 89.5 | K56: 64.8 | M56: 90.3 | N56: 91.4 | O56: 90.4 | P56: 93.3 | Q56: 90.3 | R56: 88.4 | S56: 83.3 | T56: 89.4 | U56: 77.3
B57: 46284 | C57: 91.6 | D57: 86.8 | G57: 94.1 | H57: 92 | I57: 0 | J57: 94.4 | K57: 65.3 | M57: 91.6 | N57: 92.9 | O57: 89.1 | Q57: 92.2 | R57: 89.2 | T57: 90 | U57: 79.1
B58: 46285
B59: 46286 | C59: 89.1 | E59: 89.5 | F59: 87.2 | G59: 90.4 | H59: 88.1 | J59: 90 | K59: 63.7 | M59: 89.6 | N59: 86.8 | O59: 82.9 | P59: 87 | Q59: 90.3 | R59: 92.8 | T59: 89.5 | U59: 76.9 | V59: 84.4
B60: 46287 | C60: 87.4 | E60: 87.2 | F60: 85.1 | G60: 88.7 | H60: 86.4 | J60: 89.1 | K60: 63.5 | M60: 90.9 | N60: 81.4 | O60: 83.9 | P60: 85.5 | Q60: 94.6 | R60: 88.2 | S60: 86.6 | T60: 89.6 | U60: 78.4 | V60: 79.3
B61: 46288 | C61: 85.4 | E61: 86.6 | F61: 80.7 | G61: 86.6 | H61: 84.1 | I61: 91.8 | J61: 86.6 | K61: 62 | M61: 90.8 | N61: 80.5 | O61: 81.5 | P61: 83.8 | Q61: 94.4 | R61: 88 | S61: 86 | T61: 88 | U61: 76.7 | V61: 78.9
B62: 46289 | C62: 88.5 | D62: 83 | E62: 89.5 | G62: 88.1 | H62: 87.4 | I62: 89.7 | J62: 88.1 | K62: 63 | M62: 90.1 | N62: 88.5 | Q62: 97.6 | R62: 87.9 | S62: 84.9 | T62: 87.7 | U62: 75.6 | V62: 82.1
B63: 46290 | C63: 87.9 | D63: 84.5 | E63: 88.5 | G63: 90.4 | H63: 89.8 | I63: 92.1 | J63: 91.4 | K63: 62.8 | M63: 85.2 | N63: 92.5 | P63: 83.5 | Q63: 97.3 | R63: 85.4 | S63: 83.6 | T63: 86.9 | U63: 74.7 | V63: 78.4
B64: 46291 | C64: 87.9 | D64: 87.7 | E64: 92 | G64: 93.7 | H64: 92.9 | I64: 92.3 | J64: 95 | M64: 90.3 | N64: 92.2 | O64: 90.7 | P64: 82.6 | Q64: 96.7 | R64: 86 | S64: 83.9 | T64: 86.1 | V64: 77.5
B65: 46292
B66: 46293
B67: 46294
B68: 46295

Sheet MEDIOS MOLEDORES
E3: FECHA | F3: CARGA NOMINAL MOLINO DE BARRAS | O3: CARGA NOMINAL MOLINO DE BOLAS
F4: RM - 1 | G4: RM - 2 | H4: RM - 3 | I4: RM - 4 | J4: RM - 5 | K4: RM - 6 | L4: RM - 7 | M4: RM - 8 | N4: RM - 9 | O4: BM - 1 | P4: BM - 2 | Q4: BM - 3 | R4: BM - 4 | S4: BM - 5 | T4: BM - 6 | U4: BM - 7 | V4: BM - 8 | W4: BM - 9 | X4: BM - 10
B5: RM1/2/3/4/5/6/7/8 | C5: RM9 | E5: PROCESOS | F5: 92 | G5: 92 | H5: 92 | I5: 92 | J5: 92 | K5: 92 | L5: 92 | M5: 92 | N5: 65 | O5: 92 | P5: 90 | Q5: 90 | R5: 90 | S5: 92 | T5: 92 | U5: 92 | V5: 89 | W5: 79 | X5: 88 | AB5: BM2/3/4 | AC5: BM1/5/6/7 | AD5: BM8 | AE5: BM9 | AF5: BM10
B6: 92 | C6: 65 | E6: 46235 | AB6: 90 | AC6: 92 | AD6: 89 | AE6: 79 | AF6: 88
B7: 92 | C7: 65 | E7: 46236 | F7: 0 | G7: 0 | AB7: 90 | AC7: 92 | AD7: 89 | AE7: 79 | AF7: 88
B8: 92 | C8: 65 | E8: 46237 | F8: 0 | G8: 0 | N8: 0 | AB8: 90 | AC8: 92 | AD8: 89 | AE8: 79 | AF8: 88
B9: 92 | C9: 65 | E9: 46238 | F9: 90.6 | G9: 85.3 | H9: 93.5 | I9: 91.8 | J9: 89.8 | K9: 93.9 | L9: 90.6 | M9: 87.5 | O9: 83.5 | P9: 64.6 | Q9: 95.3 | R9: 87.4 | S9: 91.4 | T9: 91.9 | U9: 93.2 | V9: 90.9 | W9: 77.7 | X9: 72.5 | AB9: 90 | AC9: 92 | AD9: 89 | AE9: 79 | AF9: 88
B10: 92 | C10: 65 | E10: 46239 | G10: 81.6 | H10: 0 | I10: 87.9 | J10: 87.4 | K10: 90.2 | L10: 86.4 | M10: 86.2 | O10: 86.1 | P10: 60.9 | Q10: 96.6 | R10: 85.7 | T10: 88.6 | U10: 92.3 | V10: 86.9 | W10: 73.9 | X10: 72.3 | AB10: 90 | AC10: 92 | AD10: 89 | AE10: 79 | AF10: 88
B11: 92 | C11: 65 | E11: 46240 | F11: 89.3 | G11: 0 | H11: 91.2 | I11: 91.4 | J11: 90 | K11: 94.3 | L11: 89.3 | M11: 83.7 | N11: 0 | O11: 83.5 | P11: 62 | Q11: 99.8 | R11: 77.9 | S11: 90.8 | T11: 87.8 | U11: 93.7 | V11: 87.2 | W11: 75.5 | X11: 79.9 | AB11: 90 | AC11: 92 | AD11: 89 | AE11: 79 | AF11: 88
B12: 92 | C12: 65 | E12: 46241 | F12: 0 | G12: 0 | H12: 92 | I12: 89.7 | J12: 88.1 | K12: 93.1 | L12: 88.1 | M12: 82.2 | N12: 49.3 | O12: 0 | P12: 60.8 | Q12: 99.9 | R12: 78.9 | S12: 93.2 | T12: 92.5 | U12: 92.7 | V12: 88 | W12: 75.6 | X12: 74.7 | AB12: 90 | AC12: 92 | AD12: 89 | AE12: 79 | AF12: 88
B13: 92 | C13: 65 | E13: 46242 | F13: 93.2 | G13: 0 | H13: 89.3 | I13: 91.6 | J13: 91.2 | K13: 91 | L13: 88.1 | M13: 82.2 | O13: 86.3 | P13: 68.6 | Q13: 95.7 | R13: 90.7 | S13: 92.2 | T13: 92.2 | U13: 90.4 | V13: 90.4 | W13: 77.6 | X13: 73.8 | AB13: 90 | AC13: 92 | AD13: 89 | AE13: 79 | AF13: 88
B14: 92 | C14: 65 | E14: 46243 | F14: 90.2 | G14: 0 | H14: 86 | I14: 90.8 | J14: 88.9 | K14: 89.3 | L14: 87.7 | M14: 85.4 | O14: 91.1 | P14: 70.8 | Q14: 0 | R14: 0 | S14: 92.5 | T14: 92.4 | U14: 91.3 | V14: 91 | W14: 79.5 | X14: 74.4 | AB14: 90 | AC14: 92 | AD14: 89 | AE14: 79 | AF14: 88
B15: 92 | C15: 65 | E15: 46244 | F15: =+'AGREGADO MEDIOS MOLEDORES'!C48 -> 95 | G15: =+'AGREGADO MEDIOS MOLEDORES'!D48 -> 89.5 | H15: =+'AGREGADO MEDIOS MOLEDORES'!E48 -> 91.8 | I15: =+'AGREGADO MEDIOS MOLEDORES'!F48 -> 0 | J15: =+'AGREGADO MEDIOS MOLEDORES'!G48 -> 93.9 | K15: =+'AGREGADO MEDIOS MOLEDORES'!H48 -> 94.8 | L15: =+'AGREGADO MEDIOS MOLEDORES'!I48 -> 92.5 | M15: =+'AGREGADO MEDIOS MOLEDORES'!J48 -> 92 | N15: =+'AGREGADO MEDIOS MOLEDORES'!K48 -> 0 | O15: =+'AGREGADO MEDIOS MOLEDORES'!M48 -> 90.9 | P15: =+'AGREGADO MEDIOS MOLEDORES'!N48 -> 91 | Q15: =+'AGREGADO MEDIOS MOLEDORES'!O48 -> 93.8 | R15: =+'AGREGADO MEDIOS MOLEDORES'!P48 -> 93.4 | S15: =+'AGREGADO MEDIOS MOLEDORES'!Q48 -> 87.3 | T15: =+'AGREGADO MEDIOS MOLEDORES'!R48 -> 94.2 | U15: =+'AGREGADO MEDIOS MOLEDORES'!S48 -> 92.1 | V15: =+'AGREGADO MEDIOS MOLEDORES'!T48 -> 91.2 | ... X15: =+'AGREGADO MEDIOS MOLEDORES'!V48 -> 88.9 | AB15: 90 | AC15: 92 | AD15: 89 | AE15: 79 | AF15: 88
B16: 92 | C16: 65 | E16: 46245 | F16: =+'AGREGADO MEDIOS MOLEDORES'!C49 -> 92.3 | G16: =+'AGREGADO MEDIOS MOLEDORES'!D49 -> 88.7 | H16: =+'AGREGADO MEDIOS MOLEDORES'!E49 -> 86.2 | I16: =+'AGREGADO MEDIOS MOLEDORES'!F49 -> 0 | J16: =+'AGREGADO MEDIOS MOLEDORES'!G49 -> 92.3 | K16: =+'AGREGADO MEDIOS MOLEDORES'!H49 -> 93.1 | L16: =+'AGREGADO MEDIOS MOLEDORES'!I49 -> 94.4 | M16: =+'AGREGADO MEDIOS MOLEDORES'!J49 -> 93.1 | N16: =+'AGREGADO MEDIOS MOLEDORES'!K49 -> 65.4 | O16: =+'AGREGADO MEDIOS MOLEDORES'!M49 -> 92.6 | P16: =+'AGREGADO MEDIOS MOLEDORES'!N49 -> 88.9 | Q16: =+'AGREGADO MEDIOS MOLEDORES'!O49 -> 91.7 | R16: =+'AGREGADO MEDIOS MOLEDORES'!P49 -> 90.5 | S16: =+'AGREGADO MEDIOS MOLEDORES'!Q49 -> 90.3 | T16: =+'AGREGADO MEDIOS MOLEDORES'!R49 -> 91.9 | U16: =+'AGREGADO MEDIOS MOLEDORES'!S49 -> 91.7 | V16: =+'AGREGADO MEDIOS MOLEDORES'!T49 -> 90.9 | ... X16: =+'AGREGADO MEDIOS MOLEDORES'!V49 -> 88.9 | AB16: 90 | AC16: 92 | AD16: 89 | AE16: 79 | AF16: 88
B17: 92 | C17: 65 | E17: 46246 | F17: =+'AGREGADO MEDIOS MOLEDORES'!C50 -> 0 | G17: =+'AGREGADO MEDIOS MOLEDORES'!D50 -> 0 | H17: =+'AGREGADO MEDIOS MOLEDORES'!E50 -> 0 | I17: =+'AGREGADO MEDIOS MOLEDORES'!F50 -> 0 | J17: =+'AGREGADO MEDIOS MOLEDORES'!G50 -> 0 | K17: =+'AGREGADO MEDIOS MOLEDORES'!H50 -> 0 | L17: =+'AGREGADO MEDIOS MOLEDORES'!I50 -> 0 | M17: =+'AGREGADO MEDIOS MOLEDORES'!J50 -> 0 | N17: =+'AGREGADO MEDIOS MOLEDORES'!K50 -> 0 | O17: =+'AGREGADO MEDIOS MOLEDORES'!M50 -> 0 | P17: =+'AGREGADO MEDIOS MOLEDORES'!N50 -> 0 | Q17: =+'AGREGADO MEDIOS MOLEDORES'!O50 -> 0 | R17: =+'AGREGADO MEDIOS MOLEDORES'!P50 -> 0 | S17: =+'AGREGADO MEDIOS MOLEDORES'!Q50 -> 0 | T17: =+'AGREGADO MEDIOS MOLEDORES'!R50 -> 0 | U17: =+'AGREGADO MEDIOS MOLEDORES'!S50 -> 0 | V17: =+'AGREGADO MEDIOS MOLEDORES'!T50 -> 0 | ... X17: =+'AGREGADO MEDIOS MOLEDORES'!V50 -> 0 | AB17: 90 | AC17: 92 | AD17: 89 | AE17: 79 | AF17: 88
B18: 92 | C18: 65 | E18: 46247 | F18: =+'AGREGADO MEDIOS MOLEDORES'!C51 -> 0 | G18: =+'AGREGADO MEDIOS MOLEDORES'!D51 -> 0 | H18: =+'AGREGADO MEDIOS MOLEDORES'!E51 -> 0 | I18: =+'AGREGADO MEDIOS MOLEDORES'!F51 -> 0 | J18: =+'AGREGADO MEDIOS MOLEDORES'!G51 -> 0 | K18: =+'AGREGADO MEDIOS MOLEDORES'!H51 -> 0 | L18: =+'AGREGADO MEDIOS MOLEDORES'!I51 -> 0 | M18: =+'AGREGADO MEDIOS MOLEDORES'!J51 -> 0 | N18: =+'AGREGADO MEDIOS MOLEDORES'!K51 -> 0 | O18: =+'AGREGADO MEDIOS MOLEDORES'!M51 -> 0 | P18: =+'AGREGADO MEDIOS MOLEDORES'!N51 -> 0 | Q18: =+'AGREGADO MEDIOS MOLEDORES'!O51 -> 0 | R18: =+'AGREGADO MEDIOS MOLEDORES'!P51 -> 0 | S18: =+'AGREGADO MEDIOS MOLEDORES'!Q51 -> 0 | T18: =+'AGREGADO MEDIOS MOLEDORES'!R51 -> 0 | U18: =+'AGREGADO MEDIOS MOLEDORES'!S51 -> 0 | V18: =+'AGREGADO MEDIOS MOLEDORES'!T51 -> 0 | ... X18: =+'AGREGADO MEDIOS MOLEDORES'!V51 -> 0 | AB18: 90 | AC18: 92 | AD18: 89 | AE18: 79 | AF18: 88
B19: 92 | C19: 65 | E19: 46248 | F19: =+'AGREGADO MEDIOS MOLEDORES'!C52 -> 0 | G19: =+'AGREGADO MEDIOS MOLEDORES'!D52 -> 91.4 | H19: =+'AGREGADO MEDIOS MOLEDORES'!E52 -> 90 | I19: =+'AGREGADO MEDIOS MOLEDORES'!F52 -> 93.7 | J19: =+'AGREGADO MEDIOS MOLEDORES'!G52 -> 91.4 | K19: =+'AGREGADO MEDIOS MOLEDORES'!H52 -> 93.1 | L19: =+'AGREGADO MEDIOS MOLEDORES'!I52 -> 94.8 | M19: =+'AGREGADO MEDIOS MOLEDORES'!J52 -> 95.4 | N19: =+'AGREGADO MEDIOS MOLEDORES'!K52 -> 62.7 | O19: =+'AGREGADO MEDIOS MOLEDORES'!M52 -> 92.9 | P19: =+'AGREGADO MEDIOS MOLEDORES'!N52 -> 90 | Q19: =+'AGREGADO MEDIOS MOLEDORES'!O52 -> 88.9 | R19: =+'AGREGADO MEDIOS MOLEDORES'!P52 -> 0 | S19: =+'AGREGADO MEDIOS MOLEDORES'!Q52 -> 87.7 | T19: =+'AGREGADO MEDIOS MOLEDORES'!R52 -> 89.7 | U19: =+'AGREGADO MEDIOS MOLEDORES'!S52 -> 87.5 | V19: =+'AGREGADO MEDIOS MOLEDORES'!T52 -> 90 | ... X19: =+'AGREGADO MEDIOS MOLEDORES'!V52 -> 88.8 | AB19: 90 | AC19: 92 | AD19: 89 | AE19: 79 | AF19: 88
B20: 92 | C20: 65 | E20: 46249 | F20: =+'AGREGADO MEDIOS MOLEDORES'!C53 -> 92.5 | G20: =+'AGREGADO MEDIOS MOLEDORES'!D53 -> 90.8 | H20: =+'AGREGADO MEDIOS MOLEDORES'!E53 -> 0 | I20: =+'AGREGADO MEDIOS MOLEDORES'!F53 -> 0 | J20: =+'AGREGADO MEDIOS MOLEDORES'!G53 -> 94.4 | K20: =+'AGREGADO MEDIOS MOLEDORES'!H53 -> 91 | L20: =+'AGREGADO MEDIOS MOLEDORES'!I53 -> 93.1 | M20: =+'AGREGADO MEDIOS MOLEDORES'!J53 -> 95.2 | N20: =+'AGREGADO MEDIOS MOLEDORES'!K53 -> 67.7 | O20: =+'AGREGADO MEDIOS MOLEDORES'!M53 -> 91.3 | P20: =+'AGREGADO MEDIOS MOLEDORES'!N53 -> 92.2 | Q20: =+'AGREGADO MEDIOS MOLEDORES'!O53 -> 94.9 | R20: =+'AGREGADO MEDIOS MOLEDORES'!P53 -> 0 | S20: =+'AGREGADO MEDIOS MOLEDORES'!Q53 -> 87.9 | T20: =+'AGREGADO MEDIOS MOLEDORES'!R53 -> 90 | U20: =+'AGREGADO MEDIOS MOLEDORES'!S53 -> 88.9 | V20: =+'AGREGADO MEDIOS MOLEDORES'!T53 -> 91.7 | ... X20: =+'AGREGADO MEDIOS MOLEDORES'!V53 -> 0 | AB20: 90 | AC20: 92 | AD20: 89 | AE20: 79 | AF20: 88
B21: 92 | C21: 65 | E21: 46250 | F21: =+'AGREGADO MEDIOS MOLEDORES'!C54 -> 91.8 | G21: =+'AGREGADO MEDIOS MOLEDORES'!D54 -> 89.8 | H21: =+'AGREGADO MEDIOS MOLEDORES'!E54 -> 0 | I21: =+'AGREGADO MEDIOS MOLEDORES'!F54 -> 0 | J21: =+'AGREGADO MEDIOS MOLEDORES'!G54 -> 92.5 | K21: =+'AGREGADO MEDIOS MOLEDORES'!H54 -> 92.9 | L21: =+'AGREGADO MEDIOS MOLEDORES'!I54 -> 91.8 | M21: =+'AGREGADO MEDIOS MOLEDORES'!J54 -> 92.7 | N21: =+'AGREGADO MEDIOS MOLEDORES'!K54 -> 64.4 | O21: =+'AGREGADO MEDIOS MOLEDORES'!M54 -> 92.5 | P21: =+'AGREGADO MEDIOS MOLEDORES'!N54 -> 92.3 | Q21: =+'AGREGADO MEDIOS MOLEDORES'!O54 -> 92.5 | R21: =+'AGREGADO MEDIOS MOLEDORES'!P54 -> 91.2 | S21: =+'AGREGADO MEDIOS MOLEDORES'!Q54 -> 89.1 | T21: =+'AGREGADO MEDIOS MOLEDORES'!R54 -> 90.4 | U21: =+'AGREGADO MEDIOS MOLEDORES'!S54 -> 88.2 | V21: =+'AGREGADO MEDIOS MOLEDORES'!T54 -> 90.9 | ... X21: =+'AGREGADO MEDIOS MOLEDORES'!V54 -> 0 | AB21: 90 | AC21: 92 | AD21: 89 | AE21: 79 | AF21: 88
B22: 92 | C22: 65 | E22: 46251 | F22: =+'AGREGADO MEDIOS MOLEDORES'!C55 -> 90.9 | G22: =+'AGREGADO MEDIOS MOLEDORES'!D55 -> 93.3 | H22: =+'AGREGADO MEDIOS MOLEDORES'!E55 -> 0 | I22: =+'AGREGADO MEDIOS MOLEDORES'!F55 -> 0 | J22: =+'AGREGADO MEDIOS MOLEDORES'!G55 -> 90.2 | K22: =+'AGREGADO MEDIOS MOLEDORES'!H55 -> 90.8 | L22: =+'AGREGADO MEDIOS MOLEDORES'!I55 -> 0 | M22: =+'AGREGADO MEDIOS MOLEDORES'!J55 -> 92.1 | N22: =+'AGREGADO MEDIOS MOLEDORES'!K55 -> 66.3 | O22: =+'AGREGADO MEDIOS MOLEDORES'!M55 -> 92.1 | P22: =+'AGREGADO MEDIOS MOLEDORES'!N55 -> 90.7 | Q22: =+'AGREGADO MEDIOS MOLEDORES'!O55 -> 92.2 | R22: =+'AGREGADO MEDIOS MOLEDORES'!P55 -> 85 | S22: =+'AGREGADO MEDIOS MOLEDORES'!Q55 -> 91.2 | T22: =+'AGREGADO MEDIOS MOLEDORES'!R55 -> 87.1 | U22: =+'AGREGADO MEDIOS MOLEDORES'!S55 -> 0 | V22: =+'AGREGADO MEDIOS MOLEDORES'!T55 -> 90.1 | ... X22: =+'AGREGADO MEDIOS MOLEDORES'!V55 -> 0 | AB22: 90 | AC22: 92 | AD22: 89 | AE22: 79 | AF22: 88
B23: 92 | C23: 65 | E23: 46252 | F23: =+'AGREGADO MEDIOS MOLEDORES'!C56 -> 90.5 | G23: =+'AGREGADO MEDIOS MOLEDORES'!D56 -> 90.2 | H23: =+'AGREGADO MEDIOS MOLEDORES'!E56 -> 0 | I23: =+'AGREGADO MEDIOS MOLEDORES'!F56 -> 91.4 | J23: =+'AGREGADO MEDIOS MOLEDORES'!G56 -> 87.5 | K23: =+'AGREGADO MEDIOS MOLEDORES'!H56 -> 90.2 | L23: =+'AGREGADO MEDIOS MOLEDORES'!I56 -> 0 | M23: =+'AGREGADO MEDIOS MOLEDORES'!J56 -> 89.5 | N23: =+'AGREGADO MEDIOS MOLEDORES'!K56 -> 64.8 | O23: =+'AGREGADO MEDIOS MOLEDORES'!M56 -> 90.3 | P23: =+'AGREGADO MEDIOS MOLEDORES'!N56 -> 91.4 | Q23: =+'AGREGADO MEDIOS MOLEDORES'!O56 -> 90.4 | R23: =+'AGREGADO MEDIOS MOLEDORES'!P56 -> 93.3 | S23: =+'AGREGADO MEDIOS MOLEDORES'!Q56 -> 90.3 | T23: =+'AGREGADO MEDIOS MOLEDORES'!R56 -> 88.4 | U23: =+'AGREGADO MEDIOS MOLEDORES'!S56 -> 83.3 | V23: =+'AGREGADO MEDIOS MOLEDORES'!T56 -> 89.4 | ... X23: =+'AGREGADO MEDIOS MOLEDORES'!V56 -> 0 | AB23: 90 | AC23: 92 | AD23: 89 | AE23: 79 | AF23: 88
B24: 92 | C24: 65 | E24: 46253 | F24: =+'AGREGADO MEDIOS MOLEDORES'!C57 -> 91.6 | G24: =+'AGREGADO MEDIOS MOLEDORES'!D57 -> 86.8 | H24: =+'AGREGADO MEDIOS MOLEDORES'!E57 -> 0 | I24: =+'AGREGADO MEDIOS MOLEDORES'!F57 -> 0 | J24: =+'AGREGADO MEDIOS MOLEDORES'!G57 -> 94.1 | K24: =+'AGREGADO MEDIOS MOLEDORES'!H57 -> 92 | L24: =+'AGREGADO MEDIOS MOLEDORES'!I57 -> 0 | M24: =+'AGREGADO MEDIOS MOLEDORES'!J57 -> 94.4 | N24: =+'AGREGADO MEDIOS MOLEDORES'!K57 -> 65.3 | O24: =+'AGREGADO MEDIOS MOLEDORES'!M57 -> 91.6 | P24: =+'AGREGADO MEDIOS MOLEDORES'!N57 -> 92.9 | Q24: =+'AGREGADO MEDIOS MOLEDORES'!O57 -> 89.1 | R24: =+'AGREGADO MEDIOS MOLEDORES'!P57 -> 0 | S24: =+'AGREGADO MEDIOS MOLEDORES'!Q57 -> 92.2 | T24: =+'AGREGADO MEDIOS MOLEDORES'!R57 -> 89.2 | U24: =+'AGREGADO MEDIOS MOLEDORES'!S57 -> 0 | V24: =+'AGREGADO MEDIOS MOLEDORES'!T57 -> 90 | ... X24: =+'AGREGADO MEDIOS MOLEDORES'!V57 -> 0 | AB24: 90 | AC24: 92 | AD24: 89 | AE24: 79 | AF24: 88
B25: 92 | C25: 65 | E25: 46254 | F25: =+'AGREGADO MEDIOS MOLEDORES'!C58 -> 0 | G25: =+'AGREGADO MEDIOS MOLEDORES'!D58 -> 0 | H25: =+'AGREGADO MEDIOS MOLEDORES'!E58 -> 0 | I25: =+'AGREGADO MEDIOS MOLEDORES'!F58 -> 0 | J25: =+'AGREGADO MEDIOS MOLEDORES'!G58 -> 0 | K25: =+'AGREGADO MEDIOS MOLEDORES'!H58 -> 0 | L25: =+'AGREGADO MEDIOS MOLEDORES'!I58 -> 0 | M25: =+'AGREGADO MEDIOS MOLEDORES'!J58 -> 0 | N25: =+'AGREGADO MEDIOS MOLEDORES'!K58 -> 0 | O25: =+'AGREGADO MEDIOS MOLEDORES'!M58 -> 0 | P25: =+'AGREGADO MEDIOS MOLEDORES'!N59 -> 86.8 | Q25: =+'AGREGADO MEDIOS MOLEDORES'!O58 -> 0 | R25: =+'AGREGADO MEDIOS MOLEDORES'!P58 -> 0 | S25: =+'AGREGADO MEDIOS MOLEDORES'!Q58 -> 0 | T25: =+'AGREGADO MEDIOS MOLEDORES'!R58 -> 0 | U25: =+'AGREGADO MEDIOS MOLEDORES'!S58 -> 0 | V25: =+'AGREGADO MEDIOS MOLEDORES'!T58 -> 0 | W25: =+'AGREGADO MEDIOS MOLEDORES'!U58 -> 0 | X25: =+'AGREGADO MEDIOS MOLEDORES'!V58 -> 0 | AB25: 90 | AC25: 92 | AD25: 89 | AE25: 79 | AF25: 88
B26: 92 | C26: 65 | E26: 46255 | F26: =+'AGREGADO MEDIOS MOLEDORES'!C59 -> 89.1 | G26: =+'AGREGADO MEDIOS MOLEDORES'!D59 -> 0 | H26: =+'AGREGADO MEDIOS MOLEDORES'!E59 -> 89.5 | I26: =+'AGREGADO MEDIOS MOLEDORES'!F59 -> 87.2 | J26: =+'AGREGADO MEDIOS MOLEDORES'!G59 -> 90.4 | K26: =+'AGREGADO MEDIOS MOLEDORES'!H59 -> 88.1 | L26: =+'AGREGADO MEDIOS MOLEDORES'!I59 -> 0 | M26: =+'AGREGADO MEDIOS MOLEDORES'!J59 -> 90 | N26: =+'AGREGADO MEDIOS MOLEDORES'!K59 -> 63.7 | O26: =+'AGREGADO MEDIOS MOLEDORES'!M59 -> 89.6 | P26: =+'AGREGADO MEDIOS MOLEDORES'!N60 -> 81.4 | Q26: =+'AGREGADO MEDIOS MOLEDORES'!O59 -> 82.9 | R26: =+'AGREGADO MEDIOS MOLEDORES'!P59 -> 87 | S26: =+'AGREGADO MEDIOS MOLEDORES'!Q59 -> 90.3 | T26: =+'AGREGADO MEDIOS MOLEDORES'!R59 -> 92.8 | U26: =+'AGREGADO MEDIOS MOLEDORES'!S59 -> 0 | V26: =+'AGREGADO MEDIOS MOLEDORES'!T59 -> 89.5 | W26: =+'AGREGADO MEDIOS MOLEDORES'!U59 -> 76.9 | X26: =+'AGREGADO MEDIOS MOLEDORES'!V59 -> 84.4 | AB26: 90 | AC26: 92 | AD26: 89 | AE26: 79 | AF26: 88
B27: 92 | C27: 65 | E27: 46256 | F27: =+'AGREGADO MEDIOS MOLEDORES'!C60 -> 87.4 | G27: =+'AGREGADO MEDIOS MOLEDORES'!D60 -> 0 | H27: =+'AGREGADO MEDIOS MOLEDORES'!E60 -> 87.2 | I27: =+'AGREGADO MEDIOS MOLEDORES'!F60 -> 85.1 | J27: =+'AGREGADO MEDIOS MOLEDORES'!G60 -> 88.7 | K27: =+'AGREGADO MEDIOS MOLEDORES'!H60 -> 86.4 | L27: =+'AGREGADO MEDIOS MOLEDORES'!I60 -> 0 | M27: =+'AGREGADO MEDIOS MOLEDORES'!J60 -> 89.1 | N27: =+'AGREGADO MEDIOS MOLEDORES'!K60 -> 63.5 | O27: =+'AGREGADO MEDIOS MOLEDORES'!M60 -> 90.9 | P27: =+'AGREGADO MEDIOS MOLEDORES'!N61 -> 80.5 | Q27: =+'AGREGADO MEDIOS MOLEDORES'!O60 -> 83.9 | R27: =+'AGREGADO MEDIOS MOLEDORES'!P60 -> 85.5 | S27: =+'AGREGADO MEDIOS MOLEDORES'!Q60 -> 94.6 | T27: =+'AGREGADO MEDIOS MOLEDORES'!R60 -> 88.2 | U27: =+'AGREGADO MEDIOS MOLEDORES'!S60 -> 86.6 | V27: =+'AGREGADO MEDIOS MOLEDORES'!T60 -> 89.6 | W27: =+'AGREGADO MEDIOS MOLEDORES'!U60 -> 78.4 | X27: =+'AGREGADO MEDIOS MOLEDORES'!V60 -> 79.3 | AB27: 90 | AC27: 92 | AD27: 89 | AE27: 79 | AF27: 88
B28: 92 | C28: 65 | E28: 46257 | F28: =+'AGREGADO MEDIOS MOLEDORES'!C61 -> 85.4 | G28: =+'AGREGADO MEDIOS MOLEDORES'!D61 -> 0 | H28: =+'AGREGADO MEDIOS MOLEDORES'!E61 -> 86.6 | I28: =+'AGREGADO MEDIOS MOLEDORES'!F61 -> 80.7 | J28: =+'AGREGADO MEDIOS MOLEDORES'!G61 -> 86.6 | K28: =+'AGREGADO MEDIOS MOLEDORES'!H61 -> 84.1 | L28: =+'AGREGADO MEDIOS MOLEDORES'!I61 -> 91.8 | M28: =+'AGREGADO MEDIOS MOLEDORES'!J61 -> 86.6 | N28: =+'AGREGADO MEDIOS MOLEDORES'!K61 -> 62 | O28: =+'AGREGADO MEDIOS MOLEDORES'!M61 -> 90.8 | P28: =+'AGREGADO MEDIOS MOLEDORES'!N61 -> 80.5 | Q28: =+'AGREGADO MEDIOS MOLEDORES'!O61 -> 81.5 | R28: =+'AGREGADO MEDIOS MOLEDORES'!P61 -> 83.8 | S28: =+'AGREGADO MEDIOS MOLEDORES'!Q61 -> 94.4 | T28: =+'AGREGADO MEDIOS MOLEDORES'!R61 -> 88 | U28: =+'AGREGADO MEDIOS MOLEDORES'!S61 -> 86 | V28: =+'AGREGADO MEDIOS MOLEDORES'!T61 -> 88 | ... X28: =+'AGREGADO MEDIOS MOLEDORES'!V61 -> 78.9 | AB28: 90 | AC28: 92 | AD28: 89 | AE28: 79 | AF28: 88
B29: 92 | C29: 65 | E29: 46258 | F29: =+'AGREGADO MEDIOS MOLEDORES'!C62 -> 88.5 | G29: =+'AGREGADO MEDIOS MOLEDORES'!D62 -> 83 | H29: =+'AGREGADO MEDIOS MOLEDORES'!E62 -> 89.5 | I29: =+'AGREGADO MEDIOS MOLEDORES'!F62 -> 0 | J29: =+'AGREGADO MEDIOS MOLEDORES'!G62 -> 88.1 | K29: =+'AGREGADO MEDIOS MOLEDORES'!H62 -> 87.4 | L29: =+'AGREGADO MEDIOS MOLEDORES'!I62 -> 89.7 | M29: =+'AGREGADO MEDIOS MOLEDORES'!J62 -> 88.1 | N29: =+'AGREGADO MEDIOS MOLEDORES'!K62 -> 63 | O29: =+'AGREGADO MEDIOS MOLEDORES'!M62 -> 90.1 | P29: =+'AGREGADO MEDIOS MOLEDORES'!N62 -> 88.5 | Q29: =+'AGREGADO MEDIOS MOLEDORES'!O62 -> 0 | R29: =+'AGREGADO MEDIOS MOLEDORES'!P62 -> 0 | S29: =+'AGREGADO MEDIOS MOLEDORES'!Q62 -> 97.6 | T29: =+'AGREGADO MEDIOS MOLEDORES'!R62 -> 87.9 | U29: =+'AGREGADO MEDIOS MOLEDORES'!S62 -> 84.9 | V29: =+'AGREGADO MEDIOS MOLEDORES'!T62 -> 87.7 | ... X29: =+'AGREGADO MEDIOS MOLEDORES'!V62 -> 82.1 | AB29: 90 | AC29: 92 | AD29: 89 | AE29: 79 | AF29: 88
B30: 92 | C30: 65 | E30: 46259 | F30: =+'AGREGADO MEDIOS MOLEDORES'!C63 -> 87.9 | G30: =+'AGREGADO MEDIOS MOLEDORES'!D63 -> 84.5 | H30: =+'AGREGADO MEDIOS MOLEDORES'!E63 -> 88.5 | I30: =+'AGREGADO MEDIOS MOLEDORES'!F63 -> 0 | J30: =+'AGREGADO MEDIOS MOLEDORES'!G63 -> 90.4 | K30: =+'AGREGADO MEDIOS MOLEDORES'!H63 -> 89.8 | L30: =+'AGREGADO MEDIOS MOLEDORES'!I63 -> 92.1 | M30: =+'AGREGADO MEDIOS MOLEDORES'!J63 -> 91.4 | N30: =+'AGREGADO MEDIOS MOLEDORES'!K63 -> 62.8 | O30: =+'AGREGADO MEDIOS MOLEDORES'!M63 -> 85.2 | P30: =+'AGREGADO MEDIOS MOLEDORES'!N63 -> 92.5 | Q30: =+'AGREGADO MEDIOS MOLEDORES'!O63 -> 0 | R30: =+'AGREGADO MEDIOS MOLEDORES'!P63 -> 83.5 | S30: =+'AGREGADO MEDIOS MOLEDORES'!Q63 -> 97.3 | T30: =+'AGREGADO MEDIOS MOLEDORES'!R63 -> 85.4 | U30: =+'AGREGADO MEDIOS MOLEDORES'!S63 -> 83.6 | V30: =+'AGREGADO MEDIOS MOLEDORES'!T63 -> 86.9 | ... X30: =+'AGREGADO MEDIOS MOLEDORES'!V63 -> 78.4 | AB30: 90 | AC30: 92 | AD30: 89 | AE30: 79 | AF30: 88
B31: 92 | C31: 65 | E31: 46260 | F31: =+'AGREGADO MEDIOS MOLEDORES'!C64 -> 87.9 | G31: =+'AGREGADO MEDIOS MOLEDORES'!D64 -> 87.7 | H31: =+'AGREGADO MEDIOS MOLEDORES'!E64 -> 92 | I31: =+'AGREGADO MEDIOS MOLEDORES'!F64 -> 0 | J31: =+'AGREGADO MEDIOS MOLEDORES'!G64 -> 93.7 | K31: =+'AGREGADO MEDIOS MOLEDORES'!H64 -> 92.9 | L31: =+'AGREGADO MEDIOS MOLEDORES'!I64 -> 92.3 | M31: =+'AGREGADO MEDIOS MOLEDORES'!J64 -> 95 | N31: =+'AGREGADO MEDIOS MOLEDORES'!K64 -> 0 | O31: =+'AGREGADO MEDIOS MOLEDORES'!M64 -> 90.3 | P31: =+'AGREGADO MEDIOS MOLEDORES'!N64 -> 92.2 | Q31: =+'AGREGADO MEDIOS MOLEDORES'!O64 -> 90.7 | R31: =+'AGREGADO MEDIOS MOLEDORES'!P64 -> 82.6 | S31: =+'AGREGADO MEDIOS MOLEDORES'!Q64 -> 96.7 | T31: =+'AGREGADO MEDIOS MOLEDORES'!R64 -> 86 | U31: =+'AGREGADO MEDIOS MOLEDORES'!S64 -> 83.9 | V31: =+'AGREGADO MEDIOS MOLEDORES'!T64 -> 86.1 | ... X31: =+'AGREGADO MEDIOS MOLEDORES'!V64 -> 77.5 | AB31: 90 | AC31: 92 | AD31: 89 | AE31: 79 | AF31: 88
B32: 92 | C32: 65 | E32: 46261 | F32: =+'AGREGADO MEDIOS MOLEDORES'!C65 -> 0 | G32: =+'AGREGADO MEDIOS MOLEDORES'!D65 -> 0 | H32: =+'AGREGADO MEDIOS MOLEDORES'!E65 -> 0 | I32: =+'AGREGADO MEDIOS MOLEDORES'!F65 -> 0 | J32: =+'AGREGADO MEDIOS MOLEDORES'!G65 -> 0 | K32: =+'AGREGADO MEDIOS MOLEDORES'!H65 -> 0 | L32: =+'AGREGADO MEDIOS MOLEDORES'!I65 -> 0 | M32: =+'AGREGADO MEDIOS MOLEDORES'!J65 -> 0 | N32: =+'AGREGADO MEDIOS MOLEDORES'!K65 -> 0 | O32: =+'AGREGADO MEDIOS MOLEDORES'!M65 -> 0 | P32: =+'AGREGADO MEDIOS MOLEDORES'!N65 -> 0 | Q32: =+'AGREGADO MEDIOS MOLEDORES'!O65 -> 0 | R32: =+'AGREGADO MEDIOS MOLEDORES'!P65 -> 0 | S32: =+'AGREGADO MEDIOS MOLEDORES'!Q65 -> 0 | T32: =+'AGREGADO MEDIOS MOLEDORES'!R65 -> 0 | U32: =+'AGREGADO MEDIOS MOLEDORES'!S65 -> 0 | V32: =+'AGREGADO MEDIOS MOLEDORES'!T65 -> 0 | ... X32: =+'AGREGADO MEDIOS MOLEDORES'!V65 -> 0 | AB32: 90 | AC32: 92 | AD32: 89 | AE32: 79 | AF32: 88
B33: 92 | C33: 65 | E33: 46262 | F33: =+'AGREGADO MEDIOS MOLEDORES'!C66 -> 0 | G33: =+'AGREGADO MEDIOS MOLEDORES'!D66 -> 0 | H33: =+'AGREGADO MEDIOS MOLEDORES'!E66 -> 0 | I33: =+'AGREGADO MEDIOS MOLEDORES'!F66 -> 0 | J33: =+'AGREGADO MEDIOS MOLEDORES'!G66 -> 0 | K33: =+'AGREGADO MEDIOS MOLEDORES'!H66 -> 0 | L33: =+'AGREGADO MEDIOS MOLEDORES'!I66 -> 0 | M33: =+'AGREGADO MEDIOS MOLEDORES'!J66 -> 0 | N33: =+'AGREGADO MEDIOS MOLEDORES'!K66 -> 0 | O33: =+'AGREGADO MEDIOS MOLEDORES'!M66 -> 0 | P33: =+'AGREGADO MEDIOS MOLEDORES'!N66 -> 0 | Q33: =+'AGREGADO MEDIOS MOLEDORES'!O66 -> 0 | R33: =+'AGREGADO MEDIOS MOLEDORES'!P66 -> 0 | S33: =+'AGREGADO MEDIOS MOLEDORES'!Q66 -> 0 | T33: =+'AGREGADO MEDIOS MOLEDORES'!R66 -> 0 | U33: =+'AGREGADO MEDIOS MOLEDORES'!S66 -> 0 | V33: =+'AGREGADO MEDIOS MOLEDORES'!T66 -> 0 | ... X33: =+'AGREGADO MEDIOS MOLEDORES'!V66 -> 0 | AB33: 90 | AC33: 92 | AD33: 89 | AE33: 79 | AF33: 88
B34: 92 | C34: 65 | E34: 46263 | F34: =+'AGREGADO MEDIOS MOLEDORES'!C67 -> 0 | G34: =+'AGREGADO MEDIOS MOLEDORES'!D67 -> 0 | H34: =+'AGREGADO MEDIOS MOLEDORES'!E67 -> 0 | I34: =+'AGREGADO MEDIOS MOLEDORES'!F67 -> 0 | J34: =+'AGREGADO MEDIOS MOLEDORES'!G67 -> 0 | K34: =+'AGREGADO MEDIOS MOLEDORES'!H67 -> 0 | L34: =+'AGREGADO MEDIOS MOLEDORES'!I67 -> 0 | M34: =+'AGREGADO MEDIOS MOLEDORES'!J67 -> 0 | N34: =+'AGREGADO MEDIOS MOLEDORES'!K67 -> 0 | O34: =+'AGREGADO MEDIOS MOLEDORES'!M67 -> 0 | P34: =+'AGREGADO MEDIOS MOLEDORES'!N67 -> 0 | Q34: =+'AGREGADO MEDIOS MOLEDORES'!O67 -> 0 | R34: =+'AGREGADO MEDIOS MOLEDORES'!P67 -> 0 | S34: =+'AGREGADO MEDIOS MOLEDORES'!Q67 -> 0 | T34: =+'AGREGADO MEDIOS MOLEDORES'!R67 -> 0 | U34: =+'AGREGADO MEDIOS MOLEDORES'!S67 -> 0 | V34: =+'AGREGADO MEDIOS MOLEDORES'!T67 -> 0 | ... X34: =+'AGREGADO MEDIOS MOLEDORES'!V67 -> 0 | AB34: 90 | AC34: 92 | AD34: 89 | AE34: 79 | AF34: 88
B35: 92 | C35: 65 | E35: 46264 | F35: =+'AGREGADO MEDIOS MOLEDORES'!C68 -> 0 | G35: =+'AGREGADO MEDIOS MOLEDORES'!D68 -> 0 | H35: =+'AGREGADO MEDIOS MOLEDORES'!E68 -> 0 | I35: =+'AGREGADO MEDIOS MOLEDORES'!F68 -> 0 | J35: =+'AGREGADO MEDIOS MOLEDORES'!G68 -> 0 | K35: =+'AGREGADO MEDIOS MOLEDORES'!H68 -> 0 | L35: =+'AGREGADO MEDIOS MOLEDORES'!I68 -> 0 | M35: =+'AGREGADO MEDIOS MOLEDORES'!J68 -> 0 | N35: =+'AGREGADO MEDIOS MOLEDORES'!K68 -> 0 | O35: =+'AGREGADO MEDIOS MOLEDORES'!M68 -> 0 | P35: =+'AGREGADO MEDIOS MOLEDORES'!N68 -> 0 | Q35: =+'AGREGADO MEDIOS MOLEDORES'!O68 -> 0 | R35: =+'AGREGADO MEDIOS MOLEDORES'!P68 -> 0 | S35: =+'AGREGADO MEDIOS MOLEDORES'!Q68 -> 0 | T35: =+'AGREGADO MEDIOS MOLEDORES'!R68 -> 0 | U35: =+'AGREGADO MEDIOS MOLEDORES'!S68 -> 0 | V35: =+'AGREGADO MEDIOS MOLEDORES'!T68 -> 0 | ... X35: =+'AGREGADO MEDIOS MOLEDORES'!V68 -> 0 | AB35: 90 | AC35: 92 | AD35: 89 | AE35: 79 | AF35: 88
B36: 92 | C36: 65 | E36: 46265 | F36: =+'AGREGADO MEDIOS MOLEDORES'!#REF! -> #REF! | G36: =+'AGREGADO MEDIOS MOLEDORES'!#REF! -> #REF! | H36: =+'AGREGADO MEDIOS MOLEDORES'!#REF! -> #REF! | I36: =+'AGREGADO MEDIOS MOLEDORES'!#REF! -> #REF! | J36: =+'AGREGADO MEDIOS MOLEDORES'!#REF! -> #REF! | K36: =+'AGREGADO MEDIOS MOLEDORES'!#REF! -> #REF! | L36: =+'AGREGADO MEDIOS MOLEDORES'!#REF! -> #REF! | M36: =+'AGREGADO MEDIOS MOLEDORES'!#REF! -> #REF! | ... X36: =+'AGREGADO MEDIOS MOLEDORES'!#REF! -> #REF! | AB36: 90 | AC36: 92 | AD36: 89 | AE36: 79 | AF36: 88

Sheet BALANZAS
B1: CONTROL MENSUAL DE CALIBRACIÓN DE BALANZAS DE FAJA - PLANTA MAGNETICA
B3: FECHA | C3: EQUIPO | D3: FAJA TRANSP | E3: ZERO AS FOUND | F3: ZERO AS LEFT | G3: DELTA ZERO | H3: ERROR ZERO ENCONTRADO (%) | I3: ERROR ZERO DEJADO (%) | J3: SPAN AS FOUND | K3: SPAN AS LEFT | L3: DELTA SPAN | M3: ERROR SPAN ENCONTRADO (%) | N3: ERROR SPAN DEJADO (%) | O3: OBSERVACION
B4: 28/04/2026 | C4: 031-071 | D4: 031-061 | E4: 28522 | F4: 28553 | G4: 31 | H4: 0.08 | I4: 0.02 | J4: 1542890 | K4: 1540453 | L4: -2437 | M4: 0.16 | N4: 0.01 | O4: Mantener limpio tren de pesaje
B5: 28/04/2026 | C5: 031-072 | D5: 031-062 | E5: 28223 | F5: 28260 | G5: 37 | H5: 0.09 | I5: 0.01 | J5: 1512326 | K5: 1496894 | L5: -15432 | M5: 1.03 | N5: -0.02 | O5: Mantener limpio tren de pesaje
B6: 28/04/2026 | C6: 031-073 | D6: 031-063 | E6: 37173 | F6: 37118 | G6: -55 | H6: -0.12 | I6: -0.01 | J6: 1484329 | K6: 1474927 | L6: -9402 | M6: 0.64 | N6: 0.07 | O6: Mantener limpio tren de pesaje
B7: 28/04/2026 | C7: 031-074 | D7: 031-064 | E7: 117969 | F7: 107574 | G7: -10395 | H7: 0.36 | I7: 0.01 | J7: 309004.56 | K7: 299558.43 | L7: -9446.13 | M7: 3.15 | N7: 0.03 | O7: Mantener limpio el tren de pesaje
B8: 28/04/2026 | C8: 031-083 | D8: 031-065 | E8: 16014 | F8: 16091 | G8: 77 | H8: 0.35 | I8: 0.02 | J8: 1406831 | K8: 1402003 | L8: -4828 | M8: 0.34 | N8: 0.15 | O8: Mantener limpio el tren de pesaje
B9: 28/04/2026 | C9: 031-076 | D9: 031-066 | E9: 32083 | F9: 33780 | G9: 1697 | H9: 7.99 | I9: -0.02 | J9: 1483913 | K9: 1498968 | L9: 15055 | M9: -1 | N9: -0.15 | O9: Mantener limpio el tren de pesaje
B10: 28/04/2026 | C10: 031-082 | D10: 031-067 | E10: 25622 | F10: 25273 | G10: -349 | H10: -1.03 | I10: -0.02 | J10: 1610420 | K10: 1653108 | L10: 42688 | M10: -2.58 | N10: -0.03 | O10: Mantener limpio tren de pesaje
B11: 28/04/2026 | C11: 031-081 | D11: 031-068 | E11: 32796 | F11: 32496 | G11: -300 | H11: 0.42 | I11: 0.05 | J11: 1478849 | K11: 1484256 | L11: 5407 | M11: -0.36 | N11: 0.01 | O11: Mantener limpio tren de pesaje

Sheet INSPECCION DE CICLONES
B2: INSPECCION DE COMPONENTES DE HIDROCICLONES
B4: Medidas de Diseño
B6: Proveedor : HAIWANG
B9: Apex Diámetro Nominal Superior (mm) | D9: 89.99
B10: Apex Diámetro Nominal Inferior (mm) | D10: 58.75
B12: Espesor del apex Diámetro superior (mm) | D12: 21.76
B13: Espesor del apex Diámetro Inferior (mm) | D13: 12.7
B15: Vortex Diámetro Nominal (mm) | D15: 120.65
B16: Espesor del Vortex (mm) | D16: 20.638
B18: Ene-26
B19: BM 01 | C19: Numero de Ciclones | E19: 212-161~164 | O19: Comentarios: | Q19: Apex: Presentan minimo desgaste
E20: 161 | G20: 162 | I20: 163 | K20: 164 | M20: 164A
C21: Fecha de Inspección | D21: 46174 | E21: mm | F21: Desg. | G21: mm | H21: Desg. | I21: mm | J21: Desg. | K21: mm | L21: Desg. | M21: mm | N21: Desg.
C22: Apex Diámetro Real Superior | E22: 90 | F22: 0.0005 | G22: 90.1 | H22: 0.0051 | I22: 90 | J22: 0.0005 | K22: 90.2 | L22: 0.0097 | M22: 90.2 | N22: 0.0097 | Q22: Vortex: 212-164A presenta mayor desgaste (15%); sin embargo, se encuentra dentro del rango permisible.
C23: Apex Diámetro Real Inferior | E23: 58.8 | F23: 0.0039 | G23: 58.8 | H23: 0.0039 | I23: 59 | J23: 0.0197 | K23: 58.8 | L23: 0.0039 | M23: 59 | N23: 0.0197
C24: Vortex Diámetro Real | E24: 121 | F24: 0.017 | G24: 120.8 | H24: 0.0073 | I24: 122 | J24: 0.0654 | K24: 122 | L24: 0.0654 | M24: 123.8 | N24: 0.1526
B26: BM 02 | C26: Numero de Ciclones | E26: 212-831~833 | M26: Comentarios: | O26: Apex:
E27: 831 | G27: 832 | I27: 833 | K27: Implementar
C28: Fecha de Inspección | D28: PM | E28: mm | F28: Desg. | G28: mm | H28: Desg. | I28: mm | J28: Desg. | K28: mm | L28: Desg.
C29: Apex Diámetro Real Superior | F29: -4.1356 | H29: -4.1356 | J29: -4.1356 | O29: Vortex:
C30: Apex Diámetro Real Inferior | F30: -4.626 | H30: -4.626 | J30: -4.626
C31: Vortex Diámetro Real | F31: -5.8462 | H31: -5.8462 | J31: -5.8462
B33: BM 03 | C33: Numero de Ciclones | E33: 212-153 ~154 | M33: Comentarios: | O33: Apex: 212-153/155 se encontraron con ceramico rejado, se reemplazaron por apex nuevos D. Inferior 2 1/8"
E34: 153 | G34: 154 | I34: 155 | K34: Implementar
C35: Fecha de Inspección | D35: PM 06/03/2026 | E35: mm | F35: Desg. | G35: mm | H35: Desg. | I35: mm | J35: Desg. | K35: mm | L35: Desg.
C36: Apex Diámetro Real Superior | E36: 90.1 | F36: 0.0051 | G36: 90 | H36: 0.0005 | I36: 90 | J36: 0.0005 | O36: Vortex: Desgaste dentro de rango permisible.
C37: Apex Diámetro Real Inferior | E37: 58.9 | F37: 0.0118 | G37: 58.8 | H37: 0.0039 | I37: 59 | J37: 0.0197
C38: Vortex Diámetro Real | E38: 120.8 | F38: 0.0073 | G38: 123.8 | H38: 0.1526 | I38: 124 | J38: 0.1623
B40: BM 04 | C40: Numero de Ciclones | E40: 212-158~160 | M40: Comentarios: | O40: Apex: 212-158 se encontró con ceramico rejado, se reemplazó por apex nuevo D. Inferior 2 1/8"
E41: 158 | G41: 159 | I41: 160 | K41: Implementar
C42: Fecha de Inspección | D42: PM 06/03/2026 | E42: mm | F42: Desg. | G42: mm | H42: Desg. | I42: mm | J42: Desg. | K42: mm | L42: Desg.
C43: Apex Diámetro Real Superior | E43: 90.2 | F43: 0.0097 | G43: 90 | H43: 0.0005 | I43: 90.1 | J43: 0.0051 | O43: Vortex: 212-159 Se reemplazó vortex por encontrarse cortado. 212-158/160 presentan minimo desgaste en la parte superior; sin emargo, parte inferor se encontraron resanados con nordbak.
C44: Apex Diámetro Real Inferior | E44: 59.1 | F44: 0.0276 | G44: 59 | H44: 0.0197 | I44: 59 | J44: 0.0197
C45: Vortex Diámetro Real | E45: 120.9 | F45: 0.0121 | G45: 120.8 | H45: 0.0073 | I45: 120.8 | J45: 0.0073
B47: BM 05 | C47: Numero de Ciclones | E47: 212-148 A/B/C/D/E/F | Q47: Comentarios: | S47: Apex: Presentan minimo desgaste
E48: A | G48: B | I48: C | K48: D | M48: E | O48: F
C49: Fecha de Inspección | D49: 46296 | E49: mm | F49: Desg. | G49: mm | H49: Desg. | I49: mm | J49: Desg. | K49: mm | L49: Desg. | M49: mm | N49: Desg. | O49: mm | P49: Desg.
C50: Apex Diámetro Real Superior | E50: 90.1 | F50: 0.0051 | G50: 90.5 | H50: 0.0234 | I50: 90 | J50: 0.0005 | K50: 90.1 | L50: 0.0051 | M50: 90.1 | N50: 0.0051 | O50: 90 | P50: 0.0005 | S50: Vortex: Presentan mínimo desgaste en la parte superior; sin embargo, parte inferior 02 vortex se encuentran resanados con nordbak.
C51: Apex Diámetro Real Inferior | E51: 59 | F51: 0.0197 | G51: 59.2 | H51: 0.0354 | I51: 59.1 | J51: 0.0276 | K51: 58.9 | L51: 0.0118 | M51: 59.1 | N51: 0.0276 | O51: 58.8 | P51: 0.0039
C52: Vortex Diámetro Real | E52: 121.2 | F52: 0.0267 | G52: 121 | H52: 0.017 | I52: 121.4 | J52: 0.0363 | K52: 122.6 | L52: 0.0945 | M52: 124 | N52: 0.1623 | O52: 122.5 | P52: 0.0896
B54: BM 06 | C54: Numero de Ciclones | E54: 212-149 A/B/C/D/E | O54: Comentarios: | Q54: Apex: 212-149 C y D presentaban rajaduras del cerámico, se reemplazó por nuevos. 212-149 A/B/E presentan mínimo desgaste. / 212-149D Presentaba forro conico hinchado, se reemplazó.
E55: A | G55: B | I55: C | K55: D | M55: E
C56: Fecha de Inspección | D56: 27/01/2026 | E56: mm | F56: Desg. | G56: mm | H56: Desg. | I56: mm | J56: Desg. | K56: mm | L56: Desg. | M56: mm | N56: Desg.
C57: Apex Diámetro Real Superior | E57: 90 | F57: 0.0005 | G57: 90.2 | H57: 0.0097 | I57: 90.2 | J57: 0.0097 | K57: 90.1 | L57: 0.0051 | M57: 90.5 | N57: 0.0234 | Q57: Vortex: Presentan minimo desgaste
C58: Apex Diámetro Real Inferior | E58: 59.1 | F58: 0.0276 | G58: 59.5 | H58: 0.0591 | I58: 59 | J58: 0.0197 | K58: 59.2 | L58: 0.0354 | M58: 59.8 | N58: 0.0827
C59: Vortex Diámetro Real | E59: 120.8 | F59: 0.0073 | G59: 121 | H59: 0.017 | I59: 120.8 | J59: 0.0073 | K59: 121.2 | L59: 0.0267 | M59: 121 | N59: 0.017
B61: BM 07 | C61: Numero de Ciclones | E61: 212-897 A/B/C/D/E | O61: Comentarios: | Q61: Apex:
E62: A | G62: B | I62: C | K62: D | M62: E
C63: Fecha de Inspección | D63: PM | E63: mm | F63: Desg. | G63: mm | H63: Desg. | I63: mm | J63: Desg. | K63: mm | L63: Desg. | M63: mm | N63: Desg.
C64: Apex Diámetro Real Superior | F64: -4.1356 | H64: -4.1356 | J64: -4.1356 | L64: -4.1356 | N64: -4.1356 | Q64: Vortex:
C65: Apex Diámetro Real Inferior | F65: -4.626 | H65: -4.626 | J65: -4.626 | L65: -4.626 | N65: -4.626
C66: Vortex Diámetro Real | F66: -5.8462 | H66: -5.8462 | J66: -5.8462 | L66: -5.8462 | N66: -5.8462
B68: BM 08 | C68: Numero de Ciclones | E68: 212-150 A/B/C/D/E/F | Q68: Comentarios: | S68: Apex: 212-150A y D presentaban rajaduras del cerámico, se reemplazó por nuevos. 212-150B/C/E/F presentan mínimo desgaste.
E69: A | G69: B | I69: C | K69: D | M69: E | O69: F
C70: Fecha de Inspección | D70: 46266 | E70: mm | F70: Desg. | G70: mm | H70: Desg. | I70: mm | J70: Desg. | K70: mm | L70: Desg. | M70: mm | N70: Desg. | O70: mm | P70: Desg.
C71: Apex Diámetro Real Superior | E71: 90 | F71: 0.0005 | G71: 90.1 | H71: 0.0051 | I71: 90 | J71: 0.0005 | K71: 90 | L71: 0.0005 | M71: 90.1 | N71: 0.0051 | O71: 90 | P71: 0.0005 | S71: Vortex: 212-150 presentan mínimo desgaste en la parte superior; sin embargo, parte inferior se encuentran resanados con nordbak.
C72: Apex Diámetro Real Inferior | E72: 59.5 | F72: 0.0591 | G72: 59 | H72: 0.0197 | I72: 59.1 | J72: 0.0276 | K72: 59 | L72: 0.0197 | M72: 59.5 | N72: 0.0591 | O72: 58.9 | P72: 0.0118
C73: Vortex Diámetro Real | E73: 120.8 | F73: 0.0073 | G73: 121 | H73: 0.017 | I73: 120.9 | J73: 0.0121 | K73: 122 | L73: 0.0654 | M73: 122.2 | N73: 0.0751 | O73: 123 | P73: 0.1139
B75: BM 09 | C75: Numero de Ciclones | E75: 212-893 A/B/C/D/E/F | Q75: Comentarios: | S75: Apex: A/C/E presentan rajaduras; sin embargo, se realizó el cambio de los 6 apex.
E76: A | G76: B | I76: C | K76: D | M76: E | O76: F
C77: Fecha de Inspección | D77: 46085 | E77: mm | F77: Desg. | G77: mm | H77: Desg. | I77: mm | J77: Desg. | K77: mm | L77: Desg. | M77: mm | N77: Desg. | O77: mm | P77: Desg.
C78: Apex Diámetro Real Superior | E78: 90.1 | F78: 0.0051 | G78: 90 | H78: 0.0005 | I78: 90 | J78: 0.0005 | K78: 90.1 | L78: 0.0051 | M78: 90 | N78: 0.0005 | O78: 90.1 | P78: 0.0051 | S78: Vortex: 212-893C presenta mayor desgaste (5.26%);
C79: Apex Diámetro Real Inferior | E79: 58.9 | F79: 0.0118 | G79: 58.9 | H79: 0.0118 | I79: 59.2 | J79: 0.0354 | K79: 59.1 | L79: 0.0276 | M79: 59.1 | N79: 0.0276 | O79: 59 | P79: 0.0197
C80: Vortex Diámetro Real | E80: 126 | F80: 0.0443 | G80: 125 | H80: 0.0361 | I80: 127 | J80: 0.0526 | K80: 124 | L80: 0.0278 | M80: 123.8 | N80: 0.0261 | O80: 122 | P80: 0.0112
B82: BM 10 | C82: Numero de Ciclones | E82: 212-892 A/B/C/D/E/F | Q82: Comentarios: | S82: Apex: Presentan minimo desgaste
E83: A | G83: B | I83: C | K83: D | M83: E | O83: F
C84: Fecha de Inspección | D84: 16/01/2026 | E84: mm | F84: Desg. | G84: mm | H84: Desg. | I84: mm | J84: Desg. | K84: mm | L84: Desg. | M84: mm | N84: Desg. | O84: mm | P84: Desg.
C85: Apex Diámetro Real Superior | E85: 90.2 | F85: 0.0097 | G85: 90.6 | H85: 0.028 | I85: 90.5 | J85: 0.0234 | K85: 90.8 | L85: 0.0372 | M85: 90.8 | N85: 0.0372 | O85: 91.5 | P85: 0.0694 | S85: Vortex: Presentan minimo desgaste
C86: Apex Diámetro Real Inferior | E86: 58.9 | F86: 0.0118 | G86: 59 | H86: 0.0197 | I86: 59.5 | J86: 0.0591 | K86: 59.5 | L86: 0.0591 | M86: 59.8 | N86: 0.0827 | O86: 59 | P86: 0.0157
C87: Vortex Diámetro Real | E87: 120.9 | F87: 0.0121 | G87: 120.8 | H87: 0.0073 | I87: 120.9 | J87: 0.0121 | K87: 121.1 | L87: 0.0194 | M87: 121.1 | N87: 0.0218 | O87: 120.8 | P87: 0.0073
B89: 46168
B90: BM 01 | C90: Numero de Ciclones | E90: 212-161~164 | O90: Comentarios: | Q90: Apex: 212-162/164 presentaban rajaduras del cerámico, se reemplazó por nuevos. 212-161/163/164A presentan mínimo desgaste.
E91: 161 | G91: 162 | I91: 163 | K91: 164 | M91: 164A
C92: Fecha de Inspección | D92: 46208 | E92: mm | F92: Desg. | G92: mm | H92: Desg. | I92: mm | J92: Desg. | K92: mm | L92: Desg. | M92: mm | N92: Desg.
C93: Apex Diámetro Real Superior | E93: 90 | F93: =+(E93-89.9)/89.9 -> 0.0011123471 | G93: 90.5 | H93: =+(G93-89.9)/89.9 -> 0.0066740823 | I93: 90.5 | J93: =+(I93-89.9)/89.9 -> 0.0066740823 | K93: 90.8 | L93: =+(K93-89.9)/89.9 -> 0.010011123 | M93: 90.5 | N93: =+(M93-89.9)/89.9 -> 0.0066740823 | Q93: Vortex: Presentan minimo desgaste
C94: Apex Diámetro Real Inferior | E94: 59.2 | F94: =+(E94-58.75)/58.75 -> 0.0076595745 | G94: 60.5 | H94: =+(G94-58.75)/58.75 -> 0.029787234 | I94: 59.5 | J94: =+(I94-58.75)/58.75 -> 0.012765957 | K94: 59.3 | L94: =+(K94-58.75)/58.75 -> 0.0093617021 | M94: 59 | N94: =+(M94-58.75)/58.75 -> 0.0042553191
C95: Vortex Diámetro Real | E95: 123.5 | F95: =+(E95-120.65)/120.65 -> 0.023622047 | G95: 119 | H95: =+(G95-120.65)/120.65 -> -0.013675922 | I95: 121 | J95: =+(I95-120.65)/120.65 -> 0.0029009532 | K95: 119 | L95: =+(K95-120.65)/120.65 -> -0.013675922 | M95: 114 | N95: =+(M95-120.65)/120.65 -> -0.05511811
B97: BM 02 | C97: Numero de Ciclones | E97: 212-831~833 | M97: Comentarios: | O97: Apex:
E98: 831 | G98: 832 | I98: 833 | K98: Implementar
C99: Fecha de Inspección | E99: mm | F99: Desg. | G99: mm | H99: Desg. | I99: mm | J99: Desg. | K99: mm | L99: Desg.
C100: Apex Diámetro Real Superior | O100: Vortex:
C101: Apex Diámetro Real Inferior
C102: Vortex Diámetro Real
B104: BM 03 | C104: Numero de Ciclones | E104: 212-153 ~154 | M104: Comentarios:
E105: 153 | G105: 154 | I105: 155 | K105: Implementar
C106: Fecha de Inspección | D106: 46270 | E106: mm | F106: Desg. | G106: mm | H106: Desg. | I106: mm | J106: Desg. | K106: mm | L106: Desg.
C107: Apex Diámetro Real Superior | E107: 88 | F107: =+(E107-89.9)/89.9 -> -0.021134594 | G107: 89 | H107: =+(G107-89.9)/89.9 -> -0.010011123 | I107: 89 | J107: =+(I107-89.9)/89.9 -> -0.010011123
C108: Apex Diámetro Real Inferior | E108: 60 | F108: =+(E108-58.75)/58.75 -> 0.021276596 | G108: 56 | H108: =+(G108-58.75)/58.75 -> -0.046808511 | I108: 55 | J108: =+(I108-58.75)/58.75 -> -0.063829787
C109: Vortex Diámetro Real | E109: 120.8 | F109: =+(E109-120.65)/120.65 -> 0.0012432656 | G109: 124 | H109: =+(G109-120.65)/120.65 -> 0.027766266 | I109: 125 | J109: =+(I109-120.65)/120.65 -> 0.036054704
B111: BM 04 | C111: Numero de Ciclones | E111: 212-158~160 | M111: Comentarios:
E112: 158 | G112: 159 | I112: 160 | K112: Implementar
C113: Fecha de Inspección | D113: 46270 | E113: mm | F113: Desg. | G113: mm | H113: Desg. | I113: mm | J113: Desg. | K113: mm | L113: Desg.
C114: Apex Diámetro Real Superior | E114: 88 | F114: =+(E114-89.9)/89.9 -> -0.021134594 | G114: 88 | H114: =+(G114-89.9)/89.9 -> -0.021134594 | I114: 88 | J114: =+(I114-89.9)/89.9 -> -0.021134594
C115: Apex Diámetro Real Inferior | E115: 54 | F115: =+(E115-58.75)/58.75 -> -0.080851064 | G115: 57 | H115: =+(G115-58.75)/58.75 -> -0.029787234 | I115: 60 | J115: =+(I115-58.75)/58.75 -> 0.021276596
C116: Vortex Diámetro Real | E116: 116 | F116: =+(E116-120.65)/120.65 -> -0.038541235 | G116: 118 | H116: =+(G116-120.65)/120.65 -> -0.02196436 | I116: 130 | J116: =+(I116-120.65)/120.65 -> 0.077496892
B118: BM 05 | C118: Numero de Ciclones | E118: 212-148 A/B/C/D/E/F | Q118: Comentarios:
E119: A | G119: B | I119: C | K119: D | M119: E | O119: F
C120: Fecha de Inspección | D120: 46147 | E120: mm | F120: Desg. | G120: mm | H120: Desg. | I120: mm | J120: Desg. | K120: mm | L120: Desg. | M120: mm | N120: Desg. | O120: mm | P120: Desg.
C121: Apex Diámetro Real Superior | E121: 89 | F121: =+(E121-89.9)/89.9 -> -0.010011123 | G121: 90 | H121: =+(G121-89.9)/89.9 -> 0.0011123471 | I121: 89 | J121: =+(I121-89.9)/89.9 -> -0.010011123 | K121: 88 | L121: =+(K121-89.9)/89.9 -> -0.021134594 | M121: 87 | N121: =+(M121-89.9)/89.9 -> -0.032258065 | O121: 105 | P121: =+(O121-89.9)/89.9 -> 0.1679644
C122: Apex Diámetro Real Inferior | E122: 58 | F122: =+(E122-58.75)/58.75 -> -0.012765957 | G122: 60 | H122: =+(G122-58.75)/58.75 -> 0.021276596 | I122: 58 | J122: =+(I122-58.75)/58.75 -> -0.012765957 | K122: 57 | L122: =+(K122-58.75)/58.75 -> -0.029787234 | M122: 58 | N122: =+(M122-58.75)/58.75 -> -0.012765957 | O122: 54 | P122: =+(O122-58.75)/58.75 -> -0.080851064
...

Sheet SOLPED FORROS RM-BM
B2: REQUERIMIENTO DE FORROS PARA MOLINO
B3: MOLINO | C3: SOLICITUD | D3: CATALOGACIÓN | E3: SOLPED | F3: FECHA LIBERACION | G3: ESTADO DE LIBERACION | H3: ESTATUS | I3: ORDEN DE COMPRA | J3: PROVEEDOR | K3: FECHA ENTREGA | L3: COMENTARIO
B4: MOLINO | C4: SOLICITUD | D4: CATALOGACIÓN | E4: SOLPED | F4: ESTADO | G4: ESTADO DE LIBERACION | H4: ESTATUS | I4: ORDEN DE COMPRA | J4: PROVEEDOR | K4: FECHA ENTREGA | L4: COMENTARIO
B5: 032-081 | C5: JUEGO COMPLETO | D5: SI | E5: 10008721 | F5: 14-ene.-26 | G5: LIBERADO | H5: COTIZACION | L5: Actualizacion de EVT / DAM2026-1853 / DAM2026-2046
C6: PERNERIA DE FORROS | D6: SI | E6: 10008722 | F6: 14-ene.-26 | G6: LIBERADO | H6: COTIZACION
C7: FORROS TAPA DESCARGA | D7: SI | E7: 10008738 | F7: 14-ene.-26 | G7: LIBERADO | H7: STOCK EN ALMACEN | I7: 4510009705 | J7: ACSA | K7: 46065 | L7: En stock
C8: PERNERIA DE TAPA | D8: SI | E8: 10008739 | F8: 14-ene.-26 | G8: LIBERADO | H8: STOCK EN ALMACEN | I8: 4510009708 | J8: ACSA | K8: 46064 | L8: En stock
B9: 032-082 | C9: JUEGO COMPLETO | D9: SI | E9: 10008727 | F9: 10-ene.-26 | G9: LIBERADO | H9: FABRICACION | I9: 4510010989 | J9: PEG | K9: 46241
C10: PERNERIA DE FORROS | D10: SI | E10: 10008728 | F10: 14-ene.-26 | G10: LIBERADO | H10: FABRICACION
C11: FORROS TAPA DESCARGA
C12: PERNERIA DE TAPA
B13: 032-083 | C13: JUEGO COMPLETO | D13: --- | E13: --- | F13: --- | G13: --- | H13: STOCK EN ALMACEN | J13: ACSA | L13: Destinado para el molino 032-081 / Cambio de molino completo
B14: 032-087 | C14: JUEGO COMPLETO | D14: SI | E14: 10008618 | F14: 09-ene.-26 | G14: LIBERADO | H14: COTIZACION | L14: Actualizacion de EVT / DAM2026-1855 / DAM2026-2046
C15: PERNERIA DE FORROS | D15: SI | E15: 10008619 | F15: 13-ene.-26 | G15: LIBERADO | H15: COTIZACION | M15: setiembre PEn
C16: FORROS TAPA DESCARGA
C17: PERNERIA DE TAPA
B18: 032-088 | C18: JUEGO COMPLETO | D18: SI | E18: 10008741 | F18: 10-ene.-26 | G18: LIBERADO | H18: COTIZACION | L18: Actualizacion de EVT / DAM2026-2311 / DAM2026-2046
C19: PERNERIA DE FORROS | D19: SI | E19: 10008742 | F19: 09-ene.-26 | G19: LIBERADO | H19: COTIZACION
C20: FORROS TAPA DESCARGA
C21: PERNERIA DE TAPA
B22: 032-089 | C22: JUEGO COMPLETO | D22: SI | E22: 10005272 | F22: 17-jul.-25 | G22: LIBERADO | H22: FABRICACION | I22: 4510006698 | J22: PEG | K22: 16/03/2026 | L22: Se confirma recepción a almacén el 25 de marzo
C23: PERNERIA DE FORROS
B25: 032-201 | C25: JUEGO COMPLETO | D25: SI | E25: 10008808 | F25: 14/01/26 | G25: LIBERADO | H25: FABRICACION | I25: 4510011229 | J25: NAIPU | K25: 24-Ago
B26: 032-202 | C26: JUEGO COMPLETO | D26: --- | E26: --- | F26: --- | G26: --- | H26: --- | I26: --- | J26: --- | K26: --- | L26: En Almacen 5
B27: 032-203 | C27: JUEGO COMPLETO | D27: --- | E27: --- | F27: --- | G27: --- | H27: --- | I27: --- | J27: --- | K27: --- | L27: ---
B28: 032-204 | C28: JUEGO COMPLETO | D28: SI | E28: 10009210 | F28: 17/02/26 | G28: LIBERADO | H28: COTIZACION | L28: Sin DAM
B29: 032-205 | C29: JUEGO COMPLETO | D29: SI | E29: 10004301 | F29: 24/05/25 | G29: LIBERADO | H29: FABRICACION | I29: 4510009513 | J29: NAIPU | K29: 46192 | L29: En Almacen 5
B30: 032-206 | C30: JUEGO COMPLETO | D30: SI | E30: 10005875 | F30: 29/08/25 | G30: LIBERADO | H30: FABRICACION | I30: 4510010031 | J30: NAIPU | K30: 46206 | L30: Se instala en molino 032-208 | M30: llega el 15 de agosto
B31: 032-207 | C31: JUEGO COMPLETO | D31: SI | E31: 10008630 | F31: 14/01/26 | G31: LIBERADO | H31: FABRICACION | I31: 4510011646 | J31: NAIPU | K31: 16-Ago | L31: Se intalará en molino 032-206
B32: 032-208 | C32: JUEGO COMPLETO | D32: SI | E32: 10008737 | F32: 14/0126 | G32: LIBERADO | H32: FABRICACION | I32: 4510011157 | J32: NAIPU | K32: 46213 | L32: Se intalará en molino 032-207
B33: 032-209 | C33: JUEGO COMPLETO | D33: Si | E33: 10010751 | F33: 22/04/26 | G33: LIBERADO | H33: FABRICACION | I33: 4510012802 | J33: INDELAT | K33: 46183 | L33: En Almacen 3
E34: 10011283 | F34: 23/05/26 | I34: 4510012982
E35: 10011426 | I35: 4510013079
B36: 032-210 | C36: JUEGO COMPLETO | D36: Si | E36: 10010752 | F36: 22/04/26 | G36: LIBERADO | H36: FABRICACION | I36: 4510012419 | J36: INDELAT | K36: 46218
B40: PROGRAMA CAMBIO DE FORROS DE MOLINOS - CONCENTRACION BENEFICIO 2026
B42: MOLINOS | C42: CODIGO | D42: CAMBIO | E42: Ene-26 | F42: 46079 | G42: 46107 | H42: Abr-26 | I42: 46168 | J42: 46199 | K42: 46229 | L42: Ago-26 | M42: Set-26 | N42: 46321 | O42: 46352 | P42: Dic-26
B43: BARRAS | C43: 032-081 | D43: Dic-22
C44: 032-082 | D44: 46077
C45: 032-083 | D45: Ago-22
C46: 032-084 | D46: 46078
C47: 032-085 | D47: 46228
C48: 032-086 | D48: 46228
C49: 032-087 | D49: 46318
C50: 032-088 | D50: 46106
C51: 032-089 | D51: Dic-23
B53: MOLINOS | C53: CODIGO | E53: Ene-26 | F53: 46079 | G53: 46107 | H53: Abr-26 | I53: 46168 | J53: 46199 | K53: 46229 | L53: Ago-26 | M53: Set-26 | N53: 46321 | O53: 46352 | P53: Dic-26
B54: BOLAS | C54: 032-201 | D54: Dic-24
C55: 032-202 | D55: Ago-18
C56: 032-203 | D56: 46163
C57: 032-204 | D57: 46076
C58: 032-205 | D58: Abr-22
C59: 032-206 | D59: 46194
C60: 032-207 | D60: Ago-21
C61: 032-208 | D61: 46317
C62: 032-209 | D62: Ago-24
C63: 032-210 | D63: Dic-24
B66: Leyenda Molinos Barras: | G66: Leyenda Molinos Bolas:
B67: Cambio Forros | G67: Cambio Forros Elevadores | M67: Cambio Forros Magneticos
B69: STD: | C69: 3,500,000 TMS | G69: Cambio Forros Planos | M69: STD: | N69: 2,500,000 TMS
G71: Cambio Forros Elevadores + Forros Planos
G73: STD: Planos BG | I73: 4,000,000 TMS
G74: STD: Elevadores BG | I74: 2,000,000 TMS
G75: STD: Planos BCH | I75: 2,400,000 TMS
G76: STD: Elevadores BCH | I76: 1,200,000 TMS

Sheet RTM-TRITURACION
B3: REPORTE DE TRABAJOS DE MANTENIMIENTO
B5: Fecha de reporte | C5: Aviso SAP | D5: Equipo | E5: Descripción | F5: Area Ejec. | G5: Estado | H5: Criticidad | J5: Criticidad
B6: 21/11/2025 | C6: 20005484 | D6: 029-115 | E6: EQUIPO PARADO / INSTALAR IMPULSOR | F6: Mantto Mecánico | G6: 1 | H6: P | J6: A | K6: Baja
B7: 21/11/2025 | C7: 10016711 | D7: 029-070 | E7: REVISAR FUGA DE ACEITE POR CHUMACERAS LADO MOTOR Y PLAYA | F7: Mantto Mecánico | G7: 1 | H7: C | J7: B | K7: Media
B8: 21/11/2025 | C8: 10016712 | D8: 021-116 | E8: PERDIDA DE ACEITE DEL REDUCTOR | F8: Mantto Mecánico | G8: 1 | H8: C | J8: C | K8: Alta
B9: 22/11/2025 | C9: 10016713 | D9: 022-042 | E9: FAJAS SUELTAS Y REPARAR GUARDA DE POLEA DE MOTOR | F9: Mantto Mecánico | G9: 1 | H9: C | J9: P | K9: Parada
B10: 22/11/2025 | C10: 10016714 | D10: 021-134 | E10: REVISION DE ZERO SWITCH | F10: Mantto Electrico | G10: 1 | H10: C
B11: 24/11/2025 | D11: 021-057 | E11: CAMBIO DE LIMPIAFAJA | F11: Mantto Mecánico | G11: 1 | H11: B
B12: 25/11/2025 | D12: 021-036 | E12: CAMBIO DE MANGUERA DEL ZERO | F12: Mantto Electrico | G12: 1 | H12: C
B13: 45942 | D13: 021-031 | E13: MODIFICACION DE PORTAMANDILES | F13: Mantto Mecánico | G13: 1 | H13: C | J13: Estado
B14: 45942 | D14: 021-033 | E14: MODIFICACION DE PORTAMANDILES | F14: Mantto Mecánico | G14: 1 | H14: C | J14: 1 | K14: Oculta el trabajo
B15: 45942 | D15: 021-055 | E15: MODIFICACION DE PORTAMANDILES | F15: Mantto Mecánico | G15: 1 | H15: C
B16: 45942 | D16: 021-057 | E16: MODIFICACION DE PORTAMANDILES | F16: Mantto Mecánico | G16: 1 | H16: C
B17: 45942 | D17: 020-110 | E17: CAMBIO DE LINNER | F17: Mantto Mecánico | G17: 1 | H17: C
B18: 46003 | D18: 021-132 | E18: CAMBIO DE MANDIL | F18: Mantto Mecánico | G18: 1 | H18: B
B19: 17/12/2025 | D19: 022-021 | E19: REPARACION DE TUBERIA POR FUGA DE ACEITE | F19: Mantto Mecánico | G19: 1 | H19: C
B20: 22/12/2025 | D20: 022-128 | E20: HERMETIZACION TAPA HACIA 021-132 | F20: Mantto Mecánico | G20: 1 | H20: B
B21: 23/12/2025 | D21: 022-042 | E21: REPOSICION DE 2 POSTES DE FIJACION | F21: Mantto Mecánico | G21: 1 | H21: C
B22: 23/12/2025 | D22: 211-024 | E22: CAMBIO DE MALLA 3/4 | F22: Mantto Mecánico | G22: 1 | H22: C
B23: 24/12/2025 | D23: 029-070 | E23: CAMBIO DUCTO SUCCION ALTURA CHANCADORA 022-042 | F23: Mantto Mecánico | G23: 1 | H23: C
B24: 26/12/2025 | D24: 211-024 | E24: CAMBIO MALLA 3/4 | F24: Mantto Mecánico | G24: 1 | H24: C
B25: 27/12/2025 | D25: 211-051 | E25: HERMETIZACION CHUTE FINOS HACIA 021-632 | F25: Mantto Mecánico | G25: 1 | H25: B
B26: 28/12/2025 | D26: 211-140 | E26: CAMBIO MALLA SET INFERIOR | F26: Mantto Mecánico | G26: 1 | H26: C
B27: 29/12/2025 | C27: 10018489 | D27: 022-130 | E27: REPOSICION DE 1 POSTE DE FIJACION | F27: Mantto Mecánico | G27: 1 | H27: C
B28: 30/12/2025 | D28: 211-024 | E28: CAMBIO DE EXCENTRICA | F28: Mantto Mecánico | G28: 1 | H28: C
B29: 30/12/2025 | D29: 020-124 | E29: REPARACION DE BANDEJA DEL FEEDER POR FISURA | F29: Mantto Mecánico | G29: 1 | H29: C
B30: 46024 | D30: 211-024 | E30: REPARACION / CAMBIO MOTOR | F30: Mantto Electrico | G30: 1 | H30: C
B31: 46024 | D31: 211-050 | E31: CAMBIO DE MALLA 3/4 | F31: Mantto Mecánico | G31: 1 | H31: C
B32: 46024 | D32: 210-402 | E32: CAMBIO DE FAJA DENTADA | F32: Mantto Mecánico | G32: 1 | H32: C
B33: 46025 | D33: 275-032 | E33: CONFIGURACION DE SEÑAL DE ZARANDAS POR MTTO EN LINEA 1 | F33: Mantto Instrumentacion | G33: 1 | H33: B
B34: 46026 | D34: 211-025 | E34: CAMBIO CANTONERA | F34: Mantto Mecánico | G34: 1 | H34: B
B35: 46027 | D35: 021-616 | E35: REPARACION DE COMPUERTA DE TOLVA DE GRANZA, CAMBIO DE BOMBA HIDRAULICA | F35: Mantto Mecánico | G35: 1 | H35: C
B36: 46028 | D36: 021-066 | E36: REGULACION DE FRENO DE TRIPPER | F36: Mantto Electrico | G36: 1 | H36: C
B37: 46029 | D37: 211-018 | E37: CAMBIO DE EXCENTRICA | F37: Mantto Mecánico | G37: 1 | H37: C
B38: 46029 | D38: 021-510 a 021-625 | E38: CAMBIO DE CHUTE | F38: Mantto Mecánico | G38: 1 | H38: C
B39: 46029 | D39: tolva a separadores 210-400/401/402 | E39: CAMBIO DE CHUTES | F39: Mantto Mecánico | G39: 1 | H39: C
B40: 46030 | D40: 211-050 | E40: CAMBIO EXCENTRICA | F40: Mantto Mecánico | G40: 1 | H40: P
B41: 46030 | D41: 021-134 A 021-061 | E41: CAMBIO PLATINAS | F41: Mantto Mecánico | G41: 1 | H41: C
... B63: 46051 | D63: 021-059 | E63: REGULACION DE MANDILES | F63: Mantto Mecánico | G63: 1 | H63: B
B64: 30/1/2026 | D64: 211-049 | E64: CAMBIO DE TAPAS | F64: Mantto Mecánico | G64: 1 | H64: B
B65: 46055 | D65: 021-632 | E65: INSTALACION DE PORTAMANDILES | F65: Mantto Mecánico | G65: 1 | H65: B
B66: 46056 | D66: 021-631 | E66: INSTALACION DE PLANCHA POLIURETANO EN CHUTE DE FINOS | F66: Mantto Mecánico | G66: 1 | H66: B
B67: 46057 | D67: 021-037 | E67: INSTALACION DE COBERTURA | F67: Mantto Mecánico | G67: 1 | H67: B
B68: 46059 | D68: 021-061 | E68: BAJAR MANDILES | F68: Mantto Mecánico | G68: 1 | H68: B
B69: 46060 | D69: 211-127 | E69: CAMBIO DE FAJAS EN V | F69: Mantto Mecánico | G69: 1 | H69: B
B70: 46063 | D70: 021-045 | E70: MODIFICACION DE BASE AUTOLINEANTE | F70: Mantto Mecánico | G70: 1 | H70: B
B71: 46072 | D71: 029-070 | E71: CAMBIO DE RADIADOR | F71: Mantto Mecánico | G71: 1 | H71: C
B72: 46078 | D72: 021-045 | E72: INSTALACION DE MANDIL | F72: Mantto Mecánico | G72: 1 | H72: B
B73: 46083 | D73: 021-063 | E73: BAJAR MANDILES | F73: Mantto Mecánico | G73: 1 | H73: B
B74: 46084 | D74: 021-033 | E74: BAJAR MANDILES | F74: Mantto Mecánico | G74: 1 | H74: B
B75: 46085 | D75: 021-012 | E75: INSTALACION DE PORTAMANDILES Y MANDILES | F75: Mantto Mecánico | G75: 1 | H75: B
B76: 46087 | D76: 021-040 | E76: CAMBIO SEGMENTO DE LIMPIADOR SECUNDARIO | F76: Mantto Mecánico | G76: 1 | H76: B
... B82: 46151 | D82: 211-124 | E82: REPARACION DE PARRILA | F82: Mantto Mecánico | G82: 1 | H82: B

Sheet RTM-MAGNETICA
B3: REPORTE DE TRABAJOS DE MANTENIMIENTO
B5: Fecha de reporte | C5: Aviso SAP | D5: Equipo | E5: Descripción | F5: Area Ejec. | G5: Estado | H5: Criticidad | J5: Criticidad
B6: 15/11/2025 | C6: 10016654 | D6: 031-061 | E6: ALINEAR POLEA DE COLA | F6: Manto. Mecánico | H6: C | J6: A | K6: Baja
B7: 45972 | C7: 10016657 | D7: 213-231 | E7: BOMBEO DEFICIENTE | F7: Manto. Mecánico | H7: C | J7: B | K7: Media
B8: 45940 | C8: 10016658 | D8: 213-822 | E8: REPONER BOMBA DE ST-BY | F8: Manto. Mecánico | H8: C | J8: C | K8: Alta
B9: 19/11/2025 | C9: 10016689 | D9: 210-107/108 | E9: CAMBIO DE VALVULA DE LINEA PRINCIPAL | F9: Manto. Mecánico | H9: B | J9: P | K9: Parada
B10: 45971 | C10: 10016691 | D10: 213-221 | E10: ALINEAR MANGUERA DE DESCARGA | F10: Manto. Mecánico | H10: C
B11: 45969 | C11: 60006775 | D11: 210-279 | E11: REPONER TAMBORES MAGNETICOS | F11: Manto. Mecánico | G11: Equipo Parado | H11: C
B12: 45901 | D12: 210-279 | E12: ALINEAR MANGUERA DESCARGA 213.211 | F12: Manto. Mecánico | H12: C
B13: 15/11/2025 | D13: 210-114/115 | E13: INSTALAR CODO EN MANGUERA DE COLAS HACIA CANAL | F13: Manto. Mecánico | H13: B | J13: Estado
B14: 15/11/2025 | D14: 032-084/085/086 | E14: INSTALAR TINA EN REBOSE LADO ALIMENTACION | F14: Manto. Mecánico | H14: C | J14: 1 | K14: Oculta el trabajo
B15: 45839 | D15: 032-081 | E15: DESATORAR MANGUERA DE DESCARGA/HABILITAR MALLA DESCARGA HACIA SUMIDERO | F15: Manto. Mecánico | H15: C
B16: 20/11/2025 | D16: 213-817 | E16: CAMBIAR MANGUERA DESCARGA CON HUECO | F16: Manto. Mecánico | H16: C
B17: 20/11/2025 | D17: 032-209 | E17: PIERDE CARGA POR RETEN ALIMENTACIÓN | F17: Manto. Mecánico | G17: Observado | H17: C
B18: 20/11/2025 | D18: 213-818 | E18: REPARAR TAPA DESCARGA SUMIDERO | F18: Manto. Mecánico | H18: B
B19: 20/11/2025 | D19: 213-312 | E19: CAMBIAR VCN | F19: Manto. Mecánico | H19: C
B20: 20/11/2025 | D20: 213-105 | E20: CAMBIAR JEBE DE SELLO | F20: Manto. Mecánico | H20: C
B21: 20/11/2025 | D21: 210-270 | E21: COLOCAR BRAZO REGULADOR | F21: Manto. Mecánico | G21: OPERATIVO | H21: C
B22: 20/11/2025 | D22: 213-213 | E22: CAMBIAR JEBE DE SELLO | F22: Manto. Mecánico | H22: C
B23: 20/11/2025 | D23: 039-272 | E23: REPARA CODO DE PVC 2" DE REACTIVOS DEBAJO DE TANQUE | F23: Manto. Mecánico | H23: B
B24: 20/11/2025 | D24: 039-282 | E24: CAMBIAR VÁLVULA DE 2" REACTIVO | F24: Manto. Mecánico | H24: B
B25: 20/11/2025 | D25: 210-278 | E25: REPONER TINA Y TAMBORES | F25: Manto. Mecánico | G25: 1 | H25: C
B26: 45982 | D26: 213-123 | E26: BOMBEO DEFICIENTE, CAMBIO DE COMPONENTES HUMEDOS | F26: Manto. Mecánico | H26: C
B27: 45982 | D27: 210-311 | E27: REPONER MOTOR EN TAMBOR B | F27: Manto. Mecánico | G27: OPERATIVO (21/11 18:00HR)
B28: 45982 | C28: 10016844 | D28: 039-280 B | E28: CAMBIO DE RODAMIETO POR EXCESIVA VIBRACION | F28: Manto. Mecánico
B29: 22/11/2025 | D29: 039-274/275 | E29: HABILITAR VENTANAS PARA MUESTREO | F29: Manto. Mecánico | G29: OPERATIVO
B30: 22/11/2025 | D30: 213-233 | E30: CAMBIAR FAJAS EN V | F30: Manto. Mecánico
B31: 22/11/2025 | C31: 60006773 | D31: 210-319 | E31: MANTENIMIENTO GENERAL | F31: Manto. Mecánico
B32: 24/11/2025 | D32: 039-290 | E32: CAMBIAR FILTRO DEL SOPLADOR | F32: Manto. Mecánico
B33: 24/11/2025 | D33: 213-804/805 | E33: CAMBIAR Ye EN DESCARGA | F33: Manto. Mecánico
B34: 25/11/2025 | D34: 039-281 | E34: CAMBIAR CILINDRO LADO DESCARGA | F34: Manto. Mecánico
D35: 039-237 | E35: REPONER CADENA DEL LANZADOR DE BARRAS | F35: Manto. Mecánico
C36: 20005542 | D36: LINEA 4 | E36: REVISAR TOMA DE 440v | F36: Manto. Mecánico
B37: 26/11/2025 | C37: 20005539 | D37: 032-206 | E37: CAMBIO DE MANGUERA DE ALIMENTACION | F37: Manto. Mecánico
C38: 20005540 | D38: 039-289 | E38: REVISAR POSICIONADOR AUTOMATICO | F38: Manto. Mecánico
C39: 20005541 | D39: 032-202 | E39: REPARAR CADENA DEL TOLVIN DE AGREGADOS | F39: Manto. Mecánico
C40: 60006828 | D40: 210-270 | E40: CAMBIO DE CODO DE DESCARGA HACIA SUMIDERO 213-808/809 | F40: Manto. Mecánico
B41: 27/11/2025 | E41: RETIRO DE TAPA DE INSPECION DEL TANQUE #1 (PLANTA OXALICO) | F41: Manto. Mecánico
E42: ALINEAR POLEA DE COLAS 031-066 | F42: Manto. Mecánico
B43: 45992 | C43: 20005587 | D43: 213-478 | E43: CAMBIO DE TRAMO MANGUERA DE 12PLG . PERFORADA ALTURA DE PLANTA FILTROS | F43: Manto. Mecánico
C44: 20005588 | D44: 213-478 | E44: MANTENIMIENTO POR BOMBEO DEFICIENTE | F44: Manto. Mecánico
C45: 20005589 | D45: 032-083 | E45: AJUSTAR PERNOS DE SHELL | F45: Manto. Mecánico
C46: 10017106 | D46: 210-295 | E46: LIMPIEZA DE TAMBOR A | F46: Manto. Mecánico
C47: 10017108 | D47: 210-105 | E47: PARCHAR CANALETA DE CONCENTRADO | F47: Manto. Mecánico
C48: 20005598 | D48: 210-099 | E48: REPARAR CAJON ALIMENTACION | F48: Manto. Mecánico
D49: 213-688 | E49: REPARAR FUGA DE ACIDO | F49: Manto. Mecánico
B50: 45993 | C50: 10017220 | D50: 213-800 | E50: DESMONTAR MANGUERA DE DESCARGA PARA REALIZAR LIMPIEZA | F50: Manto. Mecánico | G50: EQUIPO PARADO | H50: P
C51: 20005608 | D51: 302-081 | E51: AJUSTAR PERNOS DEL SHELL | F51: Manto. Mecánico | G51: EQUIPO PARADO | H51: P
C52: 20005610 | D52: 213-811 | E52: REALIZAR MANTENIMIENTO BOMBA DE PULPA | F52: Manto. Mecánico | G52: EQUIPO PARADO | H52: P
C53: 20005609 | D53: 210-106 | E53: MANTENIMIENTO GENERAL | F53: Manto. Mecánico | G53: EQUIPO PARADO | H53: P
C54: 10017235 | D54: 210-317 | E54: REVISAR TINA DE CONCENTRADO POR PERDIDA DE FeO POR LAS COLAS | F54: Manto. Mecánico | G54: EQUIPO PARADO | H54: P
C55: 10017312 | D55: 213-813 | E55: REALIZAR MANTENIMIENTO BOMBA DE PULPA | F55: Manto. Mecánico | G55: EQUIPO PARADO | H55: P
B56: 45994 | C56: 20005685 | D56: 039-281 | E56: CAMBIAR EJE ROTO DEL AGITADOR Y REPONER MOTOREDUCTOR | F56: Manto. Mecánico | G56: EQUIPO PARADO | H56: P
C57: 20005686 | D57: 032-089 | E57: CAMBIAR Y AJUSTAR PERNOS EN TAPA DE DESCARGA | F57: Manto. Mecánico | G57: EQUIPO PARADO | H57: P
C58: 10017563 | D58: 213-682 | E58: CAMBIAR JEBE DE SELLO | F58: Manto. Mecánico | G58: EQUIPO PARADO | H58: P
C59: 20005687 | D59: 039-274 | E59: RETIRAR TUBO DAMPING PARA LIMPIEZA | F59: Manto. Mecánico | G59: EQUIPO PARADO | H59: P
B60: 45995 | C60: 20005690 | D60: 213-478 | E60: CAMBIAR TRAMO DE MANGUERA DE DESCARAG DE 213-478 | F60: Manto. Mecánico | G60: EQUIPO PARADO | H60: P
C61: 10017564 | D61: 213-111 | E61: REUBICAR MANGUERA DE DESCARGA DE 213-111 | F61: Manto. Mecánico | G61: EQUIPO PARADO | H61: P
C62: 10017565 | D62: 210-285 | E62: Limpieza de manguera de alimentación. | F62: Manto. Mecánico | G62: EQUIPO PARADO | H62: P
B63: 45996 | D63: 039-275 | E63: HERMETIZAR CAJON DE DESCARGA | F63: Manto. Mecánico | G63: EQUIPO PARADO | H63: P
D64: 213-478 | E64: EMBONAR MANGUERA DE DESCARGA | F64: Manto. Mecánico | G64: EQUIPO PARADO | H64: P
D65: 032-081 | E65: AJUSTAR PERNOS EN SHELL | F65: Manto. Mecánico | G65: EQUIPO PARADO | H65: P
B66: 45997 | D66: 210-269 | E66: MANTENIMIENTO GENERAL | F66: Manto. Mecánico | G66: EQUIPO PARADO | H66: P
D67: 213-817 | E67: MANTENIMIENTO DE BOMBA DE PULPA 213-113 | F67: Manto. Mecánico | G67: EQUIPO PARADO | H67: P
D68: 039-274 | E68: REPARAR PALETAS | F68: Manto. Mecánico | G68: EQUIPO PARADO | H68: P
B69: 46001 | C69: 20005699 | D69: 213-113 | E69: MANTENIMIENTO DE BOMBA DE PULPA 213-113 | F69: Manto. Mecánico | G69: EQUIPO PARADO | H69: P
C70: 20005692 | D70: 039-288 | E70: CAMBIAR PISTON LADO DESCARGA DE 039-288 | F70: Manto. Mecánico | G70: EQUIPO PARADO | H70: P
C71: 20005693 | D71: 039-289 | E71: CAMBIAR BASTAGO Y PLANCHA DE DESCARGA | F71: Manto. Mecánico | G71: EQUIPO PARADO | H71: P
B72: 46002 | D72: 213-214 | E72: REVISAR BOMBA POR PERDIDA DE ACEITE POR RETEN | F72: Manto. Mecánico | G72: EQUIPO PARADO | H72: P
D73: 032-088 | E73: REPONER PERNO EN TORMELL | F73: Manto. Mecánico | G73: EQUIPO PARADO | H73: P
D74: 031-062 | E74: CAMBIAR PLANCHA DE IMPACTO | F74: Manto. Mecánico | G74: EQUIPO PARADO | H74: P
B75: 46003 | D75: 210-279 B | E75: CAMBIAR TAMBOR CON REVESTIMIENTO DE JEBE | F75: Manto. Mecánico | G75: EQUIPO PARADO | H75: P
D76: 039-270/271 | E76: REVISAR SISTEMA AUTOMATICO DE LA CELDA | F76: Manto. Mecánico | G76: EQUIPO PARADO | H76: P
D77: 213-231 | E77: MANTENIMIENTO GENERAL | F77: Manto. Mecánico | G77: EQUIPO PARADO
B78: 46004
B81: 46006 | D81: 213-813 | E81: cambio de fajas en V | F81: Manto. Mecánico | G81: EQUIPO PARADO | H81: P
D82: 213-108/404 | E82: REPARAR LINEA DE AGUA DE SELLO | F82: Manto. Mecánico | G82: EQUIPO PARADO | H82: P
D83: 213-480 | E83: CAMBIO JEBE DE SELLO | F83: Manto. Mecánico | G83: EQUIPO PARADO | H83: P
D84: 213-312 | E84: CAMBIO DE VALVULA DE CUCHILLA | F84: Manto. Mecánico | G84: EQUIPO PARADO | H84: P
B85: 46007 | D85: 210-099 | E85: ALINEAR MANGUERA DESCARGA-CONCENTRADO | F85: Manto. Mecánico | G85: EQUIPO PARADO | H85: P
